Workbook

Sheet CARE SHEET
A1: Age Band | B1: Age From | C1: Age To | D1: Sum Insured | E1: Cover Type | F1: No. of Members | G1: No. of Adults | H1: No. of Children | I1: Term | J1: zone | K1: COMBINATIO | L1: ROW NO | M1: COLUMN NO | N1: APPLICABLE ARRAY | S1: =VLOOKUP('CALCULATOR CARE V6'!F2,DROPDOWN!K:L,2,0) -> 18-24 | T1: =IF(R4="1+0",V5,V4) -> 4 | U1: RED IN PED | X1: 1A | AA1: Zone 1 | AX1: ZONE- 1A | BU1: ZONE 2 | CO1: ZONE 3
A2: 00-04 | B2: 0 years | C2: 4 years | D2: 5 | E2: INDIVIDUAL | F2: 1 | H2: 1 | I2: 1 | J2: Zone 1 | K2: =G2&"+"&H2 -> +1 | L2: =VLOOKUP(A2,'ZONE 1 PREMIUM'!$A$3:$M$16,13,0) -> 2 | M2: =VLOOKUP(D2,DROPDOWN!B:C,2,0) -> 4 | N2: =VLOOKUP(K2,$AQ$3:$AR$12,2,0) -> #N/A | O2: 3298.4569 | S2: =VLOOKUP('CALCULATOR CARE V6'!E2,DROPDOWN!K:L,2,0) -> 18-24 | T2: =IF(R4="1+0",U5,U4) -> 4 | U2: =VLOOKUP(S2,DROPDOWN!L20:M110,2,0) -> Upto 45 Years | Y2: Care 3 | AA2: Care 4 | AD2: Care 5 | AI2: Care 6 | AL2: Care 7 | AQ2: ARRAY | AT2: 1A | AV2: Care 3 | AX2: Care 4 | BA2: Care 5 | BF2: Care 6 | BI2: Care 7 | BN2: ARRAY | BQ2: 1A | BS2: Care 3 | BU2: Care 4 | BX2: Care 5 | CC2: Care 6 | CF2: Care 7 | CK2: ARRAY | CN2: 1A | CP2: Care 3 | CR2: Care 4 | CU2: Care 5 | CZ2: Care 6 | DC2: Care 7
A3: 05-17 | B3: 5 years | C3: 17 years | D3: 5 | E3: INDIVIDUAL | F3: 1 | G3: 1 | H3: 0 | I3: 1 | J3: Zone 1 | K3: 1+0 | L3: =VLOOKUP(A3,'ZONE 1 PREMIUM'!$A$3:$M$16,13,0) -> 3 | M3: =VLOOKUP(D3,DROPDOWN!B:C,2,0) -> 4 | N3: =VLOOKUP(K3,$AQ$3:$AR$12,2,0) -> X3:AP16 | O3: =INDEX(INDIRECT(N3),L3,M3) -> 5817.85 | S3: =VLOOKUP('CALCULATOR CARE V6'!B2,DROPDOWN!K:L,2,0) -> 18-24 | T3: =VLOOKUP('CALCULATOR CARE V6'!B6,DROPDOWN!A2:B19,2,0) -> 600 | U3: =VLOOKUP(S1,DROPDOWN!L20:M110,2,0) -> Upto 45 Years | X3: Age-Band/ SI | Y3: 3L | Z3: 4L | AA3: 5L | AB3: 7L | AC3: 10L | AD3: 15L | AE3: 20L | AF3: 25L | AG3: 30L | AH3: 40L | AI3: 50L | AJ3: 60L | AK3: 75L | AL3: 1 CR | AM3: 1.5 CR | AN3: 2 CR | AO3: 3 CR | AP3: 6 CR | AQ3: 1+0 | AR3: X3:AP16 | AU3: Age-Band/ SI | AV3: 3L | AW3: 4L | AX3: 5L | AY3: 7L | AZ3: 10L | BA3: 15L | BB3: 20L | BC3: 25L | BD3: 30L | BE3: 40L | BF3: 50L | BG3: 60L | BH3: 75L | BI3: 1 CR | BJ3: 1.5 CR | BK3: 2 CR | BL3: 3 CR | BM3: 6 CR | BN3: 1+0 | BO3: AU3:BM16 | BR3: Age-Band/ SI | BS3: 3L | BT3: 4L | BU3: 5L | BV3: 7L | BW3: 10L | BX3: 15L | BY3: 20L | BZ3: 25L | CA3: 30L | CB3: 40L | CC3: 50L | CD3: 60L | CE3: 75L | CF3: 1 CR | CG3: 1.5 CR | CH3: 2 CR | CI3: 3 CR | CJ3: 6 CR | CK3: 1+0 | CL3: BR3:CJ16 | CO3: Age-Band/ SI | CP3: 3L | CQ3: 4L | CR3: 5L | CS3: 7L | CT3: 10L | CU3: 15L | CV3: 20L | CW3: 25L | CX3: 30L | CY3: 40L | CZ3: 50L | DA3: 60L | DB3: 75L | DC3: 1 CR | DD3: 1.5 CR | DE3: 2 CR | DF3: 3 CR | DG3: 6 CR | DH3: ARRAY
A4: 18-24 | B4: 18 Years | C4: 24 Years | D4: 5 | E4: INDIVIDUAL | F4: 1 | G4: 1 | H4: 0 | I4: 1 | J4: Zone 1 | K4: =G4&"+"&H4 -> 1+0 | L4: =VLOOKUP(A4,'ZONE 1 PREMIUM'!$A$3:$M$16,13,0) -> 4 | M4: =VLOOKUP(D4,DROPDOWN!B:C,2,0) -> 4 | N4: =VLOOKUP(K4,$AQ$3:$AR$12,2,0) -> X3:AP16 | O4: =INDEX(INDIRECT(N4),L4,M4) -> 15584.8 | Q4: COMBINATIO | R4: ='CALCULATOR CARE V6'!B3&"+"&'CALCULATOR CARE V6'!B4 -> 1+0 | U4: =VLOOKUP(S2,DROPDOWN!O15:Q27,3,0) -> 2 | V4: =VLOOKUP(S1,DROPDOWN!O15:Q27,3,0) -> 2 | X4: 00-04 | Y4: 5413.05 | Z4: 6458.4 | AA4: 7586.55 | AB4: 8270.8 | AC4: 8898.7 | AD4: 10383.35 | AE4: 11302.2 | AF4: 12080.75 | AG4: 13475.7 | AH4: 16733.65 | AI4: 25731.25 | AJ4: 32788.8 | AK4: 40684.7 | AL4: 64608.15 | AM4: 76854.5 | AN4: 90276.15 | AO4: 105751.7 | AP4: 141420.1 | AQ4: 1+1 | AR4: X20:AP31 | AU4: 00-04 | AV4: 4806 | AW4: 5733 | AX4: 6730.875 | AY4: 7337.25 | AZ4: 7893 | BA4: 9208.125 | BB4: 10021.5 | BC4: 10711.125 | BD4: 11946.375 | BE4: 14832 | BF4: 22799.25 | BG4: 29048.625 | BH4: 36040.5 | BI4: 58054.5 | BJ4: 68899.5 | BK4: 80784 | BL4: 94488.75 | BM4: 126074.25 | BN4: 1+1 | BO4: AU20:BM31 | BR4: 00-04 | BS4: 4436.3 | BT4: 5289.9 | BU4: 6209.5 | BV4: 6768.3 | BW4: 7280.9 | BX4: 8492 | BY4: 9242.2 | BZ4: 9876.9 | CA4: 11015.4 | CB4: 13674.1 | CC4: 21016.6 | CD4: 26775.1 | CE4: 33218.9 | CF4: 53941.8 | CG4: 63935.3 | CH4: 74886.9 | CI4: 87516 | CJ4: 116623.1 | CK4: 1+1 | CL4: BR20:CJ31 | CO4: 00-04 | CP4: 4086.41 | CQ4: 4871.21 | CR4: 5717.05 | CS4: 6230.44 | CT4: 6701.32 | CU4: 7815.3 | CV4: 8505.27 | CW4: 9089.51 | CX4: 10135.91 | CY4: 12580.78 | CZ4: 19332.24 | DA4: 24627.46 | DB4: 30552.7 | DC4: 50049.53 | DD4: 59239.32 | DE4: 69308.74 | DF4: 80921.6 | DG4: 107686.55 | DH4: 1+0 | DI4: CO3:DG16
A5: 25-35 | B5: 25 Years | C5: 35 Years | D5: 5 | E5: INDIVIDUAL | F5: 1 | G5: 1 | H5: 0 | I5: 1 | J5: Zone 1 | K5: =G5&"+"&H5 -> 1+0 | L5: =VLOOKUP(A5,'ZONE 1 PREMIUM'!$A$3:$M$16,13,0) -> 5 | M5: =VLOOKUP(D5,DROPDOWN!B:C,2,0) -> 4 | N5: =VLOOKUP(K5,$AQ$3:$AR$12,2,0) -> X3:AP16 | O5: =INDEX(INDIRECT(N5),L5,M5) -> 17919.3 | Q5: ROW NO | R5: =IF(R4="1+0",S5,T5) -> 4 | S5: =VLOOKUP(S3,DROPDOWN!O15:Q27,2,0) -> 4 | T5: =VLOOKUP(S3,DROPDOWN!O15:Q27,3,0) -> 2 | U5: =VLOOKUP(S2,DROPDOWN!O15:Q27,2,0) -> 4 | V5: =VLOOKUP(S1,DROPDOWN!O15:Q27,2,0) -> 4 | X5: 05-17 | Y5: 4068.7 | Z5: 4867.95 | AA5: 5817.85 | AB5: 6346.85 | AC5: 6833.3 | AD5: 7974.1 | AE5: 8687.1 | AF5: 9294.3 | AG5: 10374.15 | AH5: 12886.9 | AI5: 21072.6 | AJ5: 26569.6 | AK5: 32718.65 | AL5: 43824.2 | AM5: 53201.3 | AN5: 63567.4 | AO5: 75578 | AP5: 103210.2 | AQ5: 1+2 | AR5: X35:AP46 | AU5: 05-17 | AV5: 3615.75 | AW5: 4324.5 | AX5: 5164.875 | AY5: 5632.875 | AZ5: 6063.75 | BA5: 7075.125 | BB5: 7705.125 | BC5: 8242.875 | BD5: 9199.125 | BE5: 11424.375 | BF5: 18673.875 | BG5: 23540.625 | BH5: 28986.75 | BI5: 39103.875 | BJ5: 47407.5 | BK5: 56586.375 | BL5: 67222.125 | BM5: 91692 | BN5: 1+2 | BO5: AU35:BM46 | BR5: 05-17 | BS5: 3339.6 | BT5: 3991.9 | BU5: 4766.3 | BV5: 5197.5 | BW5: 5594.6 | BX5: 6526.3 | BY5: 7108.2 | BZ5: 7603.2 | CA5: 8484.3 | CB5: 10534.7 | CC5: 17215 | CD5: 21700.8 | CE5: 26717.9 | CF5: 36191.1 | CG5: 43842.7 | CH5: 52301.7 | CI5: 62102.7 | CJ5: 84652.7 | CK5: 1+2 | CL5: BR35:CJ46 | CO5: 05-17 | CP5: 3077.07 | CQ5: 3677.66 | CR5: 4389.43 | CS5: 4786.19 | CT5: 5151.34 | CU5: 6008.08 | CV5: 6542.18 | CW5: 6997.8 | CX5: 7808.76 | CY5: 9694.46 | CZ5: 15836.61 | DA5: 19961.17 | DB5: 24575.14 | DC5: 33436.84 | DD5: 40472.79 | DE5: 48251.03 | DF5: 57263.15 | DG5: 77997.13 | DH5: 1+1 | DI5: CO20:DG31
A6: 36-40 | B6: 36 Years | C6: 40 Years | D6: 5 | E6: INDIVIDUAL | F6: 1 | G6: 1 | H6: 0 | I6: 1 | J6: Zone 1 | K6: =G6&"+"&H6 -> 1+0 | L6: =VLOOKUP(A6,'ZONE 1 PREMIUM'!$A$3:$M$16,13,0) -> 6 | M6: =VLOOKUP(D6,DROPDOWN!B:C,2,0) -> 4 | N6: =VLOOKUP(K6,$AQ$3:$AR$12,2,0) -> X3:AP16 | O6: =INDEX(INDIRECT(N6),L6,M6) -> 20648.25 | Q6: COLUMN NO | R6: =VLOOKUP('CALCULATOR CARE V6'!B6,DROPDOWN!A:C,3,0) -> 19 | X6: 18-24 | Y6: 10297.1 | Z6: 12675.3 | AA6: 15584.8 | AB6: 17001.6 | AC6: 18303.4 | AD6: 21542.95 | AE6: 23710.7 | AF6: 25618.55 | AG6: 28574.05 | AH6: 35452.2 | AI6: 74110.6 | AJ6: 88767.35 | AK6: 105253.75 | AL6: 146358.2 | AM6: 173886.9 | AN6: 204381.45 | AO6: 239773.85 | AP6: 321052.4 | AQ6: 1+3 | AR6: X50:AP61 | AU6: 18-24 | AV6: 9137.25 | AW6: 11242.125 | AX6: 13834.125 | AY6: 15088.5 | AZ6: 16240.5 | BA6: 19123.875 | BB6: 21044.25 | BC6: 22734 | BD6: 25349.625 | BE6: 31440.375 | BF6: 65674.125 | BG6: 78654.375 | BH6: 93253.5 | BI6: 129713.62 | BJ6: 154091.25 | BK6: 181095.75 | BL6: 212436 | BM6: 284410.12 | BN6: 1+3 | BO6: AU50:BM61 | BR6: 18-24 | BS6: 8429.3 | BT6: 10369.7 | BU6: 12765.5 | BV6: 13921.6 | BW6: 14983.1 | BX6: 17648.4 | BY6: 19417.2 | BZ6: 20974.8 | CA6: 23386 | CB6: 28998.2 | CC6: 60545.1 | CD6: 72505.4 | CE6: 85959.5 | CF6: 119590.9 | CG6: 142055.1 | CH6: 166940.4 | CI6: 195820.9 | CJ6: 262146.5 | CK6: 1+3 | CL6: BR50:CJ61 | CO6: 18-24 | CP6: 7760.8 | CQ6: 9545.13 | CR6: 11755.65 | CS6: 12818.4 | CT6: 13795.04 | CU6: 16252.99 | CV6: 17880.36 | CW6: 19311.53 | CX6: 21528.59 | CY6: 26689.74 | CZ6: 55697.91 | DA6: 66696.01 | DB6: 79066.42 | DC6: 110024.6 | DD6: 130681.19 | DE6: 153563.56 | DF6: 180120.32 | DG6: 241109.09 | DH6: 1+2 | DI6: CO35:DG46
A7: 41-45 | B7: 41 Years | C7: 45 Years | D7: 5 | E7: INDIVIDUAL | F7: 1 | G7: 1 | H7: 0 | I7: 1 | J7: Zone 1 | K7: =G7&"+"&H7 -> 1+0 | L7: =VLOOKUP(A7,'ZONE 1 PREMIUM'!$A$3:$M$16,13,0) -> 7 | M7: =VLOOKUP(D7,DROPDOWN!B:C,2,0) -> 4 | N7: =VLOOKUP(K7,$AQ$3:$AR$12,2,0) -> X3:AP16 | O7: =INDEX(INDIRECT(N7),L7,M7) -> 23997.05 | Q7: APPLICABLE ARRAY | R7: =HLOOKUP(R8,S7:V8,2,0) -> CO3:DG16 | S7: ZONE 1 | T7: ZONE 1A | U7: ZONE 2 | V7: ZONE 3 | X7: 25-35 | Y7: 12023.25 | Z7: 14494.6 | AA7: 17919.3 | AB7: 19554.6 | AC7: 21061.1 | AD7: 24835.4 | AE7: 27181.4 | AF7: 29242.2 | AG7: 32623.2 | AH7: 40468.5 | AI7: 83744.15 | AJ7: 101433.45 | AK7: 121762 | AL7: 164939.9 | AM7: 197145.65 | AN7: 232939.4 | AO7: 274569.4 | AP7: 370004.45 | AQ7: 1+4 | AR7: X65:AP76 | AU7: 25-35 | AV7: 10672.875 | AW7: 12861 | AX7: 15914.25 | AY7: 17362.125 | AZ7: 18695.25 | BA7: 22059 | BB7: 24135.75 | BC7: 25961.625 | BD7: 28955.25 | BE7: 35902.125 | BF7: 74224.125 | BG7: 89888.625 | BH7: 107890.88 | BI7: 146211.75 | BJ7: 174730.5 | BK7: 206427.38 | BL7: 243292.5 | BM7: 327802.5 | BN7: 1+4 | BO7: AU65:BM76 | BR7: 25-35 | BS7: 9848.3 | BT7: 11865.7 | BU7: 14689.4 | BV7: 16023.7 | BW7: 17252.4 | BX7: 20363.2 | BY7: 22276.1 | BZ7: 23959.1 | CA7: 26717.9 | CB7: 33119.9 | CC7: 68434.3 | CD7: 82869.6 | CE7: 99457.6 | CF7: 134818.2 | CG7: 161098.3 | CH7: 190307.7 | CI7: 224279 | CJ7: 302156.8 | CK7: 1+4 | CL7: BR65:CJ76 | CO7: 25-35 | CP7: 9068.8 | CQ7: 10923.98 | CR7: 13531.26 | CS7: 14758.6 | CT7: 15888.93 | CU7: 18758.9 | CV7: 20519.25 | CW7: 22065.96 | CX7: 24603.48 | CY7: 30489.48 | CZ7: 62962.76 | DA7: 76235.69 | DB7: 91489.15 | DC7: 124049.63 | DD7: 148214.93 | DE7: 175073.62 | DF7: 206311.93 | DG7: 277921.66 | DH7: 1+3 | DI7: CO50:DG61
A8: 46-50 | B8: 46 Years | C8: 50 Years | D8: 5 | E8: INDIVIDUAL | F8: 1 | G8: 1 | H8: 0 | I8: 1 | J8: Zone 1 | K8: =G8&"+"&H8 -> 1+0 | L8: =VLOOKUP(A8,'ZONE 1 PREMIUM'!$A$3:$M$16,13,0) -> 8 | M8: =VLOOKUP(D8,DROPDOWN!B:C,2,0) -> 4 | N8: =VLOOKUP(K8,$AQ$3:$AR$12,2,0) -> X3:AP16 | O8: =INDEX(INDIRECT(N8),L8,M8) -> 29750.5 | Q8: ZONE | R8: ='CALCULATOR CARE V6'!B8 -> ZONE 3 | S8: =VLOOKUP(R4,AQ2:AR12,2,0) -> X3:AP16 | T8: =VLOOKUP(R4,BN3:BO12,2,0) -> AU3:BM16 | U8: =VLOOKUP(R4,CK2:CL12,2,0) -> BR3:CJ16 | V8: =VLOOKUP(R4,DH4:DI13,2,0) -> CO3:DG16 | X8: 36-40 | Y8: 13796.55 | Z8: 16666.95 | AA8: 20648.25 | AB8: 22563 | AC8: 24330.55 | AD8: 28695.95 | AE8: 31413.4 | AF8: 33800.8 | AG8: 37761.4 | AH8: 46916.55 | AI8: 87420.7 | AJ8: 108177.05 | AK8: 132074.05 | AL8: 171404.05 | AM8: 208124.7 | AN8: 249102.65 | AO8: 296882.85 | AP8: 406216.8 | AQ8: 2+0 | AR8: X81:AP92 | AU8: 36-40 | AV8: 12242.25 | AW8: 14784.75 | AX8: 18330.75 | AY8: 20026.125 | AZ8: 21592.125 | BA8: 25476.75 | BB8: 27883.125 | BC8: 29998.125 | BD8: 33504.75 | BE8: 41612.625 | BF8: 77479.875 | BG8: 95860.125 | BH8: 117021.38 | BI8: 151935.75 | BJ8: 184453.88 | BK8: 220740.75 | BL8: 263050.88 | BM8: 359870.62 | BN8: 2+0 | BO8: AU81:BM92 | BR8: 36-40 | BS8: 11294.8 | BT8: 13637.8 | BU8: 16915.8 | BV8: 18478.9 | BW8: 19921 | BX8: 23512.5 | BY8: 25730.1 | BZ8: 27678.2 | CA8: 30910 | CB8: 38381.2 | CC8: 71434 | CD8: 88371.8 | CE8: 107872.6 | CF8: 140092.7 | CG8: 170057.8 | CH8: 203496.7 | CI8: 242487.3 | CJ8: 331708.3 | CK8: 2+0 | CL8: BR81:CJ92 | CO8: 36-40 | CP8: 10399.69 | CQ8: 12553.53 | CR8: 15579.37 | CS8: 17015.99 | CT8: 18342.52 | CU8: 21655.03 | CV8: 23694.42 | CW8: 25486.38 | CX8: 28457.72 | CY8: 35327.99 | CZ8: 65720.46 | DA8: 81295.47 | DB8: 99227.06 | DC8: 128900.13 | DD8: 156454.24 | DE8: 187202.05 | DF8: 223054.33 | DG8: 305095.36 | DH8: 1+4 | DI8: CO65:DG76
A9: 51-55 | B9: 51 Years | C9: 55 Years | D9: 5 | E9: INDIVIDUAL | F9: 1 | G9: 1 | H9: 0 | I9: 1 | J9: Zone 1 | K9: =G9&"+"&H9 -> 1+0 | L9: =VLOOKUP(A9,'ZONE 1 PREMIUM'!$A$3:$M$16,13,0) -> 9 | M9: =VLOOKUP(D9,DROPDOWN!B:C,2,0) -> 4 | N9: =VLOOKUP(K9,$AQ$3:$AR$12,2,0) -> X3:AP16 | O9: =INDEX(INDIRECT(N9),L9,M9) -> 39063.2 | X9: 41-45 | Y9: 15997.65 | Z9: 19361.4 | AA9: 23997.05 | AB9: 26256.8 | AC9: 28349.8 | AD9: 33442 | AE9: 36520.55 | AF9: 39175.9 | AG9: 43826.5 | AH9: 54534.15 | AI9: 98832.15 | AJ9: 123391.55 | AK9: 151704.55 | AL9: 185825.05 | AM9: 228186.45 | AN9: 275599.8 | AO9: 330998.75 | AP9: 457535.55 | AQ9: 2+1 | AR9: X98:AP109 | AU9: 41-45 | AV9: 14191.875 | AW9: 17170.875 | AX9: 21295.125 | AY9: 23297.625 | AZ9: 25150.5 | BA9: 29680.875 | BB9: 32405.625 | BC9: 34758 | BD9: 38875.5 | BE9: 48358.125 | BF9: 87584.625 | BG9: 109333.12 | BH9: 134404.88 | BI9: 164705.62 | BJ9: 202218.75 | BK9: 244204.88 | BL9: 293262.75 | BM9: 405313.88 | BN9: 2+1 | BO9: AU98:BM109 | BR9: 41-45 | BS9: 13092.2 | BT9: 15836.7 | BU9: 19648.2 | BV9: 21492.9 | BW9: 23200.1 | BX9: 27385.6 | BY9: 29898 | BZ9: 32065 | CA9: 35858.9 | CB9: 44597.3 | CC9: 80746.6 | CD9: 100787.5 | CE9: 123890.8 | CF9: 151860.5 | CG9: 186429.1 | CH9: 225120.5 | CI9: 270327.2 | CJ9: 373585.3 | CK9: 2+1 | CL9: BR98:CJ109 | CO9: 41-45 | CP9: 12052.13 | CQ9: 14575.48 | CR9: 18091.82 | CS9: 19787.86 | CT9: 21357.46 | CU9: 25217.15 | CV9: 27526.86 | CW9: 29519.38 | CX9: 33008.47 | CY9: 41043.95 | CZ9: 74283.5 | DA9: 92712.13 | DB9: 113956.23 | DC9: 139720.56 | DD9: 171507.14 | DE9: 207084.74 | DF9: 248654.07 | DG9: 343601.79 | DH9: 2+0 | DI9: CO81:DG92
A10: 56-60 | B10: 56 Years | C10: 60 Years | D10: 5 | E10: INDIVIDUAL | F10: 1 | G10: 1 | H10: 0 | I10: 1 | J10: Zone 1 | K10: =G10&"+"&H10 -> 1+0 | L10: =VLOOKUP(A10,'ZONE 1 PREMIUM'!$A$3:$M$16,13,0) -> 10 | M10: =VLOOKUP(D10,DROPDOWN!B:C,2,0) -> 4 | N10: =VLOOKUP(K10,$AQ$3:$AR$12,2,0) -> X3:AP16 | O10: =INDEX(INDIRECT(N10),L10,M10) -> 52811.45 | Q10: BASE PREMIUM | R10: =INDEX(INDIRECT(R7),R5,R6) -> 241109.09 | S10: =INDEX(INDIRECT(R7),T2,R6) -> 241109.09 | T10: =INDEX(INDIRECT(R7),T1,R6) -> 241109.09 | X10: 46-50 | Y10: 19736.3 | Z10: 23917.7 | AA10: 29750.5 | AB10: 32584.1 | AC10: 35214.15 | AD10: 41587.45 | AE10: 45460.65 | AF10: 48817.5 | AG10: 54664.1 | AH10: 68076.55 | AI10: 119073.3 | AJ10: 150173.9 | AK10: 186076.9 | AL10: 213205.4 | AM10: 265352.15 | AN10: 323932 | AO10: 392535.25 | AP10: 548950.2 | AQ10: 2+2 | AR10: X113:AP124 | AU10: 46-50 | AV10: 17509.5 | AW10: 21213 | AX10: 26403.75 | AY10: 28913.625 | AZ10: 31242.375 | BA10: 36912.375 | BB10: 40342.5 | BC10: 43314.75 | BD10: 48492 | BE10: 60368.625 | BF10: 105527.25 | BG10: 133068.38 | BH10: 164862 | BI10: 188995.5 | BJ10: 235174.5 | BK10: 287047.12 | BL10: 347798.25 | BM10: 486308.25 | BN10: 2+2 | BO10: AU113:BM124 | BR10: 46-50 | BS10: 16152.4 | BT10: 19564.6 | BU10: 24362.8 | BV10: 26675 | BW10: 28821.1 | BX10: 34060.4 | BY10: 37220.7 | BZ10: 39960.8 | CA10: 44731.5 | CB10: 55675.4 | CC10: 97290.6 | CD10: 122669.8 | CE10: 151968.3 | CF10: 174266.4 | CG10: 216821 | CH10: 264622.6 | CI10: 320606 | CJ10: 448245.6 | CK10: 2+2 | CL10: BR113:CJ124 | CO10: 46-50 | CP10: 14869.78 | CQ10: 18007.89 | CR10: 22433.29 | CS10: 24559.88 | CT10: 26532.78 | CU10: 31364.75 | CV10: 34270.69 | CW10: 36789.68 | CX10: 41176.93 | CY10: 51240.9 | CZ10: 89506.44 | DA10: 112843.34 | DB10: 139783.78 | DC10: 160346.63 | DD10: 199476.54 | DE10: 243431.88 | DF10: 294910.4 | DG10: 412278.33 | DH10: 2+1 | DI10: CO98:DG109
A11: 61-65 | B11: 61 Years | C11: 65 Years | D11: 5 | E11: INDIVIDUAL | F11: 1 | G11: 1 | H11: 0 | I11: 1 | J11: Zone 1 | K11: =G11&"+"&H11 -> 1+0 | L11: =VLOOKUP(A11,'ZONE 1 PREMIUM'!$A$3:$M$16,13,0) -> 11 | M11: =VLOOKUP(D11,DROPDOWN!B:C,2,0) -> 4 | N11: =VLOOKUP(K11,$AQ$3:$AR$12,2,0) -> X3:AP16 | O11: =INDEX(INDIRECT(N11),L11,M11) -> 72870.9 | R11: =IF('CALCULATOR CARE V6'!B7='CARE SENIOR'!AP12,'CARE SENIOR'!AQ12,'CARE SHEET'!R10)*'CALCULATOR CARE V6'!N3 -> 186859.54 | S11: =IF('CALCULATOR CARE V6'!B2<=45,'optional benefits'!B7,'optional benefits'!B8) -> Less than or equal to 45 years | T11: =IF('CALCULATOR CARE V6'!E2<=45,'optional benefits'!B7,'optional benefits'!B8) -> Less than or equal to 45 years | U11: =IF('CALCULATOR CARE V6'!F2<=45,'optional benefits'!B7,'optional benefits'!B8) -> Less than or equal to 45 years | X11: 51-55 | Y11: 25847.4 | Z11: 31391.55 | AA11: 39063.2 | AB11: 42850.15 | AC11: 46374.9 | AD11: 54760.7 | AE11: 59958.7 | AF11: 64483.95 | AG11: 72322.35 | AH11: 90237.05 | AI11: 167150.2 | AJ11: 209187.3 | AK11: 257778.25 | AL11: 283550.9 | AM11: 353568.65 | AN11: 432395.4 | AO11: 524864.6 | AP11: 735313.45 | AQ11: 2+3 | AR11: X128:AP139 | AU11: 51-55 | AV11: 22920.75 | AW11: 27831.375 | AX11: 34650 | AY11: 38003.625 | AZ11: 41125.5 | BA11: 48577.5 | BB11: 53179.875 | BC11: 57187.125 | BD11: 64128.375 | BE11: 79993.125 | BF11: 148101.75 | BG11: 185326.88 | BH11: 228355.88 | BI11: 251309.25 | BJ11: 313311.38 | BK11: 383115.38 | BL11: 464999.62 | BM11: 651358.12 | BN11: 2+3 | BO11: AU128:BM139 | BR11: 51-55 | BS11: 21139.8 | BT11: 25664.1 | BU11: 31961.6 | BV11: 35051.5 | BW11: 37928 | BX11: 44809.6 | BY11: 49051.2 | BZ11: 52743.9 | CA11: 59140.4 | CB11: 73759.4 | CC11: 136523.2 | CD11: 170826.7 | CE11: 210478.4 | CF11: 231699.6 | CG11: 288836.9 | CH11: 353161.6 | CI11: 428620.5 | CJ11: 600352.5 | CK11: 2+3 | CL11: BR128:CJ139 | CO11: 51-55 | CP11: 19455.41 | CQ11: 23615.94 | CR11: 29421.28 | CS11: 32262.91 | CT11: 34907.25 | CU11: 41248.87 | CV11: 45148.89 | CW11: 48545.33 | CX11: 54425.88 | CY11: 67868.85 | CZ11: 125582.17 | DA11: 157124.59 | DB11: 193586.18 | DC11: 213169.12 | DD11: 265707.12 | DE11: 324855.97 | DF11: 394242.1 | DG11: 552154.76 | DH11: 2+2 | DI11: CO113:DG124
A12: 66-70 | B12: 66 Years | C12: 70 Years | D12: 5 | E12: INDIVIDUAL | F12: 1 | G12: 1 | H12: 0 | I12: 1 | J12: Zone 1 | K12: =G12&"+"&H12 -> 1+0 | L12: =VLOOKUP(A12,'ZONE 1 PREMIUM'!$A$3:$M$16,13,0) -> 12 | M12: =VLOOKUP(D12,DROPDOWN!B:C,2,0) -> 4 | N12: =VLOOKUP(K12,$AQ$3:$AR$12,2,0) -> X3:AP16 | O12: =INDEX(INDIRECT(N12),L12,M12) -> 92842.95 | Q12: Ncb-super | R12: =INDEX('optional benefits'!C7:P8,MATCH('CARE SHEET'!S11,'optional benefits'!B7:B8,0),MATCH('CALCULATOR CARE V6'!B6,'optional benefits'!C6:P6,0)) -> #N/A | S12: =IF('CALCULATOR CARE V6'!B12="YES",1+'CARE SHEET'!R12,1) -> 1 | T12: =IF('CALCULATOR CARE V6'!B12="YES",1+INDEX('optional benefits'!C7:P8,MATCH('CARE SHEET'!T11,'optional benefits'!B7:B8,0),MATCH('CALCULATOR CARE V6'!B6,'optional benefits'!C6:P6,0)),1) -> 1 | U12: =IF('CALCULATOR CARE V6'!B12="YES",1+INDEX('optional benefits'!C7:P8,MATCH('CARE SHEET'!U11,'optional benefits'!B7:B8,0),MATCH('CALCULATOR CARE V6'!B6,'optional benefits'!C6:P6,0)),1) -> 1 | X12: 56-60 | Y12: 34827.75 | Z12: 42355.65 | AA12: 52811.45 | AB12: 57992.2 | AC12: 62829.1 | AD12: 74262.4 | AE12: 81402.75 | AF12: 86599.6 | AG12: 97227.9 | AH12: 121431.95 | AI12: 223332.3 | AJ12: 280053.75 | AK12: 345761.3 | AL12: 382320.95 | AM12: 477404.1 | AN12: 584669.2 | AO12: 710700 | AP12: 997012.05 | AQ12: 2+4 | AR12: X143:AP154 | AU12: 56-60 | AV12: 30884.625 | AW12: 37551.375 | AX12: 46845 | AY12: 51432.75 | AZ12: 55715.625 | BA12: 65874.375 | BB12: 72198 | BC12: 76799.25 | BD12: 86212.125 | BE12: 107645.62 | BF12: 197880.75 | BG12: 248109.75 | BH12: 306295.88 | BI12: 338837.62 | BJ12: 423037.12 | BK12: 518024.25 | BL12: 629627.62 | BM12: 883165.5 | BN12: 2+4 | BO12: AU143:BM154 | BR12: 56-60 | BS12: 28484.5 | BT12: 34626.9 | BU12: 43209.1 | BV12: 47437.5 | BW12: 51384.3 | BX12: 60765.1 | BY12: 66591.8 | BZ12: 70832.3 | CA12: 79505.8 | CB12: 99257.4 | CC12: 182410.8 | CD12: 228697.7 | CE12: 282317.2 | CF12: 312393.4 | CG12: 389985.2 | CH12: 477517.7 | CI12: 580362.2 | CJ12: 814002.2 | CK12: 2+4 | CL12: BR143:CJ154 | CO12: 56-60 | CP12: 26215.59 | CQ12: 31863.97 | CR12: 39774.1 | CS12: 43662.13 | CT12: 47290.74 | CU12: 55935.53 | CV12: 61292.88 | CW12: 65191.81 | CX12: 73168.43 | CY12: 91330.01 | CZ12: 167791.33 | DA12: 210353.65 | DB12: 259657.62 | DC12: 287403.57 | DD12: 358750.61 | DE12: 439239.48 | DF12: 533806.79 | DG12: 748644.7 | DH12: 2+3 | DI12: CO128:DG139
A13: 71-75 | B13: 71 Years | C13: 75 Years | D13: 5 | E13: INDIVIDUAL | F13: 1 | G13: 1 | H13: 0 | I13: 1 | J13: Zone 1 | K13: =G13&"+"&H13 -> 1+0 | L13: =VLOOKUP(A13,'ZONE 1 PREMIUM'!$A$3:$M$16,13,0) -> 13 | M13: =VLOOKUP(D13,DROPDOWN!B:C,2,0) -> 4 | N13: =VLOOKUP(K13,$AQ$3:$AR$12,2,0) -> X3:AP16 | O13: =INDEX(INDIRECT(N13),L13,M13) -> 111223.4 | Q13: Smart select | R13: =15% -> 0.15 | S13: =IF('CALCULATOR CARE V6'!B13="YES",1-'CARE SHEET'!R13,1) -> 1 | X13: 61-65 | Y13: 47927.4 | Z13: 58408.5 | AA13: 72870.9 | AB13: 80142.35 | AC13: 86946.9 | AD13: 102776.65 | AE13: 112839.15 | AF13: 119781.7 | AG13: 134693.75 | AH13: 168524.45 | AI13: 306799.3 | AJ13: 385914.7 | AK13: 477765.2 | AL13: 531930.2 | AM13: 665515.35 | AN13: 816535.65 | AO13: 994261.25 | AP13: 1397293.7 | AU13: 61-65 | AV13: 42484.5 | AW13: 51765.75 | AX13: 64607.625 | AY13: 71047.125 | AZ13: 77072.625 | BA13: 91125 | BB13: 100036.12 | BC13: 106184.25 | BD13: 119388.38 | BE13: 149347.12 | BF13: 271793.25 | BG13: 341852.62 | BH13: 423189 | BI13: 471322.12 | BJ13: 589614.75 | BK13: 723348 | BL13: 880729.88 | BM13: 1237627.1 | BR13: 61-65 | BS13: 39173.2 | BT13: 47725.7 | BU13: 59578.2 | BV13: 65512.7 | BW13: 71065.5 | BX13: 84033.4 | BY13: 92244.9 | BZ13: 97909.9 | CA13: 110078.1 | CB13: 137685.9 | CC13: 250521.7 | CD13: 315084 | CE13: 390035.8 | CF13: 434480.2 | CG13: 543490.2 | CH13: 666727.6 | CI13: 811757.1 | CJ13: 1140645 | CO13: 61-65 | CP13: 36044.12 | CQ13: 43908.47 | CR13: 54825.91 | CS13: 60282.45 | CT13: 65388.01 | CU13: 77331.14 | CV13: 84881.57 | CW13: 90091.77 | CX13: 101280.62 | CY13: 126666.72 | CZ13: 230421.64 | DA13: 289787.4 | DB13: 358708.1 | DC13: 399665.94 | DD13: 499902.34 | DE13: 613222.01 | DF13: 746581.33 | DG13: 1049001.8 | DH13: 2+4 | DI13: CO143:DG154
A14: 75+ | B14: >75 Years | D14: 5 | E14: INDIVIDUAL | F14: 1 | G14: 1 | H14: 0 | I14: 1 | J14: Zone 1 | K14: =G14&"+"&H14 -> 1+0 | L14: =VLOOKUP(A14,'ZONE 1 PREMIUM'!$A$3:$M$16,13,0) -> 14 | M14: =VLOOKUP(D14,DROPDOWN!B:C,2,0) -> 4 | N14: =VLOOKUP(K14,$AQ$3:$AR$12,2,0) -> X3:AP16 | O14: =INDEX(INDIRECT(N14),L14,M14) -> 148912.35 | Q14: Reduction in PED | R14: =VLOOKUP(T14,'optional benefits'!B51:C54,2,0) -> 0.15 | S14: =IF('CALCULATOR CARE V6'!B14="YES",1+'CARE SHEET'!R14,1) -> 1 | T14: =VLOOKUP(S3,DROPDOWN!L20:M110,2,0) -> Upto 45 Years | U14: =IF('CALCULATOR CARE V6'!B14="YES",1+VLOOKUP(U2,'optional benefits'!B51:C54,2,0),1) -> 1 | V14: =IF('CALCULATOR CARE V6'!B14="YES",1+VLOOKUP(U3,'optional benefits'!B51:C54,2,0),1) -> 1 | X14: 66-70 | Y14: 60881 | Z14: 74322.2 | AA14: 92842.95 | AB14: 102241.9 | AC14: 111062.4 | AD14: 131342.65 | AE14: 144449.2 | AF14: 155968.75 | AG14: 175617.65 | AH14: 220032.95 | AI14: 389046.15 | AJ14: 492315 | AK14: 612501.5 | AL14: 695669.5 | AM14: 871932.3 | AN14: 1071630.9 | AO14: 1307027.9 | AP14: 1839893 | AU14: 66-70 | AV14: 53958.375 | AW14: 65859.75 | AX14: 82296 | AY14: 90619.875 | AZ14: 98429.625 | BA14: 116422.88 | BB14: 128034 | BC14: 138234.38 | BD14: 155633.62 | BE14: 194964.75 | BF14: 344640.38 | BG14: 436087.12 | BH14: 542515.5 | BI14: 616317.75 | BJ14: 772403.62 | BK14: 949242.38 | BL14: 1157693.6 | BM14: 1629561.4 | BR14: 66-70 | BS14: 49747.5 | BT14: 60715.6 | BU14: 75880.2 | BV14: 83550.5 | BW14: 90747.8 | BX14: 107346.8 | BY14: 118048.7 | BZ14: 127449.3 | CA14: 143482.9 | CB14: 179726.8 | CC14: 317659.1 | CD14: 401930.1 | CE14: 500006.1 | CF14: 568097.2 | CG14: 711933.2 | CH14: 874892.7 | CI14: 1066985.7 | CJ14: 1501820.1 | CO14: 66-70 | CP14: 45769.1 | CQ14: 55853.78 | CR14: 69816.68 | CS14: 76870.07 | CT14: 83487.46 | CU14: 98770.35 | CV14: 108611.96 | CW14: 117256.75 | CX14: 132000.09 | CY14: 165327.93 | CZ14: 292163.6 | DA14: 369652.79 | DB14: 459836.12 | DC14: 522529.65 | DD14: 654790.25 | DE14: 804635.82 | DF14: 981269.23 | DG14: 1381110.7
A15: 18-24 | B15: 18 Years | C15: 24 Years | D15: 5 | E15: FLOATER | F15: 2 | G15: 1 | H15: 1 | I15: 1 | J15: Zone 1 | K15: =G15&"+"&H15 -> 1+1 | L15: =VLOOKUP(A15,'ZONE 1 PREMIUM'!$A$4:$N$16,14,0) -> 2 | M15: =VLOOKUP(D15,DROPDOWN!B:C,2,0) -> 4 | N15: =VLOOKUP(K15,$AQ$3:$AR$12,2,0) -> X20:AP31 | O15: =INDEX(INDIRECT(N15),L15,M15) -> 16951 | Q15: Room Rent modification | R15: =IF(T3<5,'optional benefits'!C87,'optional benefits'!C88) -> 0.125 | S15: =IF('CALCULATOR CARE V6'!B15="YES",1+'CARE SHEET'!R15,1) -> 1 | V15: CARE SHIELD | X15: 71-75 | Y15: 72692.65 | Z15: 88885.8 | AA15: 111223.4 | AB15: 122636 | AC15: 133374.7 | AD15: 157846.7 | AE15: 173817.9 | AF15: 187923.8 | AG15: 211866.8 | AH15: 265792.6 | AI15: 455161.95 | AJ15: 579790.9 | AK15: 725204.95 | AL15: 842438.25 | AM15: 1057553.8 | AN15: 1301772.4 | AO15: 1590109.6 | AP15: 2241659.3 | AU15: 71-75 | AV15: 64417.5 | AW15: 78756.75 | AX15: 98572.5 | AY15: 108679.5 | AZ15: 118188 | BA15: 139893.75 | BB15: 154040.62 | BC15: 166532.62 | BD15: 187734.38 | BE15: 235487.25 | BF15: 403187.62 | BG15: 513550.12 | BH15: 642318.75 | BI15: 746286.75 | BJ15: 936777.38 | BK15: 1153039.5 | BL15: 1408371.8 | BM15: 1985338.1 | BR15: 71-75 | BS15: 59386.8 | BT15: 72600 | BU15: 90878.7 | BV15: 100192.4 | BW15: 108955 | BX15: 128976.1 | BY15: 142014.4 | BZ15: 153525.9 | CA15: 173064.1 | CB15: 217069.6 | CC15: 371611.9 | CD15: 473313.5 | CE15: 591976 | CF15: 687865.2 | CG15: 863405.4 | CH15: 1062695.7 | CI15: 1297989 | CJ15: 1829675.1 | CO15: 71-75 | CP15: 54631.89 | CQ15: 66782.12 | CR15: 83608.45 | CS15: 92172.58 | CT15: 100230.95 | CU15: 118658.49 | CV15: 130649.58 | CW15: 141234.57 | CX15: 159199.95 | CY15: 199664.02 | CZ15: 341774.95 | DA15: 435291.5 | DB15: 544404.86 | DC15: 632658.89 | DD15: 794073.72 | DE15: 977325.61 | DF15: 1193683 | DG15: 1682581.8
A16: 25-35 | B16: 25 Years | C16: 35 Years | D16: 5 | E16: FLOATER | F16: 2 | G16: 1 | H16: 1 | I16: 1 | J16: Zone 1 | K16: =G16&"+"&H16 -> 1+1 | L16: =VLOOKUP(A16,'ZONE 1 PREMIUM'!$A$4:$N$16,14,0) -> 3 | M16: =VLOOKUP(D16,DROPDOWN!B:C,2,0) -> 4 | N16: =VLOOKUP(K16,$AQ$3:$AR$12,2,0) -> X20:AP31 | O16: =INDEX(INDIRECT(N16),L16,M16) -> 18759.95 | Q16: Unlimited recharge | R16: =INDEX('optional benefits'!C14:P15,MATCH('CARE SHEET'!S11,'optional benefits'!B14:B15,0),MATCH('CALCULATOR CARE V6'!B6,'optional benefits'!C13:P13,0)) -> #N/A | S16: =IF('CALCULATOR CARE V6'!B16="YES",1+'CARE SHEET'!R16,1) -> 1 | T16: =IF('CALCULATOR CARE V6'!B16="YES",1+INDEX('optional benefits'!C14:P15,MATCH('CARE SHEET'!T11,'optional benefits'!B14:B15,0),MATCH('CALCULATOR CARE V6'!B6,'optional benefits'!C13:P13,0)),1) -> 1 | U16: =IF('CALCULATOR CARE V6'!B16="YES",1+INDEX('optional benefits'!C14:P15,MATCH('CARE SHEET'!U11,'optional benefits'!B14:B15,0),MATCH('CALCULATOR CARE V6'!B6,'optional benefits'!C13:P13,0)),1) -> 1 | V16: 0.085 | X16: 75+ | Y16: 97080.7 | Z16: 118895.05 | AA16: 148912.35 | AB16: 164409.75 | AC16: 179030.85 | AD16: 212022.05 | AE16: 233781.2 | AF16: 253096.6 | AG16: 285723.25 | AH16: 358940.3 | AI16: 593725.45 | AJ16: 761879.6 | AK16: 958587.1 | AL16: 1140764.3 | AM16: 1434366.2 | AN16: 1768372.2 | AO16: 2163347.8 | AP16: 3054293 | AU16: 75+ | AV16: 86013 | AW16: 105331.5 | AX16: 131947.88 | AY16: 145670.62 | AZ16: 158618.25 | BA16: 187867.12 | BB16: 207139.5 | BC16: 224244 | BD16: 253136.25 | BE16: 317972.25 | BF16: 525889.12 | BG16: 674794.12 | BH16: 848984.62 | BI16: 1010462.6 | BJ16: 1270455.8 | BK16: 1566228.4 | BL16: 1915990.9 | BM16: 2704948.9 | BR16: 75+ | BS16: 79286.9 | BT16: 97089.3 | BU16: 121634.7 | BV16: 134281.4 | BW16: 146212 | BX16: 173184 | BY16: 190946.8 | BZ16: 206708.7 | CA16: 233333.1 | CB16: 293080.7 | CC16: 484684.2 | CD16: 621903.7 | CE16: 782423.4 | CF16: 931308.4 | CG16: 1170898.3 | CH16: 1443457.4 | CI16: 1765769.5 | CJ16: 2492810.1 | CO16: 75+ | CP16: 72930.81 | CQ16: 89300.43 | CR16: 111889.59 | CS16: 123517.71 | CT16: 134488.56 | CU16: 159308.95 | CV16: 175643.69 | CW16: 190137.42 | CX16: 214618.82 | CY16: 269558.09 | CZ16: 445746.78 | DA16: 571924.09 | DB16: 719525.35 | DC16: 856511.1 | DD16: 1076819.7 | DE16: 1327445.6 | DF16: 1623819.9 | DG16: 2292351.8
A17: 36-40 | B17: 36 Years | C17: 40 Years | D17: 5 | E17: FLOATER | F17: 2 | G17: 1 | H17: 1 | I17: 1 | J17: Zone 1 | K17: =G17&"+"&H17 -> 1+1 | L17: =VLOOKUP(A17,'ZONE 1 PREMIUM'!$A$4:$N$16,14,0) -> 4 | M17: =VLOOKUP(D17,DROPDOWN!B:C,2,0) -> 4 | N17: =VLOOKUP(K17,$AQ$3:$AR$12,2,0) -> X20:AP31 | O17: =INDEX(INDIRECT(N17),L17,M17) -> 21637.25 | Q17: CO-PAYMENT | R17: =20% -> 0.2 | S17: =IF('CALCULATOR CARE V6'!B17="YES",1-'CARE SHEET'!R17,1) -> 0.8 | V17: =R11*S12*S17*S27 -> 149487.64 | Y17: q
A18: 41-45 | B18: 41 Years | C18: 45 Years | D18: 5 | E18: FLOATER | F18: 2 | G18: 1 | H18: 1 | I18: 1 | J18: Zone 1 | K18: =G18&"+"&H18 -> 1+1 | L18: =VLOOKUP(A18,'ZONE 1 PREMIUM'!$A$4:$N$16,14,0) -> 5 | M18: =VLOOKUP(D18,DROPDOWN!B:C,2,0) -> 4 | N18: =VLOOKUP(K18,$AQ$3:$AR$12,2,0) -> X20:AP31 | O18: =INDEX(INDIRECT(N18),L18,M18) -> 25416.15 | Q18: Everyday care | R18: =IF('CALCULATOR CARE V6'!B18="YES",INDEX('optional benefits'!B21:T30,MATCH('CARE SHEET'!R4,'optional benefits'!A21:A30,0),MATCH('CALCULATOR CARE V6'!B6,'optional benefits'!B20:T20,0)),0) -> 31906.687 | V18: =V17*V16 -> 12706.449 | X18: 1A1C | Y18: q
A19: 46-50 | B19: 46 Years | C19: 50 Years | D19: 5 | E19: FLOATER | F19: 2 | G19: 1 | H19: 1 | I19: 1 | J19: Zone 1 | K19: =G19&"+"&H19 -> 1+1 | L19: =VLOOKUP(A19,'ZONE 1 PREMIUM'!$A$4:$N$16,14,0) -> 6 | M19: =VLOOKUP(D19,DROPDOWN!B:C,2,0) -> 4 | N19: =VLOOKUP(K19,$AQ$3:$AR$12,2,0) -> X20:AP31 | O19: =INDEX(INDIRECT(N19),L19,M19) -> 30929.25 | Q19: Care Shield | R19: =IF('CALCULATOR CARE V6'!B19="YES",'CARE SHEET'!V18,0) -> 12706.449 | W19: add si | Y19: Care 3 | AA19: Care 4 | AD19: Care 5 | AI19: Care 6 | AL19: Care 7 | AT19: 1A1C | AV19: Care 3 | AX19: Care 4 | BA19: Care 5 | BF19: Care 6 | BI19: Care 7 | BQ19: 1A1C | BS19: Care 3 | BU19: Care 4 | BX19: Care 5 | CC19: Care 6 | CF19: Care 7 | CN19: 1A1C | CP19: Care 3 | CR19: Care 4 | CU19: Care 5 | CZ19: Care 6 | DC19: Care 7
A20: 51-55 | B20: 51 Years | C20: 55 Years | D20: 5 | E20: FLOATER | F20: 2 | G20: 1 | H20: 1 | I20: 1 | J20: Zone 1 | K20: =G20&"+"&H20 -> 1+1 | L20: =VLOOKUP(A20,'ZONE 1 PREMIUM'!$A$4:$N$16,14,0) -> 7 | M20: =VLOOKUP(D20,DROPDOWN!B:C,2,0) -> 4 | N20: =VLOOKUP(K20,$AQ$3:$AR$12,2,0) -> X20:AP31 | O20: =INDEX(INDIRECT(N20),L20,M20) -> 40040.7 | Q20: OPD Care | R20: =IF('CALCULATOR CARE V6'!B20="YES",INDEX('optional benefits'!C35:L44,MATCH('CARE SHEET'!R4,'optional benefits'!B35:B44,0),MATCH('CALCULATOR CARE V6'!C20,'optional benefits'!C34:L34,0)),0) -> 2285.3708 | V20: DA+ | W20: =VLOOKUP('CALCULATOR CARE V6'!C24,DROPDOWN!F5:G14,2,0) -> 1 | X20: Age-Band/ SI | Y20: 3L | Z20: 4L | AA20: 5L | AB20: 7L | AC20: 10L | AD20: 15L | AE20: 20L | AF20: 25L | AG20: 30L | AH20: 40L | AI20: 50L | AJ20: 60L | AK20: 75L | AL20: 1 CR | AM20: 1.5 CR | AN20: 2 CR | AO20: 3 CR | AP20: 6 CR | AU20: Age-Band/ SI | AV20: 3L | AW20: 4L | AX20: 5L | AY20: 7L | AZ20: 10L | BA20: 15L | BB20: 20L | BC20: 25L | BD20: 30L | BE20: 40L | BF20: 50L | BG20: 60L | BH20: 75L | BI20: 1 CR | BJ20: 1.5 CR | BK20: 2 CR | BL20: 3 CR | BM20: 6 CR | BR20: Age-Band/ SI | BS20: 3L | BT20: 4L | BU20: 5L | BV20: 7L | BW20: 10L | BX20: 15L | BY20: 20L | BZ20: 25L | CA20: 30L | CB20: 40L | CC20: 50L | CD20: 60L | CE20: 75L | CF20: 1 CR | CG20: 1.5 CR | CH20: 2 CR | CI20: 3 CR | CJ20: 6 CR | CO20: Age-Band/ SI | CP20: 3L | CQ20: 4L | CR20: 5L | CS20: 7L | CT20: 10L | CU20: 15L | CV20: 20L | CW20: 25L | CX20: 30L | CY20: 40L | CZ20: 50L | DA20: 60L | DB20: 75L | DC20: 1 CR | DD20: 1.5 CR | DE20: 2 CR | DF20: 3 CR | DG20: 6 CR
A21: 56-60 | B21: 56 Years | C21: 60 Years | D21: 5 | E21: FLOATER | F21: 2 | G21: 1 | H21: 1 | I21: 1 | J21: Zone 1 | K21: =G21&"+"&H21 -> 1+1 | L21: =VLOOKUP(A21,'ZONE 1 PREMIUM'!$A$4:$N$16,14,0) -> 8 | M21: =VLOOKUP(D21,DROPDOWN!B:C,2,0) -> 4 | N21: =VLOOKUP(K21,$AQ$3:$AR$12,2,0) -> X20:AP31 | O21: =INDEX(INDIRECT(N21),L21,M21) -> 54439.85 | Q21: Air Ambulance | R21: =IF('CALCULATOR CARE V6'!B21="YES",'optional benefits'!C59*'CARE SHEET'!S17*S27,0) -> 0 | U21: =VLOOKUP('CALCULATOR CARE V6'!H3,DROPDOWN!$K:$N,4,0) -> Upto 45 Years | V21: =IF('CALCULATOR CARE V6'!I3="YES",VLOOKUP(U21,'optional benefits'!$A$115:$C$118,2,0)*$W$20,0) -> 413.08982 | W21: =IF('CALCULATOR CARE V6'!I3="yes",INDEX('ADD SI'!$B$45:$AB$49,MATCH('CARE SHEET'!U21,'ADD SI'!$B$45:$B$49,0),MATCH('CARE SHEET'!$T$3,'ADD SI'!$B$45:$Q$45,0)),0) -> #N/A | X21: 18-24 | Y21: 11110.15 | Z21: 13517.1 | AA21: 16951 | AB21: 17891.7 | AC21: 19245.25 | AD21: 24315.6 | AE21: 26655.85 | AF21: 28694.8 | AG21: 31984.95 | AH21: 39652 | AI21: 76208.2 | AJ21: 92630.2 | AK21: 111071.6 | AL21: 162783.65 | AM21: 192907.9 | AN21: 226178.55 | AO21: 264723.1 | AP21: 353329.45 | AU21: 18-24 | AV21: 9869.625 | AW21: 12001.5 | AX21: 15058.125 | AY21: 15889.5 | AZ21: 17087.625 | BA21: 21592.125 | BB21: 23664.375 | BC21: 25470 | BD21: 28383.75 | BE21: 35173.125 | BF21: 67545 | BG21: 82086.75 | BH21: 98417.25 | BI21: 145074.38 | BJ21: 171749.25 | BK21: 201211.88 | BL21: 235343.25 | BM21: 313807.5 | BR21: 18-24 | BS21: 9111.3 | BT21: 11075.9 | BU21: 13900.7 | BV21: 14666.3 | BW21: 15770.7 | BX21: 19929.8 | BY21: 21839.4 | BZ21: 23502.6 | CA21: 26187.7 | CB21: 32444.5 | CC21: 62275.4 | CD21: 75676.7 | CE21: 90724.7 | CF21: 134174.7 | CG21: 158757.5 | CH21: 185906.6 | CI21: 217360 | CJ21: 289666.3 | CO21: 18-24 | CP21: 8395.18 | CQ21: 10201.31 | CR21: 12807.5 | CS21: 13510.55 | CT21: 14526.43 | CU21: 18357.78 | CV21: 20113.77 | CW21: 21644.13 | CX21: 24112.98 | CY21: 29866 | CZ21: 57295.85 | DA21: 69618.3 | DB21: 83455.85 | DC21: 123869.78 | DD21: 146473.11 | DE21: 171438.47 | DF21: 200360.53 | DG21: 266847.26
A22: 61-65 | B22: 61 Years | C22: 65 Years | D22: 5 | E22: FLOATER | F22: 2 | G22: 1 | H22: 1 | I22: 1 | J22: Zone 1 | K22: =G22&"+"&H22 -> 1+1 | L22: =VLOOKUP(A22,'ZONE 1 PREMIUM'!$A$4:$N$16,14,0) -> 9 | M22: =VLOOKUP(D22,DROPDOWN!B:C,2,0) -> 4 | N22: =VLOOKUP(K22,$AQ$3:$AR$12,2,0) -> X20:AP31 | O22: =INDEX(INDIRECT(N22),L22,M22) -> 73485 | Q22: BE-FIT | R22: =IF('CALCULATOR CARE V6'!B22="YES",'optional benefits'!C81*'CALCULATOR CARE V6'!K10,0) -> 0 | U22: =VLOOKUP('CALCULATOR CARE V6'!H4,DROPDOWN!$K:$N,4,0) -> Upto 45 Years | V22: =IF('CALCULATOR CARE V6'!I4="YES",VLOOKUP(U22,'optional benefits'!$A$115:$C$118,2,0)*$W$20,0) -> 0 | W22: =IF('CALCULATOR CARE V6'!I4="yes",INDEX('ADD SI'!$B$45:$AB$49,MATCH('CARE SHEET'!U22,'ADD SI'!$B$45:$B$49,0),MATCH('CARE SHEET'!$T$3,'ADD SI'!$B$45:$Q$45,0)),0) -> 0 | X22: 25-35 | Y22: 12390.1 | Z22: 14867.2 | AA22: 18759.95 | AB22: 19804.15 | AC22: 21307.2 | AD22: 26939.9 | AE22: 29420.45 | AF22: 31580.15 | AG22: 35203.8 | AH22: 43627.55 | AI22: 83941.95 | AJ22: 102738.7 | AK22: 124190.8 | AL22: 177019.5 | AM22: 210804.2 | AN22: 248230.95 | AO22: 291671.05 | AP22: 391385.25 | AU22: 25-35 | AV22: 11010.375 | AW22: 13204.125 | AX22: 16673.625 | AY22: 17596.125 | AZ22: 18927 | BA22: 23936.625 | BB22: 26131.5 | BC22: 28045.125 | BD22: 31253.625 | BE22: 38713.5 | BF22: 74413.125 | BG22: 91057.5 | BH22: 110054.25 | BI22: 157686.75 | BJ22: 187605 | BK22: 220746.38 | BL22: 259214.62 | BM22: 347514.75 | BR22: 25-35 | BS22: 10167.3 | BT22: 12188 | BU22: 15397.8 | BV22: 16247 | BW22: 17473.5 | BX22: 22099 | BY22: 24123 | BZ22: 25886.3 | CA22: 28843.1 | CB22: 35717 | CC22: 68614.7 | CD22: 83953.1 | CE22: 101458.5 | CF22: 145801.7 | CG22: 173372.1 | CH22: 203912.5 | CI22: 239362.2 | CJ22: 320731.4 | CO22: 25-35 | CP22: 9369.64 | CQ22: 11228.09 | CR22: 14190.71 | CS22: 14971.15 | CT22: 16098.21 | CU22: 20363.38 | CV22: 22224.01 | CW22: 23844.84 | CX22: 26564.39 | CY22: 32885.3 | CZ22: 63136.07 | DA22: 77239.58 | DB22: 93336.7 | DC22: 134564.86 | DD22: 159916.08 | DE22: 187998.84 | DF22: 220595.29 | DG22: 295416.16
A23: 66-70 | B23: 66 Years | C23: 70 Years | D23: 5 | E23: FLOATER | F23: 2 | G23: 1 | H23: 1 | I23: 1 | J23: Zone 1 | K23: =G23&"+"&H23 -> 1+1 | L23: =VLOOKUP(A23,'ZONE 1 PREMIUM'!$A$4:$N$16,14,0) -> 10 | M23: =VLOOKUP(D23,DROPDOWN!B:C,2,0) -> 4 | N23: =VLOOKUP(K23,$AQ$3:$AR$12,2,0) -> X20:AP31 | O23: =INDEX(INDIRECT(N23),L23,M23) -> 95891.6 | Q23: INTERNATIONAL SECOND OPINION | R23: =IF('CALCULATOR CARE V6'!B23="YES",'optional benefits'!C126,0) -> 0 | U23: =VLOOKUP('CALCULATOR CARE V6'!H5,DROPDOWN!$K:$N,4,0) -> Upto 45 Years | V23: =IF('CALCULATOR CARE V6'!I5="YES",VLOOKUP(U23,'optional benefits'!$A$115:$C$118,2,0)*$W$20,0) -> 0 | W23: =IF('CALCULATOR CARE V6'!I5="yes",INDEX('ADD SI'!$B$45:$AB$49,MATCH('CARE SHEET'!U23,'ADD SI'!$B$45:$B$49,0),MATCH('CARE SHEET'!$T$3,'ADD SI'!$B$45:$Q$45,0)),0) -> 0 | X23: 36-40 | Y23: 14143.85 | Z23: 17045.3 | AA23: 21637.25 | AB23: 22866.6 | AC23: 24628.4 | AD23: 31174.2 | AE23: 34083.7 | AF23: 36626.35 | AG23: 40872.15 | AH23: 50711.55 | AI23: 89686.2 | AJ23: 111702.95 | AK23: 136874.15 | AL23: 186281.6 | AM23: 225271.2 | AN23: 268631.95 | AO23: 319087.05 | AP23: 434709.2 | AU23: 36-40 | AV23: 12564 | AW23: 15133.5 | AX23: 19225.125 | AY23: 20311.875 | AZ23: 21871.125 | BA23: 27690.75 | BB23: 30268.125 | BC23: 32519.25 | BD23: 36279 | BE23: 44992.125 | BF23: 79504.875 | BG23: 99002.25 | BH23: 121291.88 | BI23: 165692.25 | BJ23: 200218.5 | BK23: 238615.88 | BL23: 283295.25 | BM23: 385681.5 | BR23: 36-40 | BS23: 11598.4 | BT23: 13966.7 | BU23: 17750.7 | BV23: 18750.6 | BW23: 20188.3 | BX23: 25562.9 | BY23: 27937.8 | BZ23: 30012.4 | CA23: 33477.4 | CB23: 41506.3 | CC23: 73310.6 | CD23: 91276.9 | CE23: 111818.3 | CF23: 153074.9 | CG23: 184891.3 | CH23: 220275 | CI23: 261448 | CJ23: 355799.4 | CO23: 36-40 | CP23: 10686.36 | CQ23: 12864.18 | CR23: 16356.54 | CS23: 17275.41 | CT23: 18596.49 | CU23: 23551.63 | CV23: 25734.9 | CW23: 27642.4 | CX23: 30828.47 | CY23: 38212.13 | CZ23: 67456.83 | DA23: 83976.87 | DB23: 102864.39 | DC23: 141147.37 | DD23: 170402.97 | DE23: 202939.47 | DF23: 240798.44 | DG23: 327556.99
A24: 71-75 | B24: 71 Years | C24: 75 Years | D24: 5 | E24: FLOATER | F24: 2 | G24: 1 | H24: 1 | I24: 1 | J24: Zone 1 | K24: =G24&"+"&H24 -> 1+1 | L24: =VLOOKUP(A24,'ZONE 1 PREMIUM'!$A$4:$N$16,14,0) -> 11 | M24: =VLOOKUP(D24,DROPDOWN!B:C,2,0) -> 4 | N24: =VLOOKUP(K24,$AQ$3:$AR$12,2,0) -> X20:AP31 | O24: =INDEX(INDIRECT($N$24),$L$24,$M$24) -> 112788.55 | Q24: Daily Allowance+ | R24: =IF('CALCULATOR CARE V6'!B24="YES",V41*S12*S14*S16,0) -> 0 | U24: =VLOOKUP('CALCULATOR CARE V6'!H6,DROPDOWN!$K:$N,4,0) -> Upto 45 Years | V24: =IF('CALCULATOR CARE V6'!I6="YES",VLOOKUP(U24,'optional benefits'!$A$115:$C$118,2,0)*$W$20,0) -> 0 | W24: =IF('CALCULATOR CARE V6'!I6="yes",INDEX('ADD SI'!$B$45:$AB$49,MATCH('CARE SHEET'!U24,'ADD SI'!$B$45:$B$49,0),MATCH('CARE SHEET'!$T$3,'ADD SI'!$B$45:$Q$45,0)),0) -> 0 | X24: 41-45 | Y24: 16495.6 | Z24: 19943.3 | AA24: 25416.15 | AB24: 26891.6 | AC24: 28992.65 | AD24: 36714.9 | AE24: 40097.05 | AF24: 43018.05 | AG24: 48057.35 | AH24: 59696.5 | AI24: 103625.35 | AJ24: 129909.75 | AK24: 160013.3 | AL24: 204763.25 | AM24: 250572.35 | AN24: 301684.1 | AO24: 361281.7 | AP24: 497629.15 | AU24: 41-45 | AV24: 14649.75 | AW24: 17701.875 | AX24: 22576.5 | AY24: 23880.375 | AZ24: 25742.25 | BA24: 32605.875 | BB24: 35599.5 | BC24: 38187 | BD24: 42649.875 | BE24: 52956 | BF24: 91857.375 | BG24: 115131.38 | BH24: 141789.38 | BI24: 181846.12 | BJ24: 222411.38 | BK24: 267672.38 | BL24: 320448.38 | BM24: 441187.88 | BR24: 41-45 | BS24: 13522.3 | BT24: 16335 | BU24: 20841.7 | BV24: 22041.8 | BW24: 23756.7 | BX24: 30096 | BY24: 32854.8 | BZ24: 35238.5 | CA24: 39351.4 | CB24: 48849.9 | CC24: 84696.7 | CD24: 106145.6 | CE24: 130710.8 | CF24: 167849 | CG24: 205231.4 | CH24: 246940.1 | CI24: 295574.4 | CJ24: 406838.3 | CO24: 41-45 | CP24: 12455.43 | CQ24: 15042 | CR24: 19201.44 | CS24: 20303.43 | CT24: 21880.66 | CU24: 27723.06 | CV24: 30260.58 | CW24: 32452.57 | CX24: 36234.87 | CY24: 44967.95 | CZ24: 77930.64 | DA24: 97653.1 | DB24: 120241.17 | DC24: 154619.77 | DD24: 188992.92 | DE24: 227345.66 | DF24: 272066.18 | DG24: 374375.76
A25: 75+ | B25: >75 Years | D25: 5 | E25: FLOATER | F25: 2 | G25: 1 | H25: 1 | I25: 1 | J25: Zone 1 | K25: =G25&"+"&H25 -> 1+1 | L25: =VLOOKUP(A25,'ZONE 1 PREMIUM'!$A$4:$N$16,14,0) -> 12 | M25: =VLOOKUP(D25,DROPDOWN!B:C,2,0) -> 4 | N25: =VLOOKUP(K25,$AQ$3:$AR$12,2,0) -> X20:AP31 | O25: =INDEX(INDIRECT(N25),L25,M25) -> 152572.8 | Q25: Advance Annual Health Check up | R25: =IF('CALCULATOR CARE V6'!B25="YES",'CARE SHEET'!V31,0) -> 0 | U25: =VLOOKUP('CALCULATOR CARE V6'!H7,DROPDOWN!$K:$N,4,0) -> Upto 45 Years | V25: =IF('CALCULATOR CARE V6'!I7="YES",VLOOKUP(U25,'optional benefits'!$A$115:$C$118,2,0)*$W$20,0) -> 0 | W25: =IF('CALCULATOR CARE V6'!I7="yes",INDEX('ADD SI'!$B$45:$AB$49,MATCH('CARE SHEET'!U25,'ADD SI'!$B$45:$B$49,0),MATCH('CARE SHEET'!$T$3,'ADD SI'!$B$45:$Q$45,0)),0) -> 0 | X25: 46-50 | Y25: 20020.35 | Z25: 24262.7 | AA25: 30929.25 | AB25: 34506.9 | AC25: 37243.9 | AD25: 45268.6 | AE25: 49499.45 | AF25: 53171.4 | AG25: 59457.3 | AH25: 73924.3 | AI25: 125191.3 | AJ25: 158191.7 | AK25: 196071.55 | AL25: 235547.6 | AM25: 291893 | AN25: 354983.15 | AO25: 428717.7 | AP25: 597114.5 | AU25: 46-50 | AV25: 17776.125 | AW25: 21534.75 | AX25: 27471.375 | AY25: 30637.125 | AZ25: 33061.5 | BA25: 40200.75 | BB25: 43947 | BC25: 47198.25 | BD25: 52764.75 | BE25: 65575.125 | BF25: 110974.5 | BG25: 140197.5 | BH25: 173740.5 | BI25: 208992.38 | BJ25: 258888.38 | BK25: 314757 | BL25: 380050.88 | BM25: 529170.75 | BR25: 46-50 | BS25: 16406.5 | BT25: 19869.3 | BU25: 25359.4 | BV25: 28275.5 | BW25: 30509.6 | BX25: 37105.2 | BY25: 40558.1 | BZ25: 43554.5 | CA25: 48683.8 | CB25: 60489 | CC25: 102325.3 | CD25: 129254.4 | CE25: 160165.5 | CF25: 192805.8 | CG25: 238785.8 | CH25: 290270.2 | CI25: 350439.1 | CJ25: 487856.6 | CO25: 46-50 | CP25: 15112.85 | CQ25: 18296.74 | CR25: 23363.06 | CS25: 26043.37 | CT25: 28096.93 | CU25: 34179.13 | CV25: 37354.3 | CW25: 40109.82 | CX25: 44826.25 | CY25: 55681.56 | CZ25: 94150.93 | DA25: 118913.55 | DB25: 147336.39 | DC25: 177507.59 | DD25: 219786.51 | DE25: 267127.39 | DF25: 322454.7 | DG25: 448814.04
A26: 18-24 | B26: 18 Years | C26: 24 Years | D26: 5 | E26: FLOATER | F26: 3 | G26: 1 | H26: 2 | I26: 1 | J26: Zone 1 | K26: =G26&"+"&H26 -> 1+2 | L26: =VLOOKUP(A26,'ZONE 1 PREMIUM'!$A$4:$N$16,14,0) -> 2 | M26: =VLOOKUP(D26,DROPDOWN!B:C,2,0) -> 4 | N26: =VLOOKUP(K26,$AQ$3:$AR$12,2,0) -> X35:AP46 | O26: =INDEX(INDIRECT(N26),L26,M26) -> 21185.3 | Q26: Personal Accident | R26: =IF('CALCULATOR CARE V6'!B26="YES",'optional benefits'!B123*'CALCULATOR CARE V6'!C26,0) -> 0 | U26: =VLOOKUP('CALCULATOR CARE V6'!H8,DROPDOWN!$K:$N,4,0) -> Upto 45 Years | V26: =IF('CALCULATOR CARE V6'!I8="YES",VLOOKUP(U26,'optional benefits'!$A$115:$C$118,2,0)*$W$20,0) -> 0 | W26: =IF('CALCULATOR CARE V6'!I8="yes",INDEX('ADD SI'!$B$45:$AB$49,MATCH('CARE SHEET'!U26,'ADD SI'!$B$45:$B$49,0),MATCH('CARE SHEET'!$T$3,'ADD SI'!$B$45:$Q$45,0)),0) -> 0 | X26: 51-55 | Y26: 26252.2 | Z26: 31911.35 | AA26: 40040.7 | AB26: 44779.85 | AC26: 48392 | AD26: 58789.15 | AE26: 64393.1 | AF26: 69278.3 | AG26: 77572.1 | AH26: 96602.3 | AI26: 171071.7 | AJ26: 214895.9 | AK26: 265280.85 | AL26: 307837.75 | AM26: 382437.1 | AN26: 466134.1 | AO26: 564093.4 | AP26: 787464.8 | AU26: 51-55 | AV26: 23297.625 | AW26: 28308.375 | AX26: 35546.625 | AY26: 39739.5 | AZ26: 42939 | BA26: 52182 | BB26: 57143.25 | BC26: 61470 | BD26: 68815.125 | BE26: 85666.5 | BF26: 151611.75 | BG26: 190418.62 | BH26: 235036.12 | BI26: 272981.25 | BJ26: 339041.25 | BK26: 413156.25 | BL26: 499902.75 | BM26: 697704.75 | BR26: 51-55 | BS26: 21495.1 | BT26: 26114 | BU26: 32803.1 | BV26: 36666.3 | BW26: 39614.3 | BX26: 48150.3 | BY26: 52723 | BZ26: 56710.5 | CA26: 63478.8 | CB26: 79007.5 | CC26: 139777 | CD26: 175539.1 | CE26: 216654.9 | CF26: 251758.1 | CG26: 312634.3 | CH26: 380932.2 | CI26: 460870.3 | CJ26: 643149.1 | CO26: 51-55 | CP26: 19792.22 | CQ26: 24038.86 | CR26: 30210.44 | CS26: 33760.57 | CT26: 36471.4 | CU26: 44341.2 | CV26: 48545.33 | CW26: 52212.09 | CX26: 58434.9 | CY26: 72713.9 | CZ26: 128593.84 | DA26: 161476.96 | DB26: 199284.7 | DC26: 231700.21 | DD26: 287678.25 | DE26: 350479.69 | DF26: 423984.93 | DG26: 591594.23
A27: 25-35 | B27: 25 Years | C27: 35 Years | D27: 5 | E27: FLOATER | F27: 3 | G27: 1 | H27: 2 | I27: 1 | J27: Zone 1 | K27: =G27&"+"&H27 -> 1+2 | L27: =VLOOKUP(A27,'ZONE 1 PREMIUM'!$A$4:$N$16,14,0) -> 3 | M27: =VLOOKUP(D27,DROPDOWN!B:C,2,0) -> 4 | N27: =VLOOKUP(K27,$AQ$3:$AR$12,2,0) -> X35:AP46 | O27: =INDEX(INDIRECT(N27),L27,M27) -> 22760.8 | Q27: DEDUCTIBLE | R27: =INDEX('optional benefits'!C133:V140,MATCH('CALCULATOR CARE V6'!C27,'optional benefits'!B133:B140,0),MATCH('CALCULATOR CARE V6'!B6,'optional benefits'!C132:V132,0)) -> 0.0025 | S27: =IF('CALCULATOR CARE V6'!B27="YES",1-'CARE SHEET'!R27,1) -> 1 | X27: 56-60 | Y27: 35308.45 | Z27: 42972.05 | AA27: 54439.85 | AB27: 59231.9 | AC27: 64081.45 | AD27: 78394.35 | AE27: 85947.55 | AF27: 91646.95 | AG27: 102737.55 | AH27: 128088.15 | AI27: 227176.75 | AJ27: 285693.35 | AK27: 353165 | AL27: 407562.3 | AM27: 507368.5 | AN27: 619609.65 | AO27: 751212.2 | AP27: 1050733.1 | AU27: 56-60 | AV27: 31327.875 | AW27: 38115 | AX27: 48318.75 | AY27: 52558.875 | AZ27: 56854.125 | BA27: 69574.5 | BB27: 76263.75 | BC27: 81309.375 | BD27: 91131.75 | BE27: 113580 | BF27: 201325.5 | BG27: 253143 | BH27: 312891.75 | BI27: 361337.62 | BJ27: 449717.62 | BK27: 549111.38 | BL27: 665649 | BM27: 930883.5 | BR27: 56-60 | BS27: 28902.5 | BT27: 35156 | BU27: 44585.2 | BV27: 48490.2 | BW27: 52448 | BX27: 64194.9 | BY27: 70359.3 | BZ27: 75010.1 | CA27: 84060.9 | CB27: 104746.4 | CC27: 185606.3 | CD27: 233357.3 | CE27: 288416.7 | CF27: 333204.3 | CG27: 414649.4 | CH27: 506242 | CI27: 613633.9 | CJ27: 858052.8 | CO27: 56-60 | CP27: 26609.08 | CQ27: 32359.92 | CR27: 41055.94 | CS27: 44645.31 | CT27: 48284.82 | CU27: 59110.7 | CV27: 64778.7 | CW27: 69054.77 | CX27: 77378.01 | CY27: 96399.6 | CZ27: 170751.77 | DA27: 214660.24 | DB27: 265288.56 | DC27: 306618.09 | DD27: 381507.63 | DE27: 465729.75 | DF27: 564479.39 | DG27: 789228.67
A28: 36-40 | B28: 36 Years | C28: 40 Years | D28: 5 | E28: FLOATER | F28: 3 | G28: 1 | H28: 2 | I28: 1 | J28: Zone 1 | K28: =G28&"+"&H28 -> 1+2 | L28: =VLOOKUP(A28,'ZONE 1 PREMIUM'!$A$4:$N$16,14,0) -> 4 | M28: =VLOOKUP(D28,DROPDOWN!B:C,2,0) -> 4 | N28: =VLOOKUP(K28,$AQ$3:$AR$12,2,0) -> X35:AP46 | O28: =INDEX(INDIRECT(N28),L28,M28) -> 26272.9 | Q28: GLOBAL COVERAGE TOTAL | R28: =HLOOKUP('CALCULATOR CARE V6'!B6,'optional benefits'!B99:F100,2,0) -> 0.4 | S28: =IF('CALCULATOR CARE V6'!B28="YES",S31*'CARE SHEET'!R28,0) -> 0 | U28: =V21+SUM(V22:V26)*95% -> 413.08982 | V28: =V21+V22*95%+V23*95%+V24*95%+V25*95%+V26*95% -> 413.08982 | W28: =W21+SUM(W22:W26)*97.5% -> #N/A | X28: 61-65 | Y28: 48477.1 | Z28: 59098.5 | AA28: 73485 | AB28: 82624.05 | AC28: 89534.4 | AD28: 108111.5 | AE28: 118692.65 | AF28: 126257.35 | AG28: 141784.65 | AH28: 177127.6 | AI28: 314112.15 | AJ28: 395849.55 | AK28: 490394.5 | AL28: 563348.2 | AM28: 703052.5 | AN28: 860584.1 | AO28: 1045647.8 | AP28: 1465986.6 | AU28: 61-65 | AV28: 42991.875 | AW28: 52398 | AX28: 65187 | AY28: 73276.875 | AZ28: 79395.75 | BA28: 95895 | BB28: 105264 | BC28: 111963.38 | BD28: 125713.12 | BE28: 157010.62 | BF28: 278313.75 | BG28: 350696.25 | BH28: 434417.62 | BI28: 499295.25 | BJ28: 623008.12 | BK28: 762507 | BL28: 926385.75 | BM28: 1298608.9 | BR28: 61-65 | BS28: 39651.7 | BT28: 48319.7 | BU28: 60131.5 | BV28: 67584 | BW28: 73222.6 | BX28: 88452.1 | BY28: 97087.1 | BZ28: 103260.3 | CA28: 115931.2 | CB28: 144771 | CC28: 256555.2 | CD28: 323255.9 | CE28: 400407.7 | CF28: 460339 | CG28: 574343 | CH28: 702893.4 | CI28: 853911.3 | CJ28: 1196921 | CO28: 61-65 | CP28: 36495.38 | CQ28: 44466.55 | CR28: 55352.38 | CS28: 62204.12 | CT28: 67389.25 | CU28: 81418.64 | CV28: 89358.2 | CW28: 95034.92 | CX28: 106685.93 | CY28: 133205.63 | CZ28: 235993.72 | DA28: 297326.93 | DB28: 368269.58 | DC28: 423523.86 | DD28: 528353.52 | DE28: 646558.57 | DF28: 785423.48 | DG28: 1100830.2
A29: 41-45 | B29: 41 Years | C29: 45 Years | D29: 5 | E29: FLOATER | F29: 3 | G29: 1 | H29: 2 | I29: 1 | J29: Zone 1 | K29: =G29&"+"&H29 -> 1+2 | L29: =VLOOKUP(A29,'ZONE 1 PREMIUM'!$A$4:$N$16,14,0) -> 5 | M29: =VLOOKUP(D29,DROPDOWN!B:C,2,0) -> 4 | N29: =VLOOKUP(K29,$AQ$3:$AR$12,2,0) -> X35:AP46 | O29: =INDEX(INDIRECT(N29),L29,M29) -> 29431.95 | Q29: EXT OF GLOBAL COVERAGE | R29: =IF('CALCULATOR CARE V6'!C29=U34,'CARE SHEET'!V34,'CARE SHEET'!V35) -> 0.1 | S29: =IF('CALCULATOR CARE V6'!B29="YES",S32*'CARE SHEET'!R29,0) -> 0 | V29: AAHC | X29: 66-70 | Y29: 61397.35 | Z29: 74982.3 | AA29: 95891.6 | AB29: 104613.2 | AC29: 113522.25 | AD29: 136746.5 | AE29: 150382.05 | AF29: 162363.9 | AG29: 182611.95 | AH29: 228513.05 | AI29: 396721.25 | AJ29: 502570.7 | AK29: 625382.65 | AL29: 726580.35 | AM29: 908859.95 | AN29: 1114916.9 | AO29: 1357442.8 | AP29: 1907211.7 | AU29: 66-70 | AV29: 54432 | AW29: 66461.625 | AX29: 85027.5 | AY29: 92746.125 | AZ29: 100635.75 | BA29: 121249.12 | BB29: 133327.12 | BC29: 143938.12 | BD29: 161868.38 | BE29: 202514.62 | BF29: 351475.88 | BG29: 445208.62 | BH29: 553962.38 | BI29: 643801.5 | BJ29: 805215.38 | BK29: 987684.75 | BL29: 1202448.4 | BM29: 1689286.5 | BR29: 66-70 | BS29: 50193 | BT29: 61278.8 | BU29: 78413.5 | BV29: 85525 | BW29: 92796 | BX29: 111815 | BY29: 122947 | BZ29: 132724.9 | CA29: 149248 | CB29: 186705.2 | CC29: 323979.7 | CD29: 410357.2 | CE29: 510574.9 | CF29: 593481.9 | CG29: 742228.3 | CH29: 910376.5 | CI29: 1108286.3 | CJ29: 1556915.8 | CO29: 66-70 | CP29: 46186.57 | CQ29: 56380.25 | CR29: 72163.45 | CS29: 78700.18 | CT29: 85386.24 | CU29: 102900.36 | CV29: 113137.64 | CW29: 122129.05 | CX29: 137322.56 | CY29: 171765.47 | CZ29: 297996.19 | DA29: 377422.31 | DB29: 469575.27 | DC29: 545930.86 | DD29: 682706.24 | DE29: 837322.74 | DF29: 1019305.9 | DG29: 1431831.6
A30: 46-50 | B30: 46 Years | C30: 50 Years | D30: 5 | E30: FLOATER | F30: 3 | G30: 1 | H30: 2 | I30: 1 | J30: Zone 1 | K30: =G30&"+"&H30 -> 1+2 | L30: =VLOOKUP(A30,'ZONE 1 PREMIUM'!$A$4:$N$16,14,0) -> 6 | M30: =VLOOKUP(D30,DROPDOWN!B:C,2,0) -> 4 | N30: =VLOOKUP(K30,$AQ$3:$AR$12,2,0) -> X35:AP46 | O30: =INDEX(INDIRECT(N30),L30,M30) -> 36417.05 | Q30: TRAVEL PLUS | R30: =IF('CALCULATOR CARE V6'!B30="yes",'TRAVEL PLUS'!N14*S14*S15,0) -> 0 | V30: =IF('CALCULATOR CARE V6'!C25='optional benefits'!B93,'optional benefits'!C93,'optional benefits'!C94) -> 268.53197 | X30: 71-75 | Y30: 73238.9 | Z30: 89573.5 | AA30: 112788.55 | AB30: 123257 | AC30: 133919.8 | AD30: 161249.55 | AE30: 177534.7 | AF30: 191910.85 | AG30: 216127.55 | AH30: 270820.4 | AI30: 457637.9 | AJ30: 583213.3 | AK30: 729319.65 | AL30: 862299.9 | AM30: 1080508.9 | AN30: 1327733.6 | AO30: 1619209.2 | AP30: 2278725 | AU30: 71-75 | AV30: 64918.125 | AW30: 79383.375 | AX30: 99990 | AY30: 109256.62 | AZ30: 118699.88 | BA30: 142947 | BB30: 157371.75 | BC30: 170103.38 | BD30: 191548.12 | BE30: 239979.38 | BF30: 405419.62 | BG30: 516621.38 | BH30: 646002 | BI30: 763979.62 | BJ30: 957210.75 | BK30: 1176134.6 | BL30: 1434245.6 | BM30: 2018265.8 | BR30: 71-75 | BS30: 59857.6 | BT30: 73187.4 | BU30: 92202 | BV30: 100740.2 | BW30: 109441.2 | BX30: 131810.8 | BY30: 145105.4 | BZ30: 156836.9 | CA30: 176599.5 | CB30: 221229.8 | CC30: 373690.9 | CD30: 476164.7 | CE30: 595391.5 | CF30: 704225.5 | CG30: 882291.3 | CH30: 1084034.6 | CI30: 1321888.7 | CJ30: 1860074.7 | CO30: 71-75 | CP30: 55074.43 | CQ30: 67331.48 | CR30: 84842.33 | CS30: 92690.33 | CT30: 100692.02 | CU30: 121286.48 | CV30: 133513.01 | CW30: 144300.74 | CX30: 162472.13 | CY30: 203511.72 | CZ30: 343707.52 | DA30: 437934.75 | DB30: 547565.86 | DC30: 647758.66 | DD30: 811495.19 | DE30: 997003.38 | DF30: 1215715.2 | DG30: 1710591.5
A31: 51-55 | B31: 51 Years | C31: 55 Years | D31: 5 | E31: FLOATER | F31: 3 | G31: 1 | H31: 2 | I31: 1 | J31: Zone 1 | K31: =G31&"+"&H31 -> 1+2 | L31: =VLOOKUP(A31,'ZONE 1 PREMIUM'!$A$4:$N$16,14,0) -> 7 | M31: =VLOOKUP(D31,DROPDOWN!B:C,2,0) -> 4 | N31: =VLOOKUP(K31,$AQ$3:$AR$12,2,0) -> X35:AP46 | O31: =INDEX(INDIRECT(N31),L31,M31) -> 46790.05 | R31: =R11*S12*S13*S14*S15*S16*S17*S27+R18+R19+R20+R21+R22+R23+R24+R25+R26+S28+S29+R30+R32 -> 196386.14 | S31: =R11*S14*S15*S17*S27 -> 149487.64 | V31: =V30*'CALCULATOR CARE V6'!J10 -> 268.53197 | X31: 75+ | Y31: 97856.95 | Z31: 119855.3 | AA31: 152572.8 | AB31: 167082.35 | AC31: 181792 | AD31: 218673.65 | AE31: 241063 | AF31: 260923.5 | AG31: 294289.6 | AH31: 369338.6 | AI31: 606031.6 | AJ31: 777609.3 | AK31: 977864.55 | AL31: 1177658.6 | AM31: 1478545.8 | AN31: 1820271.7 | AO31: 2223910.2 | AP31: 3135399.1 | AU31: 75+ | AV31: 86720.625 | AW31: 106201.12 | AX31: 135223.88 | AY31: 148069.12 | AZ31: 161094.38 | BA31: 193803.75 | BB31: 213633 | BC31: 231220.12 | BD31: 260767.12 | BE31: 327225.38 | BF31: 536833.12 | BG31: 688770 | BH31: 866101.5 | BI31: 1043251.9 | BJ31: 1309696.9 | BK31: 1612305 | BL31: 1969738.9 | BM31: 2776889.2 | BR31: 75+ | BS31: 79949.1 | BT31: 97900 | BU31: 124672.9 | BV31: 136507.8 | BW31: 148511 | BX31: 178678.5 | BY31: 196953.9 | BZ31: 213161.3 | CA31: 240389.6 | CB31: 301632.1 | CC31: 494793.2 | CD31: 634805.6 | CE31: 798220.5 | CF31: 961587 | CG31: 1207121.3 | CH31: 1485980.1 | CI31: 1815361.9 | CJ31: 2559167.6 | CO31: 75+ | CP31: 73549.93 | CQ31: 90055.8 | CR31: 114701.79 | CS31: 125583.26 | CT31: 136619.51 | CU31: 164386.17 | CV31: 181192.88 | CW31: 196095.36 | CX31: 221131.57 | CY31: 277445.33 | CZ31: 455066.28 | DA31: 583812.72 | DB31: 734075.76 | DC31: 884416.19 | DD31: 1110191.2 | DE31: 1366609.3 | DF31: 1669484.3 | DG31: 2353431
A32: 56-60 | B32: 56 Years | C32: 60 Years | D32: 5 | E32: FLOATER | F32: 3 | G32: 1 | H32: 2 | I32: 1 | J32: Zone 1 | K32: =G32&"+"&H32 -> 1+2 | L32: =VLOOKUP(A32,'ZONE 1 PREMIUM'!$A$4:$N$16,14,0) -> 8 | M32: =VLOOKUP(D32,DROPDOWN!B:C,2,0) -> 4 | N32: =VLOOKUP(K32,$AQ$3:$AR$12,2,0) -> X35:AP46 | O32: =INDEX(INDIRECT(N32),L32,M32) -> 61353.65 | Q32: ADD SI | R32: =IF('CALCULATOR CARE V6'!B31="yes",'CARE SHEET'!V56*S27*S13*S15*S17,0) -> 0 | S32: =S31+S28 -> 149487.64
A33: 61-65 | B33: 61 Years | C33: 65 Years | D33: 5 | E33: FLOATER | F33: 3 | G33: 1 | H33: 2 | I33: 1 | J33: Zone 1 | K33: =G33&"+"&H33 -> 1+2 | L33: =VLOOKUP(A33,'ZONE 1 PREMIUM'!$A$4:$N$16,14,0) -> 9 | M33: =VLOOKUP(D33,DROPDOWN!B:C,2,0) -> 4 | N33: =VLOOKUP(K33,$AQ$3:$AR$12,2,0) -> X35:AP46 | O33: =INDEX(INDIRECT(N33),L33,M33) -> 78218.4 | V33: EXT | X33: 1A2C
A34: 66-70 | B34: 66 Years | C34: 70 Years | D34: 5 | E34: FLOATER | F34: 3 | G34: 1 | H34: 2 | I34: 1 | J34: Zone 1 | K34: =G34&"+"&H34 -> 1+2 | L34: =VLOOKUP(A34,'ZONE 1 PREMIUM'!$A$4:$N$16,14,0) -> 10 | M34: =VLOOKUP(D34,DROPDOWN!B:C,2,0) -> 4 | N34: =VLOOKUP(K34,$AQ$3:$AR$12,2,0) -> X35:AP46 | O34: =INDEX(INDIRECT(N34),L34,M34) -> 101466.8 | Q34: DA+ | R34: 1A | S34: 2 | T34: 3 | U34: EXCL US | V34: 0.05 | Y34: Care 3 | AA34: Care 4 | AD34: Care 5 | AI34: Care 6 | AL34: Care 7 | AT34: 1A2C | AV34: Care 3 | AX34: Care 4 | BA34: Care 5 | BF34: Care 6 | BI34: Care 7 | BQ34: 1A2C | BS34: Care 3 | BU34: Care 4 | BX34: Care 5 | CC34: Care 6 | CF34: Care 7 | CN34: 1A2C | CP34: Care 3 | CR34: Care 4 | CU34: Care 5 | CZ34: Care 6 | DC34: Care 7
A35: 71-75 | B35: 71 Years | C35: 75 Years | D35: 5 | E35: FLOATER | F35: 3 | G35: 1 | H35: 2 | I35: 1 | J35: Zone 1 | K35: =G35&"+"&H35 -> 1+2 | L35: =VLOOKUP(A35,'ZONE 1 PREMIUM'!$A$4:$N$16,14,0) -> 11 | M35: =VLOOKUP(D35,DROPDOWN!B:C,2,0) -> 4 | N35: =VLOOKUP(K35,$AQ$3:$AR$12,2,0) -> X35:AP46 | O35: =INDEX(INDIRECT(N35),L35,M35) -> 119402.2 | Q35: =VLOOKUP('CALCULATOR CARE V6'!H3,DROPDOWN!K:N,4,0) -> Upto 45 Years | R35: =IF('CALCULATOR CARE V6'!I3="YES",VLOOKUP(Q35,'optional benefits'!$E$114:$G$118,2,0)*$W$20,0) -> 378.66567 | S35: =IF('CALCULATOR CARE V6'!I3="YES",VLOOKUP(Q35,'optional benefits'!$I$114:$K$118,2,0)*$W$20,0) -> 361.45359 | T35: =IF('CALCULATOR CARE V6'!I3="YES",VLOOKUP(Q35,'optional benefits'!$M$114:$O$118,2,0)*$W$20,0) -> 344.24152 | U35: INCL US | V35: =HLOOKUP('CALCULATOR CARE V6'!B6,'optional benefits'!B110:F111,2,0) -> 0.1 | X35: Age-Band/ SI | Y35: 3L | Z35: 4L | AA35: 5L | AB35: 7L | AC35: 10L | AD35: 15L | AE35: 20L | AF35: 25L | AG35: 30L | AH35: 40L | AI35: 50L | AJ35: 60L | AK35: 75L | AL35: 1 CR | AM35: 1.5 CR | AN35: 2 CR | AO35: 3 CR | AP35: 6 CR | AU35: Age-Band/ SI | AV35: 3L | AW35: 4L | AX35: 5L | AY35: 7L | AZ35: 10L | BA35: 15L | BB35: 20L | BC35: 25L | BD35: 30L | BE35: 40L | BF35: 50L | BG35: 60L | BH35: 75L | BI35: 1 CR | BJ35: 1.5 CR | BK35: 2 CR | BL35: 3 CR | BM35: 6 CR | BR35: Age-Band/ SI | BS35: 3L | BT35: 4L | BU35: 5L | BV35: 7L | BW35: 10L | BX35: 15L | BY35: 20L | BZ35: 25L | CA35: 30L | CB35: 40L | CC35: 50L | CD35: 60L | CE35: 75L | CF35: 1 CR | CG35: 1.5 CR | CH35: 2 CR | CI35: 3 CR | CJ35: 6 CR | CO35: Age-Band/ SI | CP35: 3L | CQ35: 4L | CR35: 5L | CS35: 7L | CT35: 10L | CU35: 15L | CV35: 20L | CW35: 25L | CX35: 30L | CY35: 40L | CZ35: 50L | DA35: 60L | DB35: 75L | DC35: 1 CR | DD35: 1.5 CR | DE35: 2 CR | DF35: 3 CR | DG35: 6 CR
A36: 75+ | B36: >75 Years | D36: 5 | E36: FLOATER | F36: 3 | G36: 1 | H36: 2 | I36: 1 | J36: Zone 1 | K36: =G36&"+"&H36 -> 1+2 | L36: =VLOOKUP(A36,'ZONE 1 PREMIUM'!$A$4:$N$16,14,0) -> 12 | M36: =VLOOKUP(D36,DROPDOWN!B:C,2,0) -> 4 | N36: =VLOOKUP(K36,$AQ$3:$AR$12,2,0) -> X35:AP46 | O36: =INDEX(INDIRECT(N36),L36,M36) -> 155360.4 | Q36: =VLOOKUP('CALCULATOR CARE V6'!H4,DROPDOWN!K:N,4,0) -> Upto 45 Years | R36: =IF('CALCULATOR CARE V6'!I4="YES",VLOOKUP(Q36,'optional benefits'!$E$114:$G$118,2,0)*$W$20,0) -> 0 | S36: =IF('CALCULATOR CARE V6'!I4="YES",VLOOKUP(Q36,'optional benefits'!$I$114:$K$118,2,0)*$W$20,0) -> 0 | T36: =IF('CALCULATOR CARE V6'!I4="YES",VLOOKUP(Q36,'optional benefits'!$M$114:$O$118,2,0)*$W$20,0) -> 0 | X36: 18-24 | Y36: 14478.5 | Z36: 17558.2 | AA36: 21185.3 | AB36: 23100.05 | AC36: 24856.1 | AD36: 31535.3 | AE36: 34524.15 | AF36: 37113.95 | AG36: 41389.65 | AH36: 51360.15 | AI36: 94318.4 | AJ36: 115729.1 | AK36: 139752.6 | AL36: 200990.1 | AM36: 239764.65 | AN36: 282519.35 | AO36: 332002.7 | AP36: 445818.2 | AU36: 18-24 | AV36: 12853.125 | AW36: 15579 | AX36: 18806.625 | AY36: 20502 | AZ36: 22056.75 | BA36: 27985.5 | BB36: 30632.625 | BC36: 32926.5 | BD36: 36712.125 | BE36: 45541.125 | BF36: 83581.875 | BG36: 102541.5 | BH36: 123815.25 | BI36: 178906.5 | BJ36: 213242.62 | BK36: 251103.38 | BL36: 294922.12 | BM36: 395708.62 | BR36: 18-24 | BS36: 11860.2 | BT36: 14373.7 | BU36: 17354.7 | BV36: 18916.7 | BW36: 20350 | BX36: 25821.4 | BY36: 28261.2 | BZ36: 30374.3 | CA36: 33862.4 | CB36: 41999.1 | CC36: 77053.9 | CD36: 94526.3 | CE36: 114130.5 | CF36: 165352 | CG36: 196993.5 | CH36: 231883.3 | CI36: 272262.1 | CJ36: 365139.5 | CO36: 18-24 | CP36: 10922.89 | CQ36: 13233.69 | CR36: 15982.67 | CS36: 17419.29 | CT36: 18737.1 | CU36: 23775.08 | CV36: 26018.3 | CW36: 27961.77 | CX36: 31169.64 | CY36: 38651.4 | CZ36: 70885.97 | DA36: 86951.48 | DB36: 104977.9 | DC36: 152537.87 | DD36: 181632.15 | DE36: 213714.12 | DF36: 250843.88 | DG36: 336247.56
A37: 18-24 | B37: 18 Years | C37: 24 Years | D37: 5 | E37: FLOATER | F37: 4 | G37: 1 | H37: 3 | I37: 1 | J37: Zone 1 | K37: =G37&"+"&H37 -> 1+3 | L37: =VLOOKUP(A37,'ZONE 1 PREMIUM'!$A$4:$N$16,14,0) -> 2 | M37: =VLOOKUP(D37,DROPDOWN!B:C,2,0) -> 4 | N37: =VLOOKUP(K37,$AQ$3:$AR$12,2,0) -> X50:AP61 | O37: =INDEX(INDIRECT(N37),L37,M37) -> 25953.2 | Q37: =VLOOKUP('CALCULATOR CARE V6'!H5,DROPDOWN!K:N,4,0) -> Upto 45 Years | R37: =IF('CALCULATOR CARE V6'!I5="YES",VLOOKUP(Q37,'optional benefits'!$E$114:$G$118,2,0)*$W$20,0) -> 0 | S37: =IF('CALCULATOR CARE V6'!I5="YES",VLOOKUP(Q37,'optional benefits'!$I$114:$K$118,2,0)*$W$20,0) -> 0 | T37: =IF('CALCULATOR CARE V6'!I5="YES",VLOOKUP(Q37,'optional benefits'!$M$114:$O$118,2,0)*$W$20,0) -> 0 | X37: 25-35 | Y37: 15631.95 | Z37: 18756.5 | AA37: 22760.8 | AB37: 24820.45 | AC37: 26712.2 | AD37: 33897.4 | AE37: 37002.4 | AF37: 39693.4 | AG37: 44268.1 | AH37: 54912.5 | AI37: 101385.15 | AJ37: 124993.5 | AK37: 151826.45 | AL37: 213592.95 | AM37: 255708.25 | AN37: 302268.3 | AO37: 356245.85 | AP37: 480241.15 | AU37: 25-35 | AV37: 13881.375 | AW37: 16647.75 | AX37: 20214 | AY37: 22037.625 | AZ37: 23712.75 | BA37: 30096 | BB37: 32846.625 | BC37: 35229.375 | BD37: 39279.375 | BE37: 48705.75 | BF37: 89859.375 | BG37: 110765.25 | BH37: 134526.38 | BI37: 190069.88 | BJ37: 227363.62 | BK37: 268593.75 | BL37: 316392.75 | BM37: 426195 | BR37: 25-35 | BS37: 12811.7 | BT37: 15361.5 | BU37: 18659.3 | BV37: 20339 | BW37: 21883.4 | BX37: 27776.1 | BY37: 30310.5 | BZ37: 32506.1 | CA37: 36238.4 | CB37: 44925.1 | CC37: 82848.7 | CD37: 102113 | CE37: 124010.7 | CF37: 175640.3 | CG37: 210007.6 | CH37: 248002.7 | CI37: 292050 | CJ37: 393234.6 | CO37: 25-35 | CP37: 11801.43 | CQ37: 14146.02 | CR37: 17189.3 | CS37: 18733.83 | CT37: 20153.01 | CU37: 25582.3 | CV37: 27912.72 | CW37: 29932.49 | CX37: 33364.9 | CY37: 41352.42 | CZ37: 76223.7 | DA37: 93938.38 | DB37: 114072.86 | DC37: 161999.07 | DD37: 193601.44 | DE37: 228538.12 | DF37: 269040.34 | DG37: 362082.74
A38: 25-35 | B38: 25 Years | C38: 35 Years | D38: 5 | E38: FLOATER | F38: 4 | G38: 1 | H38: 3 | I38: 1 | J38: Zone 1 | K38: =G38&"+"&H38 -> 1+3 | L38: =VLOOKUP(A38,'ZONE 1 PREMIUM'!$A$4:$N$16,14,0) -> 3 | M38: =VLOOKUP(D38,DROPDOWN!B:C,2,0) -> 4 | N38: =VLOOKUP(K38,$AQ$3:$AR$12,2,0) -> X50:AP61 | O38: =INDEX(INDIRECT(N38),L38,M38) -> 27442.45 | Q38: =VLOOKUP('CALCULATOR CARE V6'!H6,DROPDOWN!K:N,4,0) -> Upto 45 Years | R38: =IF('CALCULATOR CARE V6'!I6="YES",VLOOKUP(Q38,'optional benefits'!$E$114:$G$118,2,0)*$W$20,0) -> 0 | S38: =IF('CALCULATOR CARE V6'!I6="YES",VLOOKUP(Q38,'optional benefits'!$I$114:$K$118,2,0)*$W$20,0) -> 0 | T38: =IF('CALCULATOR CARE V6'!I6="YES",VLOOKUP(Q38,'optional benefits'!$M$114:$O$118,2,0)*$W$20,0) -> 0 | X38: 36-40 | Y38: 17815.8 | Z38: 21494.65 | AA38: 26272.9 | AB38: 28676.4 | AC38: 30890.15 | AD38: 39236.85 | AE38: 42908.8 | AF38: 46105.8 | AG38: 51467.1 | AH38: 63905.5 | AI38: 109873.3 | AJ38: 137497.45 | AK38: 168949.95 | AL38: 229426.15 | AM38: 278373.6 | AN38: 332703.05 | AO38: 395840.35 | AP38: 540652.95 | AU38: 36-40 | AV38: 15815.25 | AW38: 19073.25 | AX38: 23328 | AY38: 25456.5 | AZ38: 27416.25 | BA38: 34831.125 | BB38: 38082.375 | BC38: 40912.875 | BD38: 45660.375 | BE38: 56675.25 | BF38: 97382.25 | BG38: 121843.12 | BH38: 149695.88 | BI38: 203893.88 | BJ38: 247239 | BK38: 295348.5 | BL38: 351258.75 | BM38: 479495.25 | BR38: 36-40 | BS38: 14594.8 | BT38: 17596.7 | BU38: 21529.2 | BV38: 23491.6 | BW38: 25297.8 | BX38: 32142 | BY38: 35138.4 | BZ38: 37747.6 | CA38: 42122.3 | CB38: 52272 | CC38: 89784.2 | CD38: 112325.4 | CE38: 137992.8 | CF38: 188276 | CG38: 228219.2 | CH38: 272553.6 | CI38: 324076.5 | CJ38: 442248.4 | CO38: 36-40 | CP38: 13441.88 | CQ38: 16201.76 | CR38: 19830.37 | CS38: 21634.32 | CT38: 23295.48 | CU38: 29601.13 | CV38: 32356.65 | CW38: 34754.65 | CX38: 38777.84 | CY38: 48111.51 | CZ38: 82604.56 | DA38: 103332 | DB38: 126932.68 | DC38: 173513.83 | DD38: 210242.47 | DE38: 251008.47 | DF38: 298385.32 | DG38: 407047.42
A39: 36-40 | B39: 36 Years | C39: 40 Years | D39: 5 | E39: FLOATER | F39: 4 | G39: 1 | H39: 3 | I39: 1 | J39: Zone 1 | K39: =G39&"+"&H39 -> 1+3 | L39: =VLOOKUP(A39,'ZONE 1 PREMIUM'!$A$4:$N$16,14,0) -> 4 | M39: =VLOOKUP(D39,DROPDOWN!B:C,2,0) -> 4 | N39: =VLOOKUP(K39,$AQ$3:$AR$12,2,0) -> X50:AP61 | O39: =INDEX(INDIRECT(N39),L39,M39) -> 31692.85 | Q39: =VLOOKUP('CALCULATOR CARE V6'!H7,DROPDOWN!K:N,4,0) -> Upto 45 Years | R39: =IF('CALCULATOR CARE V6'!I7="YES",VLOOKUP(Q39,'optional benefits'!$E$114:$G$118,2,0)*$W$20,0) -> 0 | S39: =IF('CALCULATOR CARE V6'!I7="YES",VLOOKUP(Q39,'optional benefits'!$I$114:$K$118,2,0)*$W$20,0) -> 0 | T39: =IF('CALCULATOR CARE V6'!I7="YES",VLOOKUP(Q39,'optional benefits'!$M$114:$O$118,2,0)*$W$20,0) -> 0 | X39: 41-45 | Y39: 19777.7 | Z39: 23952.2 | AA39: 29431.95 | AB39: 32157.45 | AC39: 34671.35 | AD39: 44049.6 | AE39: 48152.8 | AF39: 51698.25 | AG39: 57763.35 | AH39: 71794.5 | AI39: 121720.6 | AJ39: 153109.85 | AK39: 188917.4 | AL39: 244074.85 | AM39: 299127.65 | AN39: 360436.45 | AO39: 431836.5 | AP39: 595345.8 | AU39: 41-45 | AV39: 17553.375 | AW39: 21250.125 | AX39: 26128.125 | AY39: 28541.25 | AZ39: 30767.625 | BA39: 39097.125 | BB39: 42729.75 | BC39: 45870.75 | BD39: 51241.5 | BE39: 63664.875 | BF39: 107876.25 | BG39: 135672.75 | BH39: 167382 | BI39: 216636.75 | BJ39: 265388.62 | BK39: 319678.88 | BL39: 382906.12 | BM39: 527698.12 | BR39: 41-45 | BS39: 16197.5 | BT39: 19603.1 | BU39: 24112 | BV39: 26335.1 | BW39: 28386.6 | BX39: 36075.6 | BY39: 39424 | BZ39: 42318.1 | CA39: 47267 | CB39: 58715.8 | CC39: 99457.6 | CD39: 125072.2 | CE39: 154292.6 | CF39: 199899.7 | CG39: 244824.8 | CH39: 294855 | CI39: 353119.8 | CJ39: 486548.7 | CO39: 41-45 | CP39: 14915.56 | CQ39: 18047.13 | CR39: 22205.48 | CS39: 24250.32 | CT39: 26137.11 | CU39: 33219.93 | CV39: 36299.18 | CW39: 38959.87 | CX39: 43510.62 | CY39: 54038.93 | CZ39: 91501.14 | DA39: 115054.95 | DB39: 141923.45 | DC39: 184080.29 | DD39: 225390.2 | DE39: 271393.65 | DF39: 324970.42 | DG39: 447660.82
A40: 41-45 | B40: 41 Years | C40: 45 Years | D40: 5 | E40: FLOATER | F40: 4 | G40: 1 | H40: 3 | I40: 1 | J40: Zone 1 | K40: =G40&"+"&H40 -> 1+3 | L40: =VLOOKUP(A40,'ZONE 1 PREMIUM'!$A$4:$N$16,14,0) -> 5 | M40: =VLOOKUP(D40,DROPDOWN!B:C,2,0) -> 4 | N40: =VLOOKUP(K40,$AQ$3:$AR$12,2,0) -> X50:AP61 | O40: =INDEX(INDIRECT(N40),L40,M40) -> 35195.75 | Q40: =VLOOKUP('CALCULATOR CARE V6'!H8,DROPDOWN!K:N,4,0) -> Upto 45 Years | R40: =IF('CALCULATOR CARE V6'!I8="YES",VLOOKUP(Q40,'optional benefits'!$E$114:$G$118,2,0)*$W$20,0) -> 0 | S40: =IF('CALCULATOR CARE V6'!I8="YES",VLOOKUP(Q40,'optional benefits'!$I$114:$K$118,2,0)*$W$20,0) -> 0 | T40: =IF('CALCULATOR CARE V6'!I8="YES",VLOOKUP(Q40,'optional benefits'!$M$114:$O$118,2,0)*$W$20,0) -> 0 | X40: 46-50 | Y40: 24262.7 | Z40: 29466.45 | AA40: 36417.05 | AB40: 41571.35 | AC40: 44862.65 | AD40: 55080.4 | AE40: 60288.75 | AF40: 64814 | AG40: 72474.15 | AH40: 90141.6 | AI40: 149839.25 | AJ40: 189715.5 | AK40: 235315.3 | AL40: 288976.6 | AM40: 357863.9 | AN40: 434840.3 | AO40: 524680.6 | AP40: 730085.55 | AU40: 46-50 | AV40: 21533.625 | AW40: 26141.625 | AX40: 32329.125 | AY40: 36893.25 | AZ40: 39808.125 | BA40: 48889.125 | BB40: 53501.625 | BC40: 57507.75 | BD40: 64291.5 | BE40: 79935.75 | BF40: 132800.62 | BG40: 168112.12 | BH40: 208492.88 | BI40: 256306.5 | BJ40: 317308.5 | BK40: 385472.25 | BL40: 465028.88 | BM40: 646921.12 | BR40: 46-50 | BS40: 19869.3 | BT40: 24115.3 | BU40: 29834.2 | BV40: 34040.6 | BW40: 36726.8 | BX40: 45112.1 | BY40: 49362.5 | BZ40: 53054.1 | CA40: 59305.4 | CB40: 73722 | CC40: 122438.8 | CD40: 154977.9 | CE40: 192189.8 | CF40: 236406.5 | CG40: 292620.9 | CH40: 355435.3 | CI40: 428748.1 | CJ40: 596365 | CO40: 46-50 | CP40: 18295.65 | CQ40: 22200.03 | CR40: 27476.72 | CS40: 31344.04 | CT40: 33813.98 | CU40: 41542.08 | CV40: 45449.73 | CW40: 48845.08 | CX40: 54593.74 | CY40: 67850.32 | CZ40: 112646.05 | DA40: 142566.55 | DB40: 176783.83 | DC40: 217598.88 | DD40: 269289.95 | DE40: 327049.05 | DF40: 394461.19 | DG40: 548589.37
A41: 46-50 | B41: 46 Years | C41: 50 Years | D41: 5 | E41: FLOATER | F41: 4 | G41: 1 | H41: 3 | I41: 1 | J41: Zone 1 | K41: =G41&"+"&H41 -> 1+3 | L41: =VLOOKUP(A41,'ZONE 1 PREMIUM'!$A$4:$N$16,14,0) -> 6 | M41: =VLOOKUP(D41,DROPDOWN!B:C,2,0) -> 4 | N41: =VLOOKUP(K41,$AQ$3:$AR$12,2,0) -> X50:AP61 | O41: =INDEX(INDIRECT(N41),L41,M41) -> 42877.75 | R41: =R35+SUM(R36:R40)*95% -> 378.66567 | S41: =S35+SUM(S36:S40)*95% -> 361.45359 | T41: =T35+SUM(T36:T40)*95% -> 344.24152 | V41: =HLOOKUP(R8,R43:U44,2,0) -> 344.24152 | X41: 51-55 | Y41: 31017.8 | Z41: 37791.3 | AA41: 46790.05 | AB41: 53535.95 | AC41: 57835.8 | AD41: 70949.25 | AE41: 77790.6 | AF41: 83761.4 | AG41: 93766.4 | AH41: 116775.6 | AI41: 201108.55 | AJ41: 253445.05 | AK41: 313398 | AL41: 375009.25 | AM41: 465394.65 | AN41: 566572.8 | AO41: 684816.95 | AP41: 954782.9 | AU41: 51-55 | AV41: 27517.5 | AW41: 33514.875 | AX41: 41519.25 | AY41: 47494.125 | AZ41: 51301.125 | BA41: 62950.5 | BB41: 69008.625 | BC41: 74296.125 | BD41: 83154.375 | BE41: 103530.38 | BF41: 178210.12 | BG41: 224555.62 | BH41: 277645.5 | BI41: 332463.38 | BJ41: 412502.62 | BK41: 502098.75 | BL41: 606807 | BM41: 845870.62 | BR41: 51-55 | BS41: 25383.6 | BT41: 30910 | BU41: 38306.4 | BV41: 43811.9 | BW41: 47319.8 | BX41: 58074.5 | BY41: 63657 | BZ41: 68528.9 | CA41: 76693.1 | CB41: 95470.1 | CC41: 164288.3 | CD41: 206996.9 | CE41: 255920.5 | CF41: 306572.2 | CG41: 380329.4 | CH41: 462894.3 | CI41: 559385.2 | CJ41: 779686.6 | CO41: 51-55 | CP41: 23367.42 | CQ41: 28449 | CR41: 35269.13 | CS41: 40331.09 | CT41: 43557.49 | CU41: 53465.59 | CV41: 58599.49 | CW41: 63079.39 | CX41: 70586.22 | CY41: 87851.82 | CZ41: 151132.86 | DA41: 190403.38 | DB41: 235389.86 | DC41: 282103.99 | DD41: 349925.97 | DE41: 425845.56 | DF41: 514571.56 | DG41: 717144.79
A42: 51-55 | B42: 51 Years | C42: 55 Years | D42: 5 | E42: FLOATER | F42: 4 | G42: 1 | H42: 3 | I42: 1 | J42: Zone 1 | K42: =G42&"+"&H42 -> 1+3 | L42: =VLOOKUP(A42,'ZONE 1 PREMIUM'!$A$4:$N$16,14,0) -> 7 | M42: =VLOOKUP(D42,DROPDOWN!B:C,2,0) -> 4 | N42: =VLOOKUP(K42,$AQ$3:$AR$12,2,0) -> X50:AP61 | O42: =INDEX(INDIRECT(N42),L42,M42) -> 53976.4 | X42: 56-60 | Y42: 40531.75 | Z42: 49422.4 | AA42: 61353.65 | AB42: 68665.35 | AC42: 74255.5 | AD42: 91494 | AE42: 100390.4 | AF42: 107266.25 | AG42: 120201.45 | AH42: 149843.85 | AI42: 259369.85 | AJ42: 327053.1 | AK42: 404832.2 | AL42: 480230.8 | AM42: 597119.1 | AN42: 728282.35 | AO42: 881840.7 | AP42: 1231790.3 | AU42: 56-60 | AV42: 35952.75 | AW42: 43825.5 | AX42: 54437.625 | AY42: 60912 | AZ42: 65863.125 | BA42: 81174.375 | BB42: 89052.75 | BC42: 95141.25 | BD42: 106596 | BE42: 132845.62 | BF42: 229833 | BG42: 289769.62 | BH42: 358644.38 | BI42: 425687.62 | BJ42: 529195.5 | BK42: 645343.88 | BL42: 781323.75 | BM42: 1091215.1 | BR42: 56-60 | BS42: 33162.8 | BT42: 40418.4 | BU42: 50222.7 | BV42: 56188 | BW42: 60749.7 | BX42: 74884.7 | BY42: 82144.7 | BZ42: 87755.8 | CA42: 98311.4 | CB42: 122500.4 | CC42: 211876.5 | CD42: 267108.6 | CE42: 330578.6 | CF42: 392504.2 | CG42: 487888.5 | CH42: 594921.8 | CI42: 720230.5 | CJ42: 1005801.5 | CO42: 56-60 | CP42: 30526.54 | CQ42: 37198.43 | CR42: 46237.8 | CS42: 51723.77 | CT42: 55918.09 | CU42: 68940.32 | CV42: 75615.48 | CW42: 80775.54 | CX42: 90481.99 | CY42: 112724.53 | CZ42: 194908.35 | DA42: 245694.72 | DB42: 304057.68 | DC42: 361145.34 | DD42: 448854.37 | DE42: 547273.74 | DF42: 662497.64 | DG42: 925087.36
A43: 56-60 | B43: 56 Years | C43: 60 Years | D43: 5 | E43: FLOATER | F43: 4 | G43: 1 | H43: 3 | I43: 1 | J43: Zone 1 | K43: =G43&"+"&H43 -> 1+3 | L43: =VLOOKUP(A43,'ZONE 1 PREMIUM'!$A$4:$N$16,14,0) -> 8 | M43: =VLOOKUP(D43,DROPDOWN!B:C,2,0) -> 4 | N43: =VLOOKUP(K43,$AQ$3:$AR$12,2,0) -> X50:AP61 | O43: =INDEX(INDIRECT(N43),L43,M43) -> 67707.4 | R43: ZONE 1 | S43: ZONE 1A | T43: ZONE 2 | U43: ZONE 3 | X43: 61-65 | Y43: 51540.7 | Z43: 62918.8 | AA43: 78218.4 | AB43: 90211.75 | AC43: 97706.3 | AD43: 118809.95 | AE43: 130500.85 | AF43: 139082.15 | AG43: 156107.9 | AH43: 194959.5 | AI43: 339182.15 | AJ43: 428257.7 | AK43: 530988.35 | AL43: 623650.75 | AM43: 777355.15 | AN43: 950324.35 | AO43: 1153247.6 | AP43: 1614723 | AU43: 61-65 | AV43: 45700.875 | AW43: 55777.5 | AX43: 69372 | AY43: 79993.125 | AZ43: 86629.5 | BA43: 105364.12 | BB43: 115716.38 | BC43: 123315.75 | BD43: 138393 | BE43: 172796.62 | BF43: 300511.12 | BG43: 379390.5 | BH43: 470360.25 | BI43: 552684.38 | BJ43: 688794.75 | BK43: 841964.62 | BL43: 1021658.6 | BM43: 1430309.2 | BR43: 61-65 | BS43: 42146.5 | BT43: 51431.6 | BU43: 63984.8 | BV43: 73771.5 | BW43: 79887.5 | BX43: 97176.2 | BY43: 106716.5 | BZ43: 113719.1 | CA43: 127613.2 | CB43: 159317.4 | CC43: 277007.5 | CD43: 349696.6 | CE43: 433527.6 | CF43: 509532.1 | CG43: 634960.7 | CH43: 776109.4 | CI43: 941701.2 | CJ43: 1318279.6 | CO43: 61-65 | CP43: 38787.65 | CQ43: 47325.62 | CR43: 58892.7 | CS43: 67891.74 | CT43: 73516.14 | CU43: 89438.86 | CV43: 98211.18 | CW43: 104649.81 | CX43: 117425.7 | CY43: 146578.84 | CZ43: 254798.4 | DA43: 321637.2 | DB43: 398722 | DC43: 468753.41 | DD43: 584087.4 | DE43: 713876.97 | DF43: 866143.43 | DG43: 1212416.8
A44: 61-65 | B44: 61 Years | C44: 65 Years | D44: 5 | E44: FLOATER | F44: 4 | G44: 1 | H44: 3 | I44: 1 | J44: Zone 1 | K44: =G44&"+"&H44 -> 1+3 | L44: =VLOOKUP(A44,'ZONE 1 PREMIUM'!$A$4:$N$16,14,0) -> 9 | M44: =VLOOKUP(D44,DROPDOWN!B:C,2,0) -> 4 | N44: =VLOOKUP(K44,$AQ$3:$AR$12,2,0) -> X50:AP61 | O44: =INDEX(INDIRECT(N44),L44,M44) -> 85261 | R44: =V28 -> 413.08982 | S44: =R41 -> 378.66567 | T44: =S41 -> 361.45359 | U44: =T41 -> 344.24152 | X44: 66-70 | Y44: 66654 | Z44: 81485.55 | AA44: 101466.8 | AB44: 113992.6 | AC44: 123634.2 | AD44: 149817.4 | AE44: 164801.9 | AF44: 177971.7 | AG44: 200056.3 | AH44: 250238.85 | AI44: 428341.65 | AJ44: 543283 | AK44: 676298.9 | AL44: 799590.4 | AM44: 998980.85 | AN44: 1223969.1 | AO44: 1488448.4 | AP44: 2088674.8 | AU44: 66-70 | AV44: 59085 | AW44: 72219.375 | AX44: 89960.625 | AY44: 101052 | AZ44: 109590.75 | BA44: 132822 | BB44: 146095.88 | BC44: 157757.62 | BD44: 177314.62 | BE44: 221753.25 | BF44: 379476 | BG44: 481260.38 | BH44: 599049 | BI44: 708451.88 | BJ44: 885018.38 | BK44: 1084252.5 | BL44: 1318456.1 | BM44: 1849974.8 | BR44: 66-70 | BS44: 54480.8 | BT44: 66584.1 | BU44: 82957.6 | BV44: 93178.8 | BW44: 101047.1 | BX44: 122479.5 | BY44: 134713.7 | BZ44: 145459.6 | CA44: 163482 | CB44: 204432.8 | CC44: 349782.4 | CD44: 443578.3 | CE44: 552123 | CF44: 653057.9 | CG44: 815766.6 | CH44: 999364.3 | CI44: 1215188.7 | CJ44: 1704992.3 | CO44: 66-70 | CP44: 50129.1 | CQ44: 61258 | CR44: 76339.24 | CS44: 85738.31 | CT44: 92972.64 | CU44: 112706 | CV44: 123956.98 | CW44: 133838.92 | CX44: 150410.19 | CY44: 188066.42 | CZ44: 321722.22 | DA44: 407969.56 | DB44: 507779.77 | DC44: 600710.99 | DD44: 750325.48 | DE44: 919149.04 | DF44: 1117604.2 | DG44: 1567991.2
A45: 66-70 | B45: 66 Years | C45: 70 Years | D45: 5 | E45: FLOATER | F45: 4 | G45: 1 | H45: 3 | I45: 1 | J45: Zone 1 | K45: =G45&"+"&H45 -> 1+3 | L45: =VLOOKUP(A45,'ZONE 1 PREMIUM'!$A$4:$N$16,14,0) -> 10 | M45: =VLOOKUP(D45,DROPDOWN!B:C,2,0) -> 4 | N45: =VLOOKUP(K45,$AQ$3:$AR$12,2,0) -> X50:AP61 | O45: =INDEX(INDIRECT(N45),L45,M45) -> 107102.95 | V45: senior | X45: 71-75 | Y45: 78194.25 | Z45: 95711.05 | AA45: 119402.2 | AB45: 134400.5 | AC45: 145944.2 | AD45: 176645.75 | AE45: 194517.9 | AF45: 210290.15 | AG45: 236688.4 | AH45: 296445.85 | AI45: 495725.9 | AJ45: 632171.1 | AK45: 790538.75 | AL45: 947874.85 | AM45: 1186329.6 | AN45: 1456021.9 | AO45: 1773609.3 | AP45: 2493013.7 | AU45: 71-75 | AV45: 69305.625 | AW45: 84817.125 | AX45: 105844.5 | AY45: 119125.12 | AZ45: 129348 | BA45: 156582 | BB45: 172413 | BC45: 186379.88 | BD45: 209756.25 | BE45: 262672.88 | BF45: 439149.38 | BG45: 559975.5 | BH45: 700214.62 | BI45: 839761.88 | BJ45: 1050919.9 | BK45: 1289741.6 | BL45: 1570973.6 | BM45: 2208028.5 | BR45: 71-75 | BS45: 63899 | BT45: 78193.5 | BU45: 97595.3 | BV45: 109833.9 | BW45: 119254.3 | BX45: 144377.2 | BY45: 158966.5 | BZ45: 171837.6 | CA45: 193378.9 | CB45: 242143 | CC45: 404773.6 | CD45: 516116.7 | CE45: 645350.2 | CF45: 774062.3 | CG45: 968649 | CH45: 1188727.1 | CI45: 1447888.2 | CJ45: 2034946.1 | CO45: 71-75 | CP45: 58790.24 | CQ45: 71934.55 | CR45: 89799.65 | CS45: 101053.9 | CT45: 109716.13 | CU45: 132841.57 | CV45: 146259.47 | CW45: 158094.69 | CX45: 177903.26 | CY45: 222742.59 | CZ45: 372289.5 | DA45: 474673.2 | DB45: 593506.09 | DC45: 711977.1 | DD45: 890903.87 | DE45: 1093271.1 | DF45: 1331576.7 | DG45: 1871391.6
A46: 71-75 | B46: 71 Years | C46: 75 Years | D46: 5 | E46: FLOATER | F46: 4 | G46: 1 | H46: 3 | I46: 1 | J46: Zone 1 | K46: =G46&"+"&H46 -> 1+3 | L46: =VLOOKUP(A46,'ZONE 1 PREMIUM'!$A$4:$N$16,14,0) -> 11 | M46: =VLOOKUP(D46,DROPDOWN!B:C,2,0) -> 4 | N46: =VLOOKUP(K46,$AQ$3:$AR$12,2,0) -> X50:AP61 | O46: =INDEX(INDIRECT(N46),L46,M46) -> 124758.9 | R46: 1A | S46: 2 | T46: 3 | U46: 1 | V46: 1A | W46: 2 | X46: 75+ | Y46: 101472.55 | Z46: 124350.65 | AA46: 155360.4 | AB46: 175311.75 | AC46: 190647 | AD46: 230269.1 | AE46: 253856.75 | AF46: 274769.5 | AG46: 309738.7 | AH46: 388550.5 | AI46: 633439.55 | AJ46: 812895.9 | AK46: 1021919.9 | AL46: 1242840.6 | AM46: 1558758.3 | AN46: 1917027 | AO46: 2339777.3 | AP46: 3295352.6 | AU46: 75+ | AV46: 89920.125 | AW46: 110179.12 | AX46: 137687.62 | AY46: 155355.75 | AZ46: 168934.5 | BA46: 204069.38 | BB46: 224960.62 | BC46: 243480.38 | BD46: 274446 | BE46: 344236.5 | BF46: 561100.5 | BG46: 720014.62 | BH46: 905112 | BI46: 1100967.8 | BJ46: 1380721.5 | BK46: 1697979.4 | BL46: 2072337.8 | BM46: 2918527.9 | BR46: 75+ | BS46: 82897.1 | BT46: 101565.2 | BU46: 126940 | BV46: 143222.2 | BW46: 155734.7 | BX46: 188137.4 | BY46: 207391.8 | BZ46: 224457.2 | CA46: 252993.4 | CB46: 317306 | CC46: 517155.1 | CD46: 663598.1 | CE46: 834167.4 | CF46: 1014769.8 | CG46: 1272569.1 | CH46: 1564928.2 | CI46: 1909906.9 | CJ46: 2689687 | CO46: 75+ | CP46: 76258.58 | CQ46: 93426.08 | CR46: 116783.69 | CS46: 131754.84 | CT46: 143261.97 | CU46: 173082.19 | CV46: 190789.24 | CW46: 206480.88 | CX46: 232720.45 | CY46: 291857.31 | CZ46: 475628.04 | DA46: 610285.55 | DB46: 767128.92 | DC46: 933316.86 | DD46: 1170370.1 | DE46: 1439201.1 | DF46: 1756417.3 | DG46: 2473444.4
A47: 75+ | B47: >75 Years | D47: 5 | E47: FLOATER | F47: 4 | G47: 1 | H47: 3 | I47: 1 | J47: Zone 1 | K47: =G47&"+"&H47 -> 1+3 | L47: =VLOOKUP(A47,'ZONE 1 PREMIUM'!$A$4:$N$16,14,0) -> 12 | M47: =VLOOKUP(D47,DROPDOWN!B:C,2,0) -> 4 | N47: =VLOOKUP(K47,$AQ$3:$AR$12,2,0) -> X50:AP61 | O47: =INDEX(INDIRECT(N47),L47,M47) -> 161042.55 | Q47: =VLOOKUP('CALCULATOR CARE V6'!H3,DROPDOWN!K:N,4,0) -> Upto 45 Years | R47: =IF('CALCULATOR CARE V6'!I3="yes",INDEX('ADD SI'!$B$33:$Q$37,MATCH('CARE SHEET'!Q47,'ADD SI'!$B$33:$B$37,0),MATCH('CARE SHEET'!$T$3,'ADD SI'!$B$33:$Q$33,0)),0) -> #N/A | S47: =IF('CALCULATOR CARE V6'!I3="yes",INDEX('ADD SI'!$B$21:$AB$25,MATCH('CARE SHEET'!Q47,'ADD SI'!$B$21:$B$25,0),MATCH('CARE SHEET'!$T$3,'ADD SI'!$B$21:$Q$21,0)),0) -> #N/A | T47: =IF('CALCULATOR CARE V6'!I3="yes",INDEX('ADD SI'!$B$9:$AB$13,MATCH('CARE SHEET'!Q47,'ADD SI'!$B$9:$B$13,0),MATCH('CARE SHEET'!$T$3,'ADD SI'!$B$9:$Q$9,0)),0) -> #N/A | U47: =IF('CALCULATOR CARE V6'!I3="yes",INDEX('ADD SI'!$W$45:$AB$49,MATCH('CARE SHEET'!Q47,'ADD SI'!$W$45:$W$49,0),MATCH('CARE SHEET'!$T$3,'ADD SI'!$W$45:$AB$45,0)),0) -> #N/A | V47: =IF('CALCULATOR CARE V6'!I3="yes",INDEX('ADD SI'!$W$33:$AB$37,MATCH('CARE SHEET'!Q47,'ADD SI'!$W$33:$W$37,0),MATCH('CARE SHEET'!$T$3,'ADD SI'!$W$33:$AB$33,0)),0) -> #N/A | W47: =IF('CALCULATOR CARE V6'!I3="yes",INDEX('ADD SI'!$W$21:$AB$25,MATCH('CARE SHEET'!Q47,'ADD SI'!$W$21:$W$25,0),MATCH('CARE SHEET'!$T$3,'ADD SI'!$W$21:$AB$21,0)),0) -> #N/A
A48: 18-24 | B48: 18 Years | C48: 24 Years | D48: 5 | E48: FLOATER | F48: 5 | G48: 1 | H48: 4 | I48: 1 | J48: Zone 1 | K48: =G48&"+"&H48 -> 1+4 | L48: =VLOOKUP(A48,'ZONE 1 PREMIUM'!$A$4:$N$16,14,0) -> 2 | M48: =VLOOKUP(D48,DROPDOWN!B:C,2,0) -> 4 | N48: =VLOOKUP(K48,$AQ$3:$AR$12,2,0) -> X65:AP76 | O48: =INDEX(INDIRECT(N48),L48,M48) -> 30721.1 | Q48: =VLOOKUP('CALCULATOR CARE V6'!H4,DROPDOWN!K:N,4,0) -> Upto 45 Years | R48: =IF('CALCULATOR CARE V6'!I4="yes",INDEX('ADD SI'!$B$33:$Q$37,MATCH('CARE SHEET'!Q48,'ADD SI'!$B$33:$B$37,0),MATCH('CARE SHEET'!$T$3,'ADD SI'!$B$33:$Q$33,0)),0) -> 0 | S48: =IF('CALCULATOR CARE V6'!I4="yes",INDEX('ADD SI'!$B$21:$AB$25,MATCH('CARE SHEET'!Q48,'ADD SI'!$B$21:$B$25,0),MATCH('CARE SHEET'!$T$3,'ADD SI'!$B$21:$Q$21,0)),0) -> 0 | T48: =IF('CALCULATOR CARE V6'!I4="yes",INDEX('ADD SI'!$B$9:$AB$13,MATCH('CARE SHEET'!Q48,'ADD SI'!$B$9:$B$13,0),MATCH('CARE SHEET'!$T$3,'ADD SI'!$B$9:$Q$9,0)),0) -> 0 | U48: =IF('CALCULATOR CARE V6'!I4="yes",INDEX('ADD SI'!$W$45:$AB$49,MATCH('CARE SHEET'!Q48,'ADD SI'!$W$45:$W$49,0),MATCH('CARE SHEET'!$T$3,'ADD SI'!$W$45:$AB$45,0)),0) -> 0 | V48: =IF('CALCULATOR CARE V6'!I4="yes",INDEX('ADD SI'!$W$33:$AB$37,MATCH('CARE SHEET'!Q48,'ADD SI'!$W$33:$W$37,0),MATCH('CARE SHEET'!$T$3,'ADD SI'!$W$33:$AB$33,0)),0) -> 0 | W48: =IF('CALCULATOR CARE V6'!I4="yes",INDEX('ADD SI'!$W$21:$AB$25,MATCH('CARE SHEET'!Q48,'ADD SI'!$W$21:$W$25,0),MATCH('CARE SHEET'!$T$3,'ADD SI'!$W$21:$AB$21,0)),0) -> 0 | X48: 1A3C
A49: 25-35 | B49: 25 Years | C49: 35 Years | D49: 5 | E49: FLOATER | F49: 5 | G49: 1 | H49: 4 | I49: 1 | J49: Zone 1 | K49: =G49&"+"&H49 -> 1+4 | L49: =VLOOKUP(A49,'ZONE 1 PREMIUM'!$A$4:$N$16,14,0) -> 3 | M49: =VLOOKUP(D49,DROPDOWN!B:C,2,0) -> 4 | N49: =VLOOKUP(K49,$AQ$3:$AR$12,2,0) -> X65:AP76 | O49: =INDEX(INDIRECT(N49),L49,M49) -> 32124.1 | Q49: =VLOOKUP('CALCULATOR CARE V6'!H5,DROPDOWN!K:N,4,0) -> Upto 45 Years | R49: =IF('CALCULATOR CARE V6'!I5="yes",INDEX('ADD SI'!$B$33:$Q$37,MATCH('CARE SHEET'!Q49,'ADD SI'!$B$33:$B$37,0),MATCH('CARE SHEET'!$T$3,'ADD SI'!$B$33:$Q$33,0)),0) -> 0 | S49: =IF('CALCULATOR CARE V6'!I5="yes",INDEX('ADD SI'!$B$21:$AB$25,MATCH('CARE SHEET'!Q49,'ADD SI'!$B$21:$B$25,0),MATCH('CARE SHEET'!$T$3,'ADD SI'!$B$21:$Q$21,0)),0) -> 0 | T49: =IF('CALCULATOR CARE V6'!I5="yes",INDEX('ADD SI'!$B$9:$AB$13,MATCH('CARE SHEET'!Q49,'ADD SI'!$B$9:$B$13,0),MATCH('CARE SHEET'!$T$3,'ADD SI'!$B$9:$Q$9,0)),0) -> 0 | U49: =IF('CALCULATOR CARE V6'!I5="yes",INDEX('ADD SI'!$W$45:$AB$49,MATCH('CARE SHEET'!Q49,'ADD SI'!$W$45:$W$49,0),MATCH('CARE SHEET'!$T$3,'ADD SI'!$W$45:$AB$45,0)),0) -> 0 | V49: =IF('CALCULATOR CARE V6'!I5="yes",INDEX('ADD SI'!$W$33:$AB$37,MATCH('CARE SHEET'!Q49,'ADD SI'!$W$33:$W$37,0),MATCH('CARE SHEET'!$T$3,'ADD SI'!$W$33:$AB$33,0)),0) -> 0 | W49: =IF('CALCULATOR CARE V6'!I5="yes",INDEX('ADD SI'!$W$21:$AB$25,MATCH('CARE SHEET'!Q49,'ADD SI'!$W$21:$W$25,0),MATCH('CARE SHEET'!$T$3,'ADD SI'!$W$21:$AB$21,0)),0) -> 0 | Y49: Care 3 | AA49: Care 4 | AD49: Care 5 | AI49: Care 6 | AL49: Care 7 | AT49: 1A3C | AV49: Care 3 | AX49: Care 4 | BA49: Care 5 | BF49: Care 6 | BI49: Care 7 | BQ49: 1A3C | BS49: Care 3 | BU49: Care 4 | BX49: Care 5 | CC49: Care 6 | CF49: Care 7 | CN49: 1A3C | CP49: Care 3 | CR49: Care 4 | CU49: Care 5 | CZ49: Care 6 | DC49: Care 7
A50: 36-40 | B50: 36 Years | C50: 40 Years | D50: 5 | E50: FLOATER | F50: 5 | G50: 1 | H50: 4 | I50: 1 | J50: Zone 1 | K50: =G50&"+"&H50 -> 1+4 | L50: =VLOOKUP(A50,'ZONE 1 PREMIUM'!$A$4:$N$16,14,0) -> 4 | M50: =VLOOKUP(D50,DROPDOWN!B:C,2,0) -> 4 | N50: =VLOOKUP(K50,$AQ$3:$AR$12,2,0) -> X65:AP76 | O50: =INDEX(INDIRECT(N50),L50,M50) -> 37112.8 | Q50: =VLOOKUP('CALCULATOR CARE V6'!H6,DROPDOWN!K:N,4,0) -> Upto 45 Years | R50: =IF('CALCULATOR CARE V6'!I6="yes",INDEX('ADD SI'!$B$33:$Q$37,MATCH('CARE SHEET'!Q50,'ADD SI'!$B$33:$B$37,0),MATCH('CARE SHEET'!$T$3,'ADD SI'!$B$33:$Q$33,0)),0) -> 0 | S50: =IF('CALCULATOR CARE V6'!I6="yes",INDEX('ADD SI'!$B$21:$AB$25,MATCH('CARE SHEET'!Q50,'ADD SI'!$B$21:$B$25,0),MATCH('CARE SHEET'!$T$3,'ADD SI'!$B$21:$Q$21,0)),0) -> 0 | T50: =IF('CALCULATOR CARE V6'!I6="yes",INDEX('ADD SI'!$B$9:$AB$13,MATCH('CARE SHEET'!Q50,'ADD SI'!$B$9:$B$13,0),MATCH('CARE SHEET'!$T$3,'ADD SI'!$B$9:$Q$9,0)),0) -> 0 | U50: =IF('CALCULATOR CARE V6'!I6="yes",INDEX('ADD SI'!$W$45:$AB$49,MATCH('CARE SHEET'!Q50,'ADD SI'!$W$45:$W$49,0),MATCH('CARE SHEET'!$T$3,'ADD SI'!$W$45:$AB$45,0)),0) -> 0 | V50: =IF('CALCULATOR CARE V6'!I6="yes",INDEX('ADD SI'!$W$33:$AB$37,MATCH('CARE SHEET'!Q50,'ADD SI'!$W$33:$W$37,0),MATCH('CARE SHEET'!$T$3,'ADD SI'!$W$33:$AB$33,0)),0) -> 0 | W50: =IF('CALCULATOR CARE V6'!I6="yes",INDEX('ADD SI'!$W$21:$AB$25,MATCH('CARE SHEET'!Q50,'ADD SI'!$W$21:$W$25,0),MATCH('CARE SHEET'!$T$3,'ADD SI'!$W$21:$AB$21,0)),0) -> 0 | X50: Age-Band/ SI | Y50: 3L | Z50: 4L | AA50: 5L | AB50: 7L | AC50: 10L | AD50: 15L | AE50: 20L | AF50: 25L | AG50: 30L | AH50: 40L | AI50: 50L | AJ50: 60L | AK50: 75L | AL50: 1 CR | AM50: 1.5 CR | AN50: 2 CR | AO50: 3 CR | AP50: 6 CR | AU50: Age-Band/ SI | AV50: 3L | AW50: 4L | AX50: 5L | AY50: 7L | AZ50: 10L | BA50: 15L | BB50: 20L | BC50: 25L | BD50: 30L | BE50: 40L | BF50: 50L | BG50: 60L | BH50: 75L | BI50: 1 CR | BJ50: 1.5 CR | BK50: 2 CR | BL50: 3 CR | BM50: 6 CR | BR50: Age-Band/ SI | BS50: 3L | BT50: 4L | BU50: 5L | BV50: 7L | BW50: 10L | BX50: 15L | BY50: 20L | BZ50: 25L | CA50: 30L | CB50: 40L | CC50: 50L | CD50: 60L | CE50: 75L | CF50: 1 CR | CG50: 1.5 CR | CH50: 2 CR | CI50: 3 CR | CJ50: 6 CR | CO50: Age-Band/ SI | CP50: 3L | CQ50: 4L | CR50: 5L | CS50: 7L | CT50: 10L | CU50: 15L | CV50: 20L | CW50: 25L | CX50: 30L | CY50: 40L | CZ50: 50L | DA50: 60L | DB50: 75L | DC50: 1 CR | DD50: 1.5 CR | DE50: 2 CR | DF50: 3 CR | DG50: 6 CR
A51: 41-45 | B51: 41 Years | C51: 45 Years | D51: 5 | E51: FLOATER | F51: 5 | G51: 1 | H51: 4 | I51: 1 | J51: Zone 1 | K51: =G51&"+"&H51 -> 1+4 | L51: =VLOOKUP(A51,'ZONE 1 PREMIUM'!$A$4:$N$16,14,0) -> 5 | M51: =VLOOKUP(D51,DROPDOWN!B:C,2,0) -> 4 | N51: =VLOOKUP(K51,$AQ$3:$AR$12,2,0) -> X65:AP76 | O51: =INDEX(INDIRECT(N51),L51,M51) -> 40958.4 | Q51: =VLOOKUP('CALCULATOR CARE V6'!H7,DROPDOWN!K:N,4,0) -> Upto 45 Years | R51: =IF('CALCULATOR CARE V6'!I7="yes",INDEX('ADD SI'!$B$33:$Q$37,MATCH('CARE SHEET'!Q51,'ADD SI'!$B$33:$B$37,0),MATCH('CARE SHEET'!$T$3,'ADD SI'!$B$33:$Q$33,0)),0) -> 0 | S51: =IF('CALCULATOR CARE V6'!I7="yes",INDEX('ADD SI'!$B$21:$AB$25,MATCH('CARE SHEET'!Q51,'ADD SI'!$B$21:$B$25,0),MATCH('CARE SHEET'!$T$3,'ADD SI'!$B$21:$Q$21,0)),0) -> 0 | T51: =IF('CALCULATOR CARE V6'!I7="yes",INDEX('ADD SI'!$B$9:$AB$13,MATCH('CARE SHEET'!Q51,'ADD SI'!$B$9:$B$13,0),MATCH('CARE SHEET'!$T$3,'ADD SI'!$B$9:$Q$9,0)),0) -> 0 | U51: =IF('CALCULATOR CARE V6'!I7="yes",INDEX('ADD SI'!$W$45:$AB$49,MATCH('CARE SHEET'!Q51,'ADD SI'!$W$45:$W$49,0),MATCH('CARE SHEET'!$T$3,'ADD SI'!$W$45:$AB$45,0)),0) -> 0 | V51: =IF('CALCULATOR CARE V6'!I7="yes",INDEX('ADD SI'!$W$33:$AB$37,MATCH('CARE SHEET'!Q51,'ADD SI'!$W$33:$W$37,0),MATCH('CARE SHEET'!$T$3,'ADD SI'!$W$33:$AB$33,0)),0) -> 0 | W51: =IF('CALCULATOR CARE V6'!I7="yes",INDEX('ADD SI'!$W$21:$AB$25,MATCH('CARE SHEET'!Q51,'ADD SI'!$W$21:$W$25,0),MATCH('CARE SHEET'!$T$3,'ADD SI'!$W$21:$AB$21,0)),0) -> 0 | X51: 18-24 | Y51: 17848 | Z51: 21599.3 | AA51: 25953.2 | AB51: 28308.4 | AC51: 30468.1 | AD51: 38755 | AE51: 42393.6 | AF51: 45534.25 | AG51: 50795.5 | AH51: 63068.3 | AI51: 112428.6 | AJ51: 138828 | AK51: 168433.6 | AL51: 239195.4 | AM51: 286621.4 | AN51: 338860.15 | AO51: 399282.3 | AP51: 538306.95 | AU51: 18-24 | AV51: 15836.625 | AW51: 19157.625 | AX51: 23028.75 | AY51: 25113.375 | AZ51: 27025.875 | BA51: 34378.875 | BB51: 37600.875 | BC51: 40381.875 | BD51: 45040.5 | BE51: 55909.125 | BF51: 99619.875 | BG51: 122997.38 | BH51: 149213.25 | BI51: 212738.62 | BJ51: 254736 | BK51: 300994.88 | BL51: 354499.88 | BM51: 477610.88 | BR51: 18-24 | BS51: 14610.2 | BT51: 17670.4 | BU51: 21245.4 | BV51: 23167.1 | BW51: 24929.3 | BX51: 31713 | BY51: 34681.9 | BZ51: 37244.9 | CA51: 41538.2 | CB51: 51552.6 | CC51: 91832.4 | CD51: 113375.9 | CE51: 137535.2 | CF51: 196529.3 | CG51: 235230.6 | CH51: 277858.9 | CI51: 327165.3 | CJ51: 440613.8 | CO51: 18-24 | CP51: 13450.6 | CQ51: 16264.98 | CR51: 19560.05 | CS51: 21326.94 | CT51: 22947.77 | CU51: 29192.38 | CV51: 31922.83 | CW51: 34279.41 | CX51: 38227.39 | CY51: 47436.8 | CZ51: 84475 | DA51: 104284.66 | DB51: 126498.86 | DC51: 181204.87 | DD51: 216792.28 | DE51: 255989.77 | DF51: 301328.32 | DG51: 405647.86
A52: 46-50 | B52: 46 Years | C52: 50 Years | D52: 5 | E52: FLOATER | F52: 5 | G52: 1 | H52: 4 | I52: 1 | J52: Zone 1 | K52: =G52&"+"&H52 -> 1+4 | L52: =VLOOKUP(A52,'ZONE 1 PREMIUM'!$A$4:$N$16,14,0) -> 6 | M52: =VLOOKUP(D52,DROPDOWN!B:C,2,0) -> 4 | N52: =VLOOKUP(K52,$AQ$3:$AR$12,2,0) -> X65:AP76 | O52: =INDEX(INDIRECT(N52),L52,M52) -> 49339.6 | Q52: =VLOOKUP('CALCULATOR CARE V6'!H8,DROPDOWN!K:N,4,0) -> Upto 45 Years | R52: =IF('CALCULATOR CARE V6'!I8="yes",INDEX('ADD SI'!$B$33:$Q$37,MATCH('CARE SHEET'!Q52,'ADD SI'!$B$33:$B$37,0),MATCH('CARE SHEET'!$T$3,'ADD SI'!$B$33:$Q$33,0)),0) -> 0 | S52: =IF('CALCULATOR CARE V6'!I8="yes",INDEX('ADD SI'!$B$21:$AB$25,MATCH('CARE SHEET'!Q52,'ADD SI'!$B$21:$B$25,0),MATCH('CARE SHEET'!$T$3,'ADD SI'!$B$21:$Q$21,0)),0) -> 0 | T52: =IF('CALCULATOR CARE V6'!I8="yes",INDEX('ADD SI'!$B$9:$AB$13,MATCH('CARE SHEET'!Q52,'ADD SI'!$B$9:$B$13,0),MATCH('CARE SHEET'!$T$3,'ADD SI'!$B$9:$Q$9,0)),0) -> 0 | U52: =IF('CALCULATOR CARE V6'!I8="yes",INDEX('ADD SI'!$W$45:$AB$49,MATCH('CARE SHEET'!Q52,'ADD SI'!$W$45:$W$49,0),MATCH('CARE SHEET'!$T$3,'ADD SI'!$W$45:$AB$45,0)),0) -> 0 | V52: =IF('CALCULATOR CARE V6'!I8="yes",INDEX('ADD SI'!$W$33:$AB$37,MATCH('CARE SHEET'!Q52,'ADD SI'!$W$33:$W$37,0),MATCH('CARE SHEET'!$T$3,'ADD SI'!$W$33:$AB$33,0)),0) -> 0 | W52: =IF('CALCULATOR CARE V6'!I8="yes",INDEX('ADD SI'!$W$21:$AB$25,MATCH('CARE SHEET'!Q52,'ADD SI'!$W$21:$W$25,0),MATCH('CARE SHEET'!$T$3,'ADD SI'!$W$21:$AB$21,0)),0) -> 0 | X52: 25-35 | Y52: 18935.9 | Z52: 22719.4 | AA52: 27442.45 | AB52: 29934.5 | AC52: 32223 | AD52: 40987.15 | AE52: 44731.55 | AF52: 47963.05 | AG52: 53507.2 | AH52: 66414.8 | AI52: 119245.8 | AJ52: 147758.9 | AK52: 180080.8 | AL52: 251047.3 | AM52: 301659.95 | AN52: 357540.75 | AO52: 422270.8 | AP52: 571045.15 | AU52: 25-35 | AV52: 16806.375 | AW52: 20157.75 | AX52: 24360.75 | AY52: 26566.875 | AZ52: 28593 | BA52: 36374.625 | BB52: 39690 | BC52: 42552 | BD52: 47461.5 | BE52: 58891.5 | BF52: 105674.62 | BG52: 130924.12 | BH52: 159546.38 | BI52: 223237.12 | BJ52: 268056 | BK52: 317539.12 | BL52: 374860.12 | BM52: 506604.38 | BR52: 25-35 | BS52: 15507.8 | BT52: 18595.5 | BU52: 22479.6 | BV52: 24512.4 | BW52: 26380.2 | BX52: 33562.1 | BY52: 36616.8 | BZ52: 39254.6 | CA52: 43777.8 | CB52: 54311.4 | CC52: 97423.7 | CD52: 120690.9 | CE52: 147066.7 | CF52: 206204.9 | CG52: 247506.6 | CH52: 293106 | CI52: 345929.1 | CJ52: 467333.9 | CO52: 25-35 | CP52: 14280.09 | CQ52: 17119.54 | CR52: 20702.37 | CS52: 22571.72 | CT52: 24288.47 | CU52: 30903.68 | CV52: 33712.61 | CW52: 36137.86 | CX52: 40297.3 | CY52: 49983.04 | CZ52: 89625.25 | DA52: 111020.86 | DB52: 135273.36 | DC52: 190103.63 | DD52: 228081.41 | DE52: 270012.62 | DF52: 318583.02 | DG52: 430218.64
A53: 51-55 | B53: 51 Years | C53: 55 Years | D53: 5 | E53: FLOATER | F53: 5 | G53: 1 | H53: 4 | I53: 1 | J53: Zone 1 | K53: =G53&"+"&H53 -> 1+4 | L53: =VLOOKUP(A53,'ZONE 1 PREMIUM'!$A$4:$N$16,14,0) -> 7 | M53: =VLOOKUP(D53,DROPDOWN!B:C,2,0) -> 4 | N53: =VLOOKUP(K53,$AQ$3:$AR$12,2,0) -> X65:AP76 | O53: =INDEX(INDIRECT(N53),L53,M53) -> 59981.7 | R53: =R47+SUM(R48:R52)*97.5% -> #N/A | S53: =S47+SUM(S48:S52)*97.5% -> #N/A | T53: =T47+SUM(T48:T52)*97.5% -> #N/A | U53: =U47+SUM(U48:U52)*97.5% -> #N/A | V53: =V47+SUM(V48:V52)*97.5% -> #N/A | W53: =W47+SUM(W48:W52)*97.5% -> #N/A | X53: 36-40 | Y53: 21557.9 | Z53: 26027.95 | AA53: 31692.85 | AB53: 34600.05 | AC53: 37274.95 | AD53: 47454.75 | AE53: 51902.95 | AF53: 55766.95 | AG53: 62264.45 | AH53: 77351.3 | AI53: 130507.75 | AJ53: 163848.55 | AK53: 201707.7 | AL53: 273496.45 | AM53: 332597.25 | AN53: 398109.3 | AO53: 474181.8 | AP53: 648759.85 | AU53: 36-40 | AV53: 19129.5 | AW53: 23088.375 | AX53: 28127.25 | AY53: 30701.25 | AZ53: 33070.5 | BA53: 42108.75 | BB53: 46047.375 | BC53: 49469.625 | BD53: 55221.75 | BE53: 68582.25 | BF53: 115653.38 | BG53: 145177.88 | BH53: 178704 | BI53: 242919 | BJ53: 295255.12 | BK53: 353268 | BL53: 420631.88 | BM53: 575227.12 | BR53: 36-40 | BS53: 17649.5 | BT53: 21297.1 | BU53: 25952.3 | BV53: 28325 | BW53: 30507.4 | BX53: 38848.7 | BY53: 42478.7 | BZ53: 45631.3 | CA53: 50933.3 | CB53: 63244.5 | CC53: 106621.9 | CD53: 133829.3 | CE53: 164723.9 | CF53: 224239.4 | CG53: 272467.8 | CH53: 325927.8 | CI53: 388005.2 | CJ53: 530467.3 | CO53: 36-40 | CP53: 16249.72 | CQ53: 19603.65 | CR53: 23897.16 | CS53: 26078.25 | CT53: 28086.03 | CU53: 35767.26 | CV53: 39104.84 | CW53: 42005.33 | CX53: 46879.81 | CY53: 58200.55 | CZ53: 98086.92 | DA53: 123104.6 | DB53: 151513.27 | DC53: 206582.25 | DD53: 250929.99 | DE53: 300086.81 | DF53: 357169.02 | DG53: 488166.31
A54: 56-60 | B54: 56 Years | C54: 60 Years | D54: 5 | E54: FLOATER | F54: 5 | G54: 1 | H54: 4 | I54: 1 | J54: Zone 1 | K54: =G54&"+"&H54 -> 1+4 | L54: =VLOOKUP(A54,'ZONE 1 PREMIUM'!$A$4:$N$16,14,0) -> 8 | M54: =VLOOKUP(D54,DROPDOWN!B:C,2,0) -> 4 | N54: =VLOOKUP(K54,$AQ$3:$AR$12,2,0) -> X65:AP76 | O54: =INDEX(INDIRECT(N54),L54,M54) -> 73499.95 | X54: 41-45 | Y54: 23693.45 | Z54: 28727 | AA54: 35195.75 | AB54: 38457.15 | AC54: 41464.4 | AD54: 52796.5 | AE54: 57750.7 | AF54: 62034.45 | AG54: 69317.4 | AH54: 86186.75 | AI54: 143800.6 | AJ54: 181306.7 | AK54: 223976.3 | AL54: 291261.65 | AM54: 357319.95 | AN54: 430792.3 | AO54: 516287.9 | AP54: 712200.75 | AU54: 41-45 | AV54: 21021.75 | AW54: 25479 | AX54: 31231.125 | AY54: 34120.125 | AZ54: 36783 | BA54: 46842.75 | BB54: 51229.125 | BC54: 55022.625 | BD54: 61472.25 | BE54: 76411.125 | BF54: 127428.75 | BG54: 160642.12 | BH54: 198427.5 | BI54: 258422.62 | BJ54: 316920.38 | BK54: 381981.38 | BL54: 457690.5 | BM54: 631177.88 | BR54: 41-45 | BS54: 19393 | BT54: 23500.4 | BU54: 28814.5 | BV54: 31476.5 | BW54: 33930.6 | BX54: 43213.5 | BY54: 47256 | BZ54: 50751.8 | CA54: 56695.1 | CB54: 70461.6 | CC54: 117475.6 | CD54: 148080.9 | CE54: 182901.4 | CF54: 238406.3 | CG54: 292311.8 | CH54: 352267.3 | CI54: 422034.8 | CJ54: 581906.6 | CO54: 41-45 | CP54: 17853.11 | CQ54: 21631.05 | CR54: 26529.51 | CS54: 28977.65 | CT54: 31233.95 | CU54: 39783.91 | CV54: 43500.81 | CW54: 46715.22 | CX54: 52180.48 | CY54: 64838.65 | CZ54: 108069.14 | DA54: 136211.85 | DB54: 168230.6 | DC54: 219487.85 | DD54: 269055.6 | DE54: 324185.62 | DF54: 388338.66 | DG54: 535344.78
A55: 61-65 | B55: 61 Years | C55: 65 Years | D55: 5 | E55: FLOATER | F55: 5 | G55: 1 | H55: 4 | I55: 1 | J55: Zone 1 | K55: =G55&"+"&H55 -> 1+4 | L55: =VLOOKUP(A55,'ZONE 1 PREMIUM'!$A$4:$N$16,14,0) -> 9 | M55: =VLOOKUP(D55,DROPDOWN!B:C,2,0) -> 4 | N55: =VLOOKUP(K55,$AQ$3:$AR$12,2,0) -> X65:AP76 | O55: =INDEX(INDIRECT(N55),L55,M55) -> 91234.1 | R55: ZONE 1 | S55: ZONE 1A | T55: ZONE 2 | U55: ZONE 3 | X55: 46-50 | Y55: 28605.1 | Z55: 34789.8 | AA55: 42877.75 | AB55: 48635.8 | AC55: 52482.55 | AD55: 64892.2 | AE55: 71078.05 | AF55: 76455.45 | AG55: 85491 | AH55: 106357.75 | AI55: 174487.2 | AJ55: 221238.15 | AK55: 274560.2 | AL55: 342406.75 | AM55: 423835.95 | AN55: 514696.3 | AO55: 620642.35 | AP55: 863055.45 | AU55: 46-50 | AV55: 25378.875 | AW55: 30855.375 | AX55: 38050.875 | AY55: 43149.375 | AZ55: 46555.875 | BA55: 57577.5 | BB55: 63055.125 | BC55: 67817.25 | BD55: 75818.25 | BE55: 94296.375 | BF55: 154626.75 | BG55: 196026.75 | BH55: 243244.12 | BI55: 303620.62 | BJ55: 375727.5 | BK55: 456187.5 | BL55: 550005.75 | BM55: 764670.38 | BR55: 46-50 | BS55: 23412.4 | BT55: 28459.2 | BU55: 35106.5 | BV55: 39805.7 | BW55: 42944 | BX55: 53119 | BY55: 58166.9 | BZ55: 62554.8 | CA55: 69928.1 | CB55: 86956.1 | CC55: 142551.2 | CD55: 180702.5 | CE55: 224214.1 | CF55: 280007.2 | CG55: 346456 | CH55: 420600.4 | CI55: 507056 | CJ55: 704873.4 | CO55: 46-50 | CP55: 21553.66 | CQ55: 26194.88 | CR55: 32325.04 | CS55: 36645.8 | CT55: 39531.03 | CU55: 48905.03 | CV55: 53546.25 | CW55: 57580.34 | CX55: 64361.23 | CY55: 80019.08 | CZ55: 131140.08 | DA55: 166220.64 | DB55: 206231.27 | DC55: 257691.26 | DD55: 318792.3 | DE55: 386969.62 | DF55: 466468.77 | DG55: 648365.79
A56: 66-70 | B56: 66 Years | C56: 70 Years | D56: 5 | E56: FLOATER | F56: 5 | G56: 1 | H56: 4 | I56: 1 | J56: Zone 1 | K56: =G56&"+"&H56 -> 1+4 | L56: =VLOOKUP(A56,'ZONE 1 PREMIUM'!$A$4:$N$16,14,0) -> 10 | M56: =VLOOKUP(D56,DROPDOWN!B:C,2,0) -> 4 | N56: =VLOOKUP(K56,$AQ$3:$AR$12,2,0) -> X65:AP76 | O56: =INDEX(INDIRECT(N56),L56,M56) -> 112918.5 | R56: =IF('CALCULATOR CARE V6'!$B$7="care senior",'CARE SHEET'!U53,'CARE SHEET'!W28) -> #N/A | S56: =IF('CALCULATOR CARE V6'!B7="care senior",'CARE SHEET'!V53,'CARE SHEET'!R53) -> #N/A | T56: =IF('CALCULATOR CARE V6'!B7="care senior",W53,S53) -> #N/A | U56: =IF('CALCULATOR CARE V6'!B7="care senior",R65,T53) -> #N/A | V56: =HLOOKUP(R8,R55:U56,2,0) -> #N/A | X56: 51-55 | Y56: 35816.75 | Z56: 43708.05 | AA56: 53976.4 | AB56: 61358.25 | AC56: 66269.9 | AD56: 81863.9 | AE56: 89821.9 | AF56: 96771.35 | AG56: 108309.3 | AH56: 134895 | AI56: 227679.3 | AJ56: 287615 | AK56: 356092.9 | AL56: 435548.7 | AM56: 540126.25 | AN56: 657006.5 | AO56: 793457.45 | AP56: 1105269.6 | AU56: 51-55 | AV56: 31765.5 | AW56: 38752.875 | AX56: 47882.25 | AY56: 54419.625 | AZ56: 58768.875 | BA56: 72613.125 | BB56: 79660.125 | BC56: 85813.875 | BD56: 96032.25 | BE56: 119574 | BF56: 201736.12 | BG56: 254812.5 | BH56: 315451.12 | BI56: 386066.25 | BJ56: 478674 | BK56: 582174 | BL56: 703005.75 | BM56: 979125.75 | BR56: 51-55 | BS56: 29298.5 | BT56: 35736.8 | BU56: 44169.4 | BV56: 50193 | BW56: 54201.4 | BX56: 66977.9 | BY56: 73471.2 | BZ56: 79142.8 | CA56: 88558.8 | CB56: 110253 | CC56: 185967.1 | CD56: 234877.5 | CE56: 290757.5 | CF56: 355965.5 | CG56: 441304.6 | CH56: 536682.3 | CI56: 648030.9 | CJ56: 902480.7 | CO56: 51-55 | CP56: 26966.6 | CQ56: 32887.48 | CR56: 40659.18 | CS56: 46198.56 | CT56: 49883.85 | CU56: 61651.49 | CV56: 67622.51 | CW56: 72838.16 | CX56: 81496.03 | CY56: 101444.12 | CZ56: 171065.69 | DA56: 216040.18 | DB56: 267422.78 | DC56: 327518.84 | DD56: 405991.21 | DE56: 493692.61 | DF56: 596080.67 | DG56: 830053.53
A57: 71-75 | B57: 71 Years | C57: 75 Years | D57: 5 | E57: FLOATER | F57: 5 | G57: 1 | H57: 4 | I57: 1 | J57: Zone 1 | K57: =G57&"+"&H57 -> 1+4 | L57: =VLOOKUP(A57,'ZONE 1 PREMIUM'!$A$4:$N$16,14,0) -> 11 | M57: =VLOOKUP(D57,DROPDOWN!B:C,2,0) -> 4 | N57: =VLOOKUP(K57,$AQ$3:$AR$12,2,0) -> X65:AP76 | O57: =INDEX(INDIRECT(N57),L57,M57) -> 130604.35 | X57: 56-60 | Y57: 44772.95 | Z57: 54671 | AA57: 67707.4 | AB57: 75559.6 | AC57: 81684.5 | AD57: 101195.4 | AE57: 111100.35 | AF57: 118892.75 | AG57: 133191.85 | AH57: 166023.2 | AI57: 282085.8 | AJ57: 356440.2 | AK57: 441663.25 | AL57: 534930.55 | AM57: 664547.05 | AN57: 809752.95 | AO57: 979563.1 | AP57: 1366930.2 | AU57: 56-60 | AV57: 39705.75 | AW57: 48471.75 | AX57: 60060.375 | AY57: 67015.125 | AZ57: 72437.625 | BA57: 89760.375 | BB57: 98530.875 | BC57: 105431.62 | BD57: 118093.5 | BE57: 147168 | BF57: 249944.62 | BG57: 315787.5 | BH57: 391254.75 | BI57: 474111 | BJ57: 588890.25 | BK57: 717474.38 | BL57: 867846.38 | BM57: 1210872.4 | BR57: 56-60 | BS57: 36621.2 | BT57: 44698.5 | BU57: 55401.5 | BV57: 61810.1 | BW57: 66807.4 | BX57: 82793.7 | BY57: 90876.5 | BZ57: 97235.6 | CA57: 108904.4 | CB57: 135696 | CC57: 230407.1 | CD57: 291082 | CE57: 360627.3 | CF57: 437120.2 | CG57: 542891.8 | CH57: 661384.9 | CI57: 799955.2 | CJ57: 1116060 | CO57: 56-60 | CP57: 33704.98 | CQ57: 41133.33 | CR57: 50998.92 | CS57: 56891.46 | CT57: 61486.9 | CU57: 76210.62 | CV57: 83643.33 | CW57: 89490.09 | CX57: 100220.05 | CY57: 124855.14 | CZ57: 211945.05 | DA57: 267736.7 | DB57: 331684.82 | DC57: 402164.22 | DD57: 499423.83 | DE57: 608380.23 | DF57: 735799.05 | DG57: 1026465
A58: 75+ | B58: >75 Years | D58: 5 | E58: FLOATER | F58: 5 | G58: 1 | H58: 4 | I58: 1 | J58: Zone 1 | K58: =G58&"+"&H58 -> 1+4 | L58: =VLOOKUP(A58,'ZONE 1 PREMIUM'!$A$4:$N$16,14,0) -> 12 | M58: =VLOOKUP(D58,DROPDOWN!B:C,2,0) -> 4 | N58: =VLOOKUP(K58,$AQ$3:$AR$12,2,0) -> X65:AP76 | O58: =INDEX(INDIRECT(N58),L58,M58) -> 167088.1 | R58: 3 | X58: 61-65 | Y58: 56237.3 | Z58: 68727.45 | AA58: 85261 | AB58: 97817.85 | AC58: 105901.2 | AD58: 129501.5 | AE58: 142298.7 | AF58: 151886.25 | AG58: 170411.6 | AH58: 212768.4 | AI58: 364475.25 | AJ58: 460914.25 | AK58: 571870.85 | AL58: 683739.4 | AM58: 851428.95 | AN58: 1039833.4 | AO58: 1260625.4 | AP58: 1763231.7 | AU58: 61-65 | AV58: 49860 | AW58: 60919.875 | AX58: 75606.75 | AY58: 86726.25 | AZ58: 93883.5 | BA58: 114828.75 | BB58: 126162 | BC58: 134651.25 | BD58: 151056 | BE58: 188564.62 | BF58: 322905.38 | BG58: 408305.25 | BH58: 506560.5 | BI58: 605886.75 | BJ58: 754381.12 | BK58: 921218.62 | BL58: 1116736.9 | BM58: 1561809.4 | BR58: 61-65 | BS58: 45978.9 | BT58: 56170.4 | BU58: 69729 | BV58: 79975.5 | BW58: 86571.1 | BX58: 105897 | BY58: 116340.4 | BZ58: 124163.6 | CA58: 139280.9 | CB58: 173846.2 | CC58: 297643.5 | CD58: 376340.8 | CE58: 466885.1 | CF58: 558554.7 | CG58: 695394.7 | CH58: 849139.5 | CI58: 1029311.8 | CJ58: 1439455.6 | CO58: 61-65 | CP58: 42310.53 | CQ58: 51681.26 | CR58: 64173.75 | CS58: 73595.71 | CT58: 79660.47 | CU58: 97455.81 | CV58: 107058.71 | CW58: 114252.71 | CX58: 128153.48 | CY58: 159936.79 | CZ58: 273770.94 | DA58: 346136.04 | DB58: 429393.51 | DC58: 513826 | DD58: 639654.51 | DE58: 781025.33 | DF58: 946699.88 | DG58: 1323835.5
A59: 18-24 | B59: 18 Years | C59: 24 Years | D59: 5 | E59: FLOATER | F59: 2 | G59: 2 | H59: 0 | I59: 1 | J59: Zone 1 | K59: =G59&"+"&H59 -> 2+0 | L59: =VLOOKUP(A59,'ZONE 1 PREMIUM'!$A$4:$N$16,14,0) -> 2 | M59: =VLOOKUP(D59,DROPDOWN!B:C,2,0) -> 4 | N59: =VLOOKUP(K59,$AQ$3:$AR$12,2,0) -> X81:AP92 | O59: =INDEX(INDIRECT(N59),L59,M59) -> 22973.55 | R59: =IF('CALCULATOR CARE V6'!I3="yes",INDEX('ADD SI'!$W$9:$AB$13,MATCH('CARE SHEET'!Q47,'ADD SI'!$W$9:$W$13,0),MATCH('CARE SHEET'!$T$3,'ADD SI'!$W$9:$AB$9,0)),0) -> #N/A | X59: 66-70 | Y59: 70421.4 | Z59: 86164.9 | AA59: 107102.95 | AB59: 120060 | AC59: 130155.85 | AD59: 158505.65 | AE59: 174400.95 | AF59: 188371.15 | AG59: 211650.6 | AH59: 264651.8 | AI59: 447645.55 | AJ59: 568350.7 | AK59: 707730.7 | AL59: 849102.5 | AM59: 1059782.5 | AN59: 1297149.4 | AO59: 1575888.7 | AP59: 2209087.9 | AU59: 66-70 | AV59: 62419.5 | AW59: 76361.625 | AX59: 94947.75 | AY59: 106421.62 | AZ59: 115362 | BA59: 140512.5 | BB59: 154591.88 | BC59: 166962.38 | BD59: 187576.88 | BE59: 234510.75 | BF59: 396564.75 | BG59: 503452.12 | BH59: 626878.12 | BI59: 752284.12 | BJ59: 938847.38 | BK59: 1149042.4 | BL59: 1395875.2 | BM59: 1956592.1 | BR59: 66-70 | BS59: 57553.1 | BT59: 70400 | BU59: 87551.2 | BV59: 98125.5 | BW59: 106363.4 | BX59: 129563.5 | BY59: 142540.2 | BZ59: 153939.5 | CA59: 172936.5 | CB59: 216187.4 | CC59: 365526.7 | CD59: 464026.2 | CE59: 577765.1 | CF59: 693443.3 | CG59: 865365.6 | CH59: 1059064.6 | CI59: 1286524.8 | CJ59: 1803235.5 | CO59: 66-70 | CP59: 52953.29 | CQ59: 64766.71 | CR59: 80561.9 | CS59: 90284.7 | CT59: 97859.11 | CU59: 119216.57 | CV59: 131150.98 | CW59: 141633.51 | CX59: 159100.76 | CY59: 198871.59 | CZ59: 336197.42 | DA59: 426769.88 | DB59: 531355.38 | DC59: 637839.66 | DD59: 795926.72 | DE59: 974037.08 | DF59: 1183192.8 | DG59: 1658321.6
A60: 25-35 | B60: 25 Years | C60: 35 Years | D60: 5 | E60: FLOATER | F60: 2 | G60: 2 | H60: 0 | I60: 1 | J60: Zone 1 | K60: =G60&"+"&H60 -> 2+0 | L60: =VLOOKUP(A60,'ZONE 1 PREMIUM'!$A$4:$N$16,14,0) -> 3 | M60: =VLOOKUP(D60,DROPDOWN!B:C,2,0) -> 4 | N60: =VLOOKUP(K60,$AQ$3:$AR$12,2,0) -> X81:AP92 | O60: =INDEX(INDIRECT(N60),L60,M60) -> 26207.35 | R60: =IF('CALCULATOR CARE V6'!I4="yes",INDEX('ADD SI'!$W$9:$AB$13,MATCH('CARE SHEET'!Q48,'ADD SI'!$W$9:$W$13,0),MATCH('CARE SHEET'!$T$3,'ADD SI'!$W$9:$AB$9,0)),0) -> 0 | X60: 71-75 | Y60: 81784.55 | Z60: 100175.35 | AA60: 124758.9 | AB60: 140139 | AC60: 152102.45 | AD60: 184922.3 | AE60: 203659.25 | AF60: 220191.65 | AG60: 247710 | AH60: 310127.4 | AI60: 513951.1 | AJ60: 655788.65 | AK60: 820071.9 | AL60: 995173.2 | AM60: 1244272.4 | AN60: 1525587.7 | AO60: 1856519.7 | AP60: 2606880.9 | AU60: 71-75 | AV60: 72483.75 | AW60: 88768.125 | AX60: 110584.12 | AY60: 124203.38 | AZ60: 134797.5 | BA60: 163906.88 | BB60: 180502.88 | BC60: 195142.5 | BD60: 219511.12 | BE60: 274783.5 | BF60: 455283 | BG60: 580884.75 | BH60: 726361.88 | BI60: 881633.25 | BJ60: 1102218.8 | BK60: 1351330.9 | BL60: 1644382.1 | BM60: 2308848.8 | BR60: 71-75 | BS60: 66827.2 | BT60: 81833.4 | BU60: 101962.3 | BV60: 114512.2 | BW60: 124274.7 | BX60: 151123.5 | BY60: 166419 | BZ60: 179909.4 | CA60: 202365.9 | CB60: 253300.3 | CC60: 419637.9 | CD60: 535382.1 | CE60: 669442.4 | CF60: 812641.5 | CG60: 1015914.9 | CH60: 1245476.1 | CI60: 1515528.3 | CJ60: 2127847.7 | CO60: 71-75 | CP60: 61481.45 | CQ60: 75280.85 | CR60: 93813.03 | CS60: 105352.86 | CT60: 114330.1 | CU60: 139042.58 | CV60: 153110.12 | CW60: 165514.32 | CX60: 186163.28 | CY60: 232999.49 | CZ60: 385954.83 | DA60: 492384.61 | DB60: 615655.98 | DC60: 747444.61 | DD60: 934359.99 | DE60: 1145448.3 | DF60: 1393767.7 | DG60: 1956809.4
A61: 36-40 | B61: 36 Years | C61: 40 Years | D61: 5 | E61: FLOATER | F61: 2 | G61: 2 | H61: 0 | I61: 1 | J61: Zone 1 | K61: =G61&"+"&H61 -> 2+0 | L61: =VLOOKUP(A61,'ZONE 1 PREMIUM'!$A$4:$N$16,14,0) -> 4 | M61: =VLOOKUP(D61,DROPDOWN!B:C,2,0) -> 4 | N61: =VLOOKUP(K61,$AQ$3:$AR$12,2,0) -> X81:AP92 | O61: =INDEX(INDIRECT(N61),L61,M61) -> 29059.35 | R61: =IF('CALCULATOR CARE V6'!I5="yes",INDEX('ADD SI'!$W$9:$AB$13,MATCH('CARE SHEET'!Q49,'ADD SI'!$W$9:$W$13,0),MATCH('CARE SHEET'!$T$3,'ADD SI'!$W$9:$AB$9,0)),0) -> 0 | X61: 75+ | Y61: 105284.8 | Z61: 129082.9 | AA61: 161042.55 | AB61: 181401 | AC61: 197176.7 | AD61: 239024.05 | AE61: 263520.2 | AF61: 285227.6 | AG61: 321373.25 | AH61: 402983 | AI61: 653193.1 | AJ61: 838354.6 | AK61: 1053632.3 | AL61: 1292603.4 | AM61: 1619686.4 | AN61: 1990133.6 | AO61: 2426858.8 | AP61: 3414875.5 | AU61: 75+ | AV61: 93294 | AW61: 114368.62 | AX61: 142716.38 | AY61: 160744.5 | AZ61: 174713.62 | BA61: 211818.38 | BB61: 233514 | BC61: 252736.88 | BD61: 284744.25 | BE61: 357013.12 | BF61: 578589.75 | BG61: 742556.25 | BH61: 933189.75 | BI61: 1145025 | BJ61: 1434667.5 | BK61: 1762708.5 | BL61: 2149441.9 | BM61: 3024361.1 | BR61: 75+ | BS61: 86005.7 | BT61: 105425.1 | BU61: 131573.2 | BV61: 148186.5 | BW61: 161059.8 | BX61: 195276.4 | BY61: 215272.2 | BZ61: 232985.5 | CA61: 262482 | CB61: 329078.2 | CC61: 533269 | CD61: 684367.2 | CE61: 860040.5 | CF61: 1055366.4 | CG61: 1322275.9 | CH61: 1624573.5 | CI61: 1980954.8 | CJ61: 2787209.7 | CO61: 75+ | CP61: 79116.56 | CQ61: 96974.03 | CR61: 121043.41 | CS61: 136318.67 | CT61: 148156.07 | CU61: 179645.08 | CV61: 198032.29 | CW61: 214321.25 | CX61: 241443.72 | CY61: 302681.01 | CZ61: 490443.32 | DA61: 629382.35 | DB61: 790918.17 | DC61: 970640.64 | DD61: 1216071.6 | DE61: 1494041.2 | DF61: 1821743.2 | DG61: 2563114.3
A62: 41-45 | B62: 41 Years | C62: 45 Years | D62: 5 | E62: FLOATER | F62: 2 | G62: 2 | H62: 0 | I62: 1 | J62: Zone 1 | K62: =G62&"+"&H62 -> 2+0 | L62: =VLOOKUP(A62,'ZONE 1 PREMIUM'!$A$4:$N$16,14,0) -> 5 | M62: =VLOOKUP(D62,DROPDOWN!B:C,2,0) -> 4 | N62: =VLOOKUP(K62,$AQ$3:$AR$12,2,0) -> X81:AP92 | O62: =INDEX(INDIRECT(N62),L62,M62) -> 33631.75 | R62: =IF('CALCULATOR CARE V6'!I6="yes",INDEX('ADD SI'!$W$9:$AB$13,MATCH('CARE SHEET'!Q50,'ADD SI'!$W$9:$W$13,0),MATCH('CARE SHEET'!$T$3,'ADD SI'!$W$9:$AB$9,0)),0) -> 0
A63: 46-50 | B63: 46 Years | C63: 50 Years | D63: 5 | E63: FLOATER | F63: 2 | G63: 2 | H63: 0 | I63: 1 | J63: Zone 1 | K63: =G63&"+"&H63 -> 2+0 | L63: =VLOOKUP(A63,'ZONE 1 PREMIUM'!$A$4:$N$16,14,0) -> 6 | M63: =VLOOKUP(D63,DROPDOWN!B:C,2,0) -> 4 | N63: =VLOOKUP(K63,$AQ$3:$AR$12,2,0) -> X81:AP92 | O63: =INDEX(INDIRECT(N63),L63,M63) -> 42558.05 | R63: =IF('CALCULATOR CARE V6'!I7="yes",INDEX('ADD SI'!$W$9:$AB$13,MATCH('CARE SHEET'!Q51,'ADD SI'!$W$9:$W$13,0),MATCH('CARE SHEET'!$T$3,'ADD SI'!$W$9:$AB$9,0)),0) -> 0
A64: 51-55 | B64: 51 Years | C64: 55 Years | D64: 5 | E64: FLOATER | F64: 2 | G64: 2 | H64: 0 | I64: 1 | J64: Zone 1 | K64: =G64&"+"&H64 -> 2+0 | L64: =VLOOKUP(A64,'ZONE 1 PREMIUM'!$A$4:$N$16,14,0) -> 7 | M64: =VLOOKUP(D64,DROPDOWN!B:C,2,0) -> 4 | N64: =VLOOKUP(K64,$AQ$3:$AR$12,2,0) -> X81:AP92 | O64: =INDEX(INDIRECT(N64),L64,M64) -> 55824.45 | R64: =IF('CALCULATOR CARE V6'!I8="yes",INDEX('ADD SI'!$W$9:$AB$13,MATCH('CARE SHEET'!Q52,'ADD SI'!$W$9:$W$13,0),MATCH('CARE SHEET'!$T$3,'ADD SI'!$W$9:$AB$9,0)),0) -> 0 | X64: 1A4C | Y64: Care 3 | AA64: Care 4 | AD64: Care 5 | AI64: Care 6 | AL64: Care 7 | AT64: 1A4C | AV64: Care 3 | AX64: Care 4 | BA64: Care 5 | BF64: Care 6 | BI64: Care 7 | BQ64: 1A4C | BS64: Care 3 | BU64: Care 4 | BX64: Care 5 | CC64: Care 6 | CF64: Care 7 | CN64: 1A4C | CP64: Care 3 | CR64: Care 4 | CU64: Care 5 | CZ64: Care 6 | DC64: Care 7
A65: 56-60 | B65: 56 Years | C65: 60 Years | D65: 5 | E65: FLOATER | F65: 2 | G65: 2 | H65: 0 | I65: 1 | J65: Zone 1 | K65: =G65&"+"&H65 -> 2+0 | L65: =VLOOKUP(A65,'ZONE 1 PREMIUM'!$A$4:$N$16,14,0) -> 8 | M65: =VLOOKUP(D65,DROPDOWN!B:C,2,0) -> 4 | N65: =VLOOKUP(K65,$AQ$3:$AR$12,2,0) -> X81:AP92 | O65: =INDEX(INDIRECT(N65),L65,M65) -> 78168.95 | R65: =R59+SUM(R60:R64)*97.5% -> #N/A | X65: Age-Band/ SI | Y65: 3L | Z65: 4L | AA65: 5L | AB65: 7L | AC65: 10L | AD65: 15L | AE65: 20L | AF65: 25L | AG65: 30L | AH65: 40L | AI65: 50L | AJ65: 60L | AK65: 75L | AL65: 1 CR | AM65: 1.5 CR | AN65: 2 CR | AO65: 3 CR | AP65: 6 CR | AU65: Age-Band/ SI | AV65: 3L | AW65: 4L | AX65: 5L | AY65: 7L | AZ65: 10L | BA65: 15L | BB65: 20L | BC65: 25L | BD65: 30L | BE65: 40L | BF65: 50L | BG65: 60L | BH65: 75L | BI65: 1 CR | BJ65: 1.5 CR | BK65: 2 CR | BL65: 3 CR | BM65: 6 CR | BR65: Age-Band/ SI | BS65: 3L | BT65: 4L | BU65: 5L | BV65: 7L | BW65: 10L | BX65: 15L | BY65: 20L | BZ65: 25L | CA65: 30L | CB65: 40L | CC65: 50L | CD65: 60L | CE65: 75L | CF65: 1 CR | CG65: 1.5 CR | CH65: 2 CR | CI65: 3 CR | CJ65: 6 CR | CO65: Age-Band/ SI | CP65: 3L | CQ65: 4L | CR65: 5L | CS65: 7L | CT65: 10L | CU65: 15L | CV65: 20L | CW65: 25L | CX65: 30L | CY65: 40L | CZ65: 50L | DA65: 60L | DB65: 75L | DC65: 1 CR | DD65: 1.5 CR | DE65: 2 CR | DF65: 3 CR | DG65: 6 CR
A66: 61-65 | B66: 61 Years | C66: 65 Years | D66: 5 | E66: FLOATER | F66: 2 | G66: 2 | H66: 0 | I66: 1 | J66: Zone 1 | K66: =G66&"+"&H66 -> 2+0 | L66: =VLOOKUP(A66,'ZONE 1 PREMIUM'!$A$4:$N$16,14,0) -> 9 | M66: =VLOOKUP(D66,DROPDOWN!B:C,2,0) -> 4 | N66: =VLOOKUP(K66,$AQ$3:$AR$12,2,0) -> X81:AP92 | O66: =INDEX(INDIRECT(N66),L66,M66) -> 108993.55 | X66: 18-24 | Y66: 21217.5 | Z66: 25639.25 | AA66: 30721.1 | AB66: 33516.75 | AC66: 36078.95 | AD66: 45974.7 | AE66: 50263.05 | AF66: 53953.4 | AG66: 60200.2 | AH66: 74776.45 | AI66: 130538.8 | AJ66: 161928.05 | AK66: 197114.6 | AL66: 277400.7 | AM66: 333478.15 | AN66: 395200.95 | AO66: 466560.75 | AP66: 630795.7 | AU66: 18-24 | AV66: 18819 | AW66: 22736.25 | AX66: 27250.875 | AY66: 29725.875 | AZ66: 31995 | BA66: 40772.25 | BB66: 44569.125 | BC66: 47838.375 | BD66: 53368.875 | BE66: 66277.125 | BF66: 115656.75 | BG66: 143452.12 | BH66: 174611.25 | BI66: 246570.75 | BJ66: 296228.25 | BK66: 350886.38 | BL66: 414077.62 | BM66: 559512 | BR66: 18-24 | BS66: 17359.1 | BT66: 20968.2 | BU66: 25136.1 | BV66: 27416.4 | BW66: 29508.6 | BX66: 37604.6 | BY66: 41103.7 | BZ66: 44115.5 | CA66: 49212.9 | CB66: 61107.2 | CC66: 106612 | CD66: 132225.5 | CE66: 160939.9 | CF66: 227705.5 | CG66: 273466.6 | CH66: 323834.5 | CI66: 382067.4 | CJ66: 516088.1 | CO66: 18-24 | CP66: 15978.31 | CQ66: 19297.36 | CR66: 23137.43 | CS66: 25234.59 | CT66: 27158.44 | CU66: 34609.68 | CV66: 37828.45 | CW66: 40597.05 | CX66: 45284.05 | CY66: 56222.2 | CZ66: 98064.03 | DA66: 121616.75 | DB66: 148019.82 | DC66: 209872.96 | DD66: 251951.32 | DE66: 298266.51 | DF66: 351812.76 | DG66: 475047.07
A67: 66-70 | B67: 66 Years | C67: 70 Years | D67: 5 | E67: FLOATER | F67: 2 | G67: 2 | H67: 0 | I67: 1 | J67: Zone 1 | K67: =G67&"+"&H67 -> 2+0 | L67: =VLOOKUP(A67,'ZONE 1 PREMIUM'!$A$4:$N$16,14,0) -> 10 | M67: =VLOOKUP(D67,DROPDOWN!B:C,2,0) -> 4 | N67: =VLOOKUP(K67,$AQ$3:$AR$12,2,0) -> X81:AP92 | O67: =INDEX(INDIRECT(N67),L67,M67) -> 153867.7 | X67: 25-35 | Y67: 22238.7 | Z67: 26682.3 | AA67: 32124.1 | AB67: 35048.55 | AC67: 37733.8 | AD67: 48078.05 | AE67: 52460.7 | AF67: 56233.85 | AG67: 62745.15 | AH67: 77915.95 | AI67: 137106.45 | AJ67: 170525.45 | AK67: 208335.15 | AL67: 288502.8 | AM67: 347612.8 | AN67: 412813.2 | AO67: 488295.75 | AP67: 661849.15 | AU67: 25-35 | AV67: 19731.375 | AW67: 23666.625 | AX67: 28506.375 | AY67: 31095 | AZ67: 33473.25 | BA67: 42654.375 | BB67: 46534.5 | BC67: 49875.75 | BD67: 55642.5 | BE67: 69076.125 | BF67: 121491 | BG67: 151084.12 | BH67: 184566.38 | BI67: 256404.38 | BJ67: 308747.25 | BK67: 366484.5 | BL67: 433327.5 | BM67: 587013.75 | BR67: 25-35 | BS67: 18203.9 | BT67: 21829.5 | BU67: 26299.9 | BV67: 28685.8 | BW67: 30877 | BX67: 39348.1 | BY67: 42924.2 | BZ67: 46003.1 | CA67: 51317.2 | CB67: 63696.6 | CC67: 111997.6 | CD67: 139268.8 | CE67: 170122.7 | CF67: 236769.5 | CG67: 285004.5 | CH67: 338210.4 | CI67: 399807.1 | CJ67: 541432.1 | CO67: 25-35 | CP67: 16758.75 | CQ67: 20093.06 | CR67: 24215.44 | CS67: 26408.52 | CT67: 28423.93 | CU67: 36223.97 | CV67: 39512.5 | CW67: 42343.23 | CX67: 47229.7 | CY67: 58613.66 | CZ67: 103026.8 | DA67: 128103.34 | DB67: 156473.86 | DC67: 218208.19 | DD67: 262562.47 | DE67: 311487.12 | DF67: 368126.79 | DG67: 498354.54
A68: 71-75 | B68: 71 Years | C68: 75 Years | D68: 5 | E68: FLOATER | F68: 2 | G68: 2 | H68: 0 | I68: 1 | J68: Zone 1 | K68: =G68&"+"&H68 -> 2+0 | L68: =VLOOKUP(A68,'ZONE 1 PREMIUM'!$A$4:$N$16,14,0) -> 11 | M68: =VLOOKUP(D68,DROPDOWN!B:C,2,0) -> 4 | N68: =VLOOKUP(K68,$AQ$3:$AR$12,2,0) -> X81:AP92 | O68: =INDEX(INDIRECT(N68),L68,M68) -> 191587.7 | X68: 36-40 | Y68: 25301.15 | Z68: 30562.4 | AA68: 37112.8 | AB68: 40522.55 | AC68: 43659.75 | AD68: 55673.8 | AE68: 60898.25 | AF68: 65429.25 | AG68: 73061.8 | AH68: 90798.25 | AI68: 151142.2 | AJ68: 190198.5 | AK68: 234465.45 | AL68: 317566.75 | AM68: 386820.9 | AN68: 463515.55 | AO68: 552523.25 | AP68: 756866.75 | AU68: 36-40 | AV68: 22444.875 | AW68: 27103.5 | AX68: 32926.5 | AY68: 35946 | AZ68: 38724.75 | BA68: 49385.25 | BB68: 54012.375 | BC68: 58025.25 | BD68: 64783.125 | BE68: 80489.25 | BF68: 133925.62 | BG68: 168511.5 | BH68: 207711 | BI68: 281945.25 | BJ68: 343271.25 | BK68: 411187.5 | BL68: 490006.12 | BM68: 670959 | BR68: 36-40 | BS68: 20703.1 | BT68: 24996.4 | BU68: 30375.4 | BV68: 33158.4 | BW68: 35718.1 | BX68: 45554.3 | BY68: 49817.9 | BZ68: 53516.1 | CA68: 59744.3 | CB68: 74217 | CC68: 123459.6 | CD68: 155332.1 | CE68: 191455 | CF68: 260201.7 | CG68: 316715.3 | CH68: 379300.9 | CI68: 451933.9 | CJ68: 618686.2 | CO68: 36-40 | CP68: 19058.65 | CQ68: 23006.63 | CR68: 27963.95 | CS68: 30523.27 | CT68: 32876.58 | CU68: 41934.48 | CV68: 45854.12 | CW68: 49254.92 | CX68: 54981.78 | CY68: 68289.59 | CZ68: 113570.37 | DA68: 142877.2 | DB68: 176092.77 | DC68: 239651.76 | DD68: 291616.42 | DE68: 349166.24 | DF68: 415953.81 | DG68: 569286.29
A69: 75+ | B69: >75 Years | D69: 5 | E69: FLOATER | F69: 2 | G69: 2 | H69: 0 | I69: 1 | J69: Zone 1 | K69: =G69&"+"&H69 -> 2+0 | L69: =VLOOKUP(A69,'ZONE 1 PREMIUM'!$A$4:$N$16,14,0) -> 12 | M69: =VLOOKUP(D69,DROPDOWN!B:C,2,0) -> 4 | N69: =VLOOKUP(K69,$AQ$3:$AR$12,2,0) -> X81:AP92 | O69: =INDEX(INDIRECT(N69),L69,M69) -> 244326.7 | X69: 41-45 | Y69: 27609.2 | Z69: 33502.95 | AA69: 40958.4 | AB69: 44756.85 | AC69: 48257.45 | AD69: 61543.4 | AE69: 67348.6 | AF69: 72369.5 | AG69: 80872.6 | AH69: 100580.15 | AI69: 165880.6 | AJ69: 209502.4 | AK69: 259035.2 | AL69: 338448.45 | AM69: 415513.4 | AN69: 501148.15 | AO69: 600738.15 | AP69: 829056.85 | AU69: 41-45 | AV69: 24489 | AW69: 29707.875 | AX69: 36334.125 | AY69: 39697.875 | AZ69: 42798.375 | BA69: 54588.375 | BB69: 59728.5 | BC69: 64174.5 | BD69: 71704.125 | BE69: 89156.25 | BF69: 146981.25 | BG69: 185610.38 | BH69: 229473 | BI69: 300208.5 | BJ69: 368451 | BK69: 444283.88 | BL69: 532473.75 | BM69: 734656.5 | BR69: 41-45 | BS69: 22588.5 | BT69: 27397.7 | BU69: 33517 | BV69: 36616.8 | BW69: 39473.5 | BX69: 50351.4 | BY69: 55088 | BZ69: 59185.5 | CA69: 66124.3 | CB69: 82206.3 | CC69: 135493.6 | CD69: 171090.7 | CE69: 211510.2 | CF69: 276912.9 | CG69: 339798.8 | CH69: 409679.6 | CI69: 490948.7 | CJ69: 677264.5 | CO69: 41-45 | CP69: 20791.75 | CQ69: 25213.88 | CR69: 30854.63 | CS69: 33704.98 | CT69: 36331.88 | CU69: 46346.8 | CV69: 50702.44 | CW69: 54470.57 | CX69: 60850.34 | CY69: 75638.37 | CZ69: 124637.14 | DA69: 157369.84 | DB69: 194536.66 | DC69: 254895.41 | DD69: 312721 | DE69: 376978.68 | DF69: 451706.9 | DG69: 623028.74
A70: 18-24 | B70: 18 Years | C70: 24 Years | D70: 5 | E70: FLOATER | F70: 3 | G70: 2 | H70: 1 | I70: 1 | J70: Zone 1 | K70: =G70&"+"&H70 -> 2+1 | L70: =VLOOKUP(A70,'ZONE 1 PREMIUM'!$A$4:$N$16,14,0) -> 2 | M70: =VLOOKUP(D70,DROPDOWN!B:C,2,0) -> 4 | N70: =VLOOKUP(K70,$AQ$3:$AR$12,2,0) -> X98:AP109 | O70: =INDEX(INDIRECT(N70),L70,M70) -> 27904.75 | T70: =R71*T12*S17*S27 -> 149487.64 | U70: =S71*U12*S17*S27 -> 149487.64 | X70: 46-50 | Y70: 32947.5 | Z70: 40113.15 | AA70: 49339.6 | AB70: 55701.4 | AC70: 60101.3 | AD70: 74704 | AE70: 81867.35 | AF70: 88096.9 | AG70: 98507.85 | AH70: 122575.05 | AI70: 199135.15 | AJ70: 252761.95 | AK70: 313803.95 | AL70: 395836.9 | AM70: 489808 | AN70: 594552.3 | AO70: 716605.25 | AP70: 996026.5 | AU70: 46-50 | AV70: 29224.125 | AW70: 35570.25 | AX70: 43772.625 | AY70: 49405.5 | AZ70: 53302.5 | BA70: 66265.875 | BB70: 72609.75 | BC70: 78125.625 | BD70: 87345 | BE70: 108657 | BF70: 176452.88 | BG70: 223941.38 | BH70: 277996.5 | BI70: 350933.62 | BJ70: 434147.62 | BK70: 526901.62 | BL70: 634983.75 | BM70: 882419.62 | BR70: 46-50 | BS70: 26955.5 | BT70: 32804.2 | BU70: 40379.9 | BV70: 45570.8 | BW70: 49162.3 | BX70: 61125.9 | BY70: 66971.3 | BZ70: 72054.4 | CA70: 80549.7 | CB70: 100190.2 | CC70: 162664.7 | CD70: 206426 | CE70: 256238.4 | CF70: 323607.9 | CG70: 400290 | CH70: 485765.5 | CI70: 585365 | CJ70: 813381.8 | CO70: 46-50 | CP70: 24812.76 | CQ70: 30189.73 | CR70: 37173.36 | CS70: 41946.47 | CT70: 45249.17 | CU70: 56266.89 | CV70: 61641.68 | CW70: 66316.69 | CX70: 74127.63 | CY70: 92187.84 | CZ70: 149635.2 | DA70: 189874.73 | DB70: 235678.71 | DC70: 297782.55 | DD70: 368294.65 | DE70: 446891.28 | DF70: 538475.26 | DG70: 748142.21
A71: 25-35 | B71: 25 Years | C71: 35 Years | D71: 5 | E71: FLOATER | F71: 3 | G71: 2 | H71: 1 | I71: 1 | J71: Zone 1 | K71: =G71&"+"&H71 -> 2+1 | L71: =VLOOKUP(A71,'ZONE 1 PREMIUM'!$A$4:$N$16,14,0) -> 3 | M71: =VLOOKUP(D71,DROPDOWN!B:C,2,0) -> 4 | N71: =VLOOKUP(K71,$AQ$3:$AR$12,2,0) -> X98:AP109 | O71: =INDEX(INDIRECT(N71),L71,M71) -> 31052.3 | R71: =IF('CALCULATOR CARE V6'!B7='CARE SENIOR'!AP12,'CARE SENIOR'!AR12,'CARE SHEET'!S10)*'CALCULATOR CARE V6'!N3 -> 186859.54 | S71: =IF('CALCULATOR CARE V6'!B7='CARE SENIOR'!AP12,'CARE SENIOR'!AS12,'CARE SHEET'!T10)*'CALCULATOR CARE V6'!N3 -> 186859.54 | T71: 0.085 | X71: 51-55 | Y71: 39830.25 | Z71: 48662.25 | AA71: 59981.7 | AB71: 67852.3 | AC71: 73269.95 | AD71: 90983.4 | AE71: 99880.95 | AF71: 107656.1 | AG71: 120475.15 | AH71: 150052 | AI71: 249429.25 | AJ71: 315670.4 | AK71: 391200.1 | AL71: 486431.6 | AM71: 602900.15 | AN71: 732914.55 | AO71: 884582.3 | AP71: 1231395.8 | AU71: 51-55 | AV71: 35318.25 | AW71: 43139.25 | AX71: 53196.75 | AY71: 60167.25 | AZ71: 64965.375 | BA71: 80685 | BB71: 88564.5 | BC71: 95448.375 | BD71: 106800.75 | BE71: 132993 | BF71: 220993.88 | BG71: 279652.5 | BH71: 346536 | BI71: 431114.62 | BJ71: 534250.12 | BK71: 649382.62 | BL71: 783688.5 | BM71: 1090802.2 | BR71: 51-55 | BS71: 32571 | BT71: 39778.2 | BU71: 49065.5 | BV71: 55488.4 | BW71: 59909.3 | BX71: 74415 | BY71: 81675 | BZ71: 88019.8 | CA71: 98480.8 | CB71: 122617 | CC71: 203711.2 | CD71: 257766.3 | CE71: 319400.4 | CF71: 397471.8 | CG71: 492514 | CH71: 598610.1 | CI71: 722375.5 | CJ71: 1005386.8 | CO71: 51-55 | CP71: 29975 | CQ71: 36602.2 | CR71: 45159.79 | CS71: 51066.5 | CT71: 55132.2 | CU71: 68487.97 | CV71: 75164.22 | CW71: 80997.9 | CX71: 90617.15 | CY71: 112810.64 | CZ71: 187379.72 | DA71: 237084.81 | DB71: 293759.36 | DC71: 365678.65 | DD71: 453072.67 | DE71: 550630.94 | DF71: 664435.66 | DG71: 924672.07
A72: 36-40 | B72: 36 Years | C72: 40 Years | D72: 5 | E72: FLOATER | F72: 3 | G72: 2 | H72: 1 | I72: 1 | J72: Zone 1 | K72: =G72&"+"&H72 -> 2+1 | L72: =VLOOKUP(A72,'ZONE 1 PREMIUM'!$A$4:$N$16,14,0) -> 4 | M72: =VLOOKUP(D72,DROPDOWN!B:C,2,0) -> 4 | N72: =VLOOKUP(K72,$AQ$3:$AR$12,2,0) -> X98:AP109 | O72: =INDEX(INDIRECT(N72),L72,M72) -> 34685.15 | R72: =R71*T12*S13*U14*S15*T16*S17*S27+R18+T72+R20+R21+R22+R23+R24+R25+R26+R77+R79+R30+R32 -> 196386.14 | S72: =S71*U12*S13*V14*S15*U16*S17*S27+R18+U72+R20+R21+R22+R23+R24+R25+R26+S77+S79+R30+R32 -> 196386.14 | T72: =IF('CALCULATOR CARE V6'!B19="YES",T70*T71,0) -> 12706.449 | U72: =IF('CALCULATOR CARE V6'!B19="YES",U70*T71,0) -> 12706.449 | X72: 56-60 | Y72: 48640.4 | Z72: 59459.6 | AA72: 73499.95 | AB72: 81842.05 | AC72: 88452.25 | AD72: 110044.65 | AE72: 120870.75 | AF72: 129502.65 | AG72: 145046.05 | AH72: 180788.05 | AI72: 302711.05 | AJ72: 383138.6 | AK72: 475135.15 | AL72: 584906.1 | AM72: 726141.05 | AN72: 884160.25 | AO72: 1068795 | AP72: 1490302.2 | AU72: 56-60 | AV72: 43129.125 | AW72: 52709.625 | AX72: 65187 | AY72: 72573.75 | AZ72: 78428.25 | BA72: 97591.5 | BB72: 107178.75 | BC72: 114823.12 | BD72: 128586.38 | BE72: 160237.12 | BF72: 268203.38 | BG72: 339423.75 | BH72: 420890.62 | BI72: 518351.62 | BJ72: 643420.12 | BK72: 783351 | BL72: 946850.62 | BM72: 1320107.6 | BR72: 56-60 | BS72: 39773.8 | BT72: 48603.5 | BU72: 60123.8 | BV72: 66931.7 | BW72: 72326.1 | BX72: 90008.6 | BY72: 98842.7 | BZ72: 105887.1 | CA72: 118571.2 | CB72: 147737.7 | CC72: 247230.5 | CD72: 312862 | CE72: 387934.8 | CF72: 477881.8 | CG72: 593135.4 | CH72: 722084 | CI72: 872751 | CJ72: 1216714.4 | CO72: 56-60 | CP72: 36603.29 | CQ72: 44721.61 | CR72: 55339.3 | CS72: 61598.08 | CT72: 66558.67 | CU72: 82841.09 | CV72: 90965.95 | CW72: 97442.73 | CX72: 109105.73 | CY72: 135925.18 | CZ72: 227411.06 | DA72: 287761.09 | DB72: 356791.88 | DC72: 439637.33 | DD72: 545615.85 | DE72: 664187.14 | DF72: 802729.41 | DG72: 1119012.5
A73: 41-45 | B73: 41 Years | C73: 45 Years | D73: 5 | E73: FLOATER | F73: 3 | G73: 2 | H73: 1 | I73: 1 | J73: Zone 1 | K73: =G73&"+"&H73 -> 2+1 | L73: =VLOOKUP(A73,'ZONE 1 PREMIUM'!$A$4:$N$16,14,0) -> 5 | M73: =VLOOKUP(D73,DROPDOWN!B:C,2,0) -> 4 | N73: =VLOOKUP(K73,$AQ$3:$AR$12,2,0) -> X98:AP109 | O73: =INDEX(INDIRECT(N73),L73,M73) -> 39630.15 | X73: 61-65 | Y73: 60227.8 | Z73: 73667.85 | AA73: 91234.1 | AB73: 104218.75 | AC73: 112793.15 | AD73: 138569.25 | AE73: 152310.6 | AF73: 162772.15 | AG73: 182567.1 | AH73: 227897.8 | AI73: 385424.8 | AJ73: 488045.05 | AK73: 605882.1 | AL73: 735077.7 | AM73: 914643.3 | AN73: 1116125.6 | AO73: 1352032 | AP73: 1889482.2 | AU73: 61-65 | AV73: 53391.375 | AW73: 65292.75 | AX73: 80893.125 | AY73: 92391.75 | AZ73: 99984.375 | BA73: 122854.5 | BB73: 135022.5 | BC73: 144286.88 | BD73: 161815.5 | BE73: 201957.75 | BF73: 341452.12 | BG73: 432326.25 | BH73: 536674.5 | BI73: 651336.75 | BJ73: 810347.62 | BK73: 988765.88 | BL73: 1197668.2 | BM73: 1673596.1 | BR73: 61-65 | BS73: 49231.6 | BT73: 60198.6 | BU73: 74598.7 | BV73: 85195 | BW73: 92191 | BX73: 113290.1 | BY73: 124503.5 | BZ73: 133040.6 | CA73: 149194.1 | CB73: 186186 | CC73: 314732 | CD73: 398475 | CE73: 494632.6 | CF73: 600431.7 | CG73: 746962.7 | CH73: 911378.6 | CI73: 1103886.3 | CJ73: 1542462.9 | CO73: 61-65 | CP73: 45300.4 | CQ73: 55385.08 | CR73: 68650.38 | CS73: 78393.89 | CT73: 84827.07 | CU73: 104251.96 | CV73: 114563.36 | CW73: 122413.54 | CX73: 137265.88 | CY73: 171280.42 | CZ73: 289483.29 | DA73: 366485.25 | DB73: 454906.05 | DC73: 552326.98 | DD73: 687065.15 | DE73: 838250.33 | DF73: 1015266.3 | DG73: 1418547.8
A74: 46-50 | B74: 46 Years | C74: 50 Years | D74: 5 | E74: FLOATER | F74: 3 | G74: 2 | H74: 1 | I74: 1 | J74: Zone 1 | K74: =G74&"+"&H74 -> 2+1 | L74: =VLOOKUP(A74,'ZONE 1 PREMIUM'!$A$4:$N$16,14,0) -> 6 | M74: =VLOOKUP(D74,DROPDOWN!B:C,2,0) -> 4 | N74: =VLOOKUP(K74,$AQ$3:$AR$12,2,0) -> X98:AP109 | O74: =INDEX(INDIRECT(N74),L74,M74) -> 49291.3 | R74: =R71*U14*S15*S17*S27 -> 149487.64 | S74: =S71*V14*S15*S17*S27 -> 149487.64 | X74: 66-70 | Y74: 74303.8 | Z74: 90981.1 | AA74: 112918.5 | AB74: 126343.6 | AC74: 136913.25 | AD74: 167441.15 | AE74: 184270.25 | AF74: 199060.4 | AG74: 223573.8 | AH74: 279481.05 | AI74: 467937.3 | AJ74: 594640.85 | AK74: 740675.9 | AL74: 899766.9 | AM74: 1122080.3 | AN74: 1372229.4 | AO74: 1665718.6 | AP74: 2332972.8 | AU74: 66-70 | AV74: 65856.375 | AW74: 80624.25 | AX74: 100095.75 | AY74: 111982.5 | AZ74: 121343.62 | BA74: 148421.25 | BB74: 163326.38 | BC74: 176423.62 | BD74: 198131.62 | BE74: 247638.38 | BF74: 414529.88 | BG74: 526729.5 | BH74: 656047.12 | BI74: 797140.12 | BJ74: 994003.88 | BK74: 1215518.6 | BL74: 1475412.8 | BM74: 2066286.4 | BR74: 66-70 | BS74: 60718.9 | BT74: 74328.1 | BU74: 92293.3 | BV74: 103248.2 | BW74: 111874.4 | BX74: 136849.9 | BY74: 150586.7 | BZ74: 162657 | CA74: 182660.5 | CB74: 228281.9 | CC74: 382079.5 | CD74: 485474 | CE74: 604642.5 | CF74: 734773.6 | CG74: 916187.8 | CH74: 1120318.1 | CI74: 1359814.5 | CJ74: 1904315.6 | CO74: 66-70 | CP74: 55863.59 | CQ74: 68376.79 | CR74: 84920.81 | CS74: 94993.5 | CT74: 102925.43 | CU74: 125914.62 | CV74: 138548.81 | CW74: 149646.1 | CX74: 168040.94 | CY74: 209990.68 | CZ74: 351416 | DA74: 446489.07 | DB74: 556067.86 | DC74: 675839.24 | DD74: 842653.93 | DE74: 1030356.3 | DF74: 1250579.9 | DG74: 1751262.7
A75: 51-55 | B75: 51 Years | C75: 55 Years | D75: 5 | E75: FLOATER | F75: 3 | G75: 2 | H75: 1 | I75: 1 | J75: Zone 1 | K75: =G75&"+"&H75 -> 2+1 | L75: =VLOOKUP(A75,'ZONE 1 PREMIUM'!$A$4:$N$16,14,0) -> 7 | M75: =VLOOKUP(D75,DROPDOWN!B:C,2,0) -> 4 | N75: =VLOOKUP(K75,$AQ$3:$AR$12,2,0) -> X98:AP109 | O75: =INDEX(INDIRECT(N75),L75,M75) -> 64167.7 | R75: =R74+R77 -> 149487.64 | S75: =S74+S77 -> 149487.64 | X75: 71-75 | Y75: 85692.25 | Z75: 105022.6 | AA75: 130604.35 | AB75: 146441 | AC75: 158874.8 | AD75: 193903.8 | AE75: 213576.85 | AF75: 230930.35 | AG75: 259681.5 | AH75: 325003.8 | AI75: 534394.65 | AJ75: 682219.1 | AK75: 853120.6 | AL75: 1046120.5 | AM75: 1306845 | AN75: 1600905.8 | AO75: 1946526.8 | AP75: 2730849.8 | AU75: 71-75 | AV75: 75942 | AW75: 93060 | AX75: 115758 | AY75: 129781.12 | AZ75: 140792.62 | BA75: 171857.25 | BB75: 189281.25 | BC75: 204648.75 | BD75: 230107.5 | BE75: 287952.75 | BF75: 473382 | BG75: 604284.75 | BH75: 755624.25 | BI75: 926740.12 | BJ75: 1157619.4 | BK75: 1418019.8 | BL75: 1724076 | BM75: 2418617.2 | BR75: 71-75 | BS75: 70012.8 | BT75: 85787.9 | BU75: 106728.6 | BV75: 119651.4 | BW75: 129797.8 | BX75: 158447.3 | BY75: 174507.3 | BZ75: 188667.6 | CA75: 212129.5 | CB75: 265434.4 | CC75: 436315 | CD75: 556944.3 | CE75: 696405.6 | CF75: 854202.8 | CG75: 1066962.6 | CH75: 1306926.5 | CI75: 1588963.2 | CJ75: 2228996 | CO75: 71-75 | CP75: 64410.28 | CQ75: 78914.91 | CR75: 98194.83 | CS75: 110076.92 | CT75: 119407.32 | CU75: 145775.51 | CV75: 160545.01 | CW75: 173566.15 | CX75: 195139.43 | CY75: 244154.55 | CZ75: 401287.86 | DA75: 512209.53 | DB75: 640448.03 | DC75: 785657.83 | DD75: 981295.39 | DE75: 1201947.4 | DF75: 1461287.8 | DG75: 2049814.8
A76: 56-60 | B76: 56 Years | C76: 60 Years | D76: 5 | E76: FLOATER | F76: 3 | G76: 2 | H76: 1 | I76: 1 | J76: Zone 1 | K76: =G76&"+"&H76 -> 2+1 | L76: =VLOOKUP(A76,'ZONE 1 PREMIUM'!$A$4:$N$16,14,0) -> 8 | M76: =VLOOKUP(D76,DROPDOWN!B:C,2,0) -> 4 | N76: =VLOOKUP(K76,$AQ$3:$AR$12,2,0) -> X98:AP109 | O76: =INDEX(INDIRECT(N76),L76,M76) -> 87155.05 | X76: 75+ | Y76: 109330.5 | Z76: 134100.35 | AA76: 167088.1 | AB76: 187911.15 | AC76: 204168.7 | AD76: 248305.7 | AE76: 273763.25 | AF76: 296313.6 | AG76: 333721.95 | AH76: 418317.1 | AI76: 674557.8 | AJ76: 865877.55 | AK76: 1087949.4 | AL76: 1345118.2 | AM76: 1684120.9 | AN76: 2067619.5 | AO76: 2519364.8 | AP76: 3542156.4 | AU76: 75+ | AV76: 96876 | AW76: 118810.12 | AX76: 148069.12 | AY76: 166507.88 | AZ76: 180904.5 | BA76: 220035.38 | BB76: 242582.62 | BC76: 262551.38 | BD76: 295677 | BE76: 370588.5 | BF76: 597505.5 | BG76: 766924.88 | BH76: 963576 | BI76: 1191521.2 | BJ76: 1491718.5 | BK76: 1831317.8 | BL76: 2231352 | BM76: 3137064.8 | BR76: 75+ | BS76: 89304.6 | BT76: 109518.2 | BU76: 136504.5 | BV76: 153496.2 | BW76: 166763.3 | BX76: 202846.6 | BY76: 223626.7 | BZ76: 242028.6 | CA76: 272554.7 | CB76: 341587.4 | CC76: 550698.5 | CD76: 706822.6 | CE76: 888039.9 | CF76: 1098209.2 | CG76: 1374846 | CH76: 1687793.8 | CI76: 2056432.4 | CJ76: 2891064 | CO76: 75+ | CP76: 82151.12 | CQ76: 100736.71 | CR76: 125575.63 | CS76: 141200.78 | CT76: 153400.06 | CU76: 186604.73 | CV76: 205713.52 | CW76: 222634.68 | CX76: 250704.36 | CY76: 314181.6 | CZ76: 506468.5 | DA76: 650028.04 | DB76: 816662.88 | DC76: 1010032.2 | DD76: 1264406.5 | DE76: 1552169.8 | DF76: 1891142.4 | DG76: 2658607
A77: 61-65 | B77: 61 Years | C77: 65 Years | D77: 5 | E77: FLOATER | F77: 3 | G77: 2 | H77: 1 | I77: 1 | J77: Zone 1 | K77: =G77&"+"&H77 -> 2+1 | L77: =VLOOKUP(A77,'ZONE 1 PREMIUM'!$A$4:$N$16,14,0) -> 9 | M77: =VLOOKUP(D77,DROPDOWN!B:C,2,0) -> 4 | N77: =VLOOKUP(K77,$AQ$3:$AR$12,2,0) -> X98:AP109 | O77: =INDEX(INDIRECT(N77),L77,M77) -> 118140.65 | R77: =IF('CALCULATOR CARE V6'!B28="YES",R74*'CARE SHEET'!R28,0) -> 0 | S77: =IF('CALCULATOR CARE V6'!B28="YES",S74*'CARE SHEET'!R28,0) -> 0
A78: 66-70 | B78: 66 Years | C78: 70 Years | D78: 5 | E78: FLOATER | F78: 3 | G78: 2 | H78: 1 | I78: 1 | J78: Zone 1 | K78: =G78&"+"&H78 -> 2+1 | L78: =VLOOKUP(A78,'ZONE 1 PREMIUM'!$A$4:$N$16,14,0) -> 10 | M78: =VLOOKUP(D78,DROPDOWN!B:C,2,0) -> 4 | N78: =VLOOKUP(K78,$AQ$3:$AR$12,2,0) -> X98:AP109 | O78: =INDEX(INDIRECT(N78),L78,M78) -> 159565.95 | R78: =R74+R77 -> 149487.64 | S78: =S74+S77 -> 149487.64
A79: 71-75 | B79: 71 Years | C79: 75 Years | D79: 5 | E79: FLOATER | F79: 3 | G79: 2 | H79: 1 | I79: 1 | J79: Zone 1 | K79: =G79&"+"&H79 -> 2+1 | L79: =VLOOKUP(A79,'ZONE 1 PREMIUM'!$A$4:$N$16,14,0) -> 11 | M79: =VLOOKUP(D79,DROPDOWN!B:C,2,0) -> 4 | N79: =VLOOKUP(K79,$AQ$3:$AR$12,2,0) -> X98:AP109 | O79: =INDEX(INDIRECT(N79),L79,M79) -> 195995.65 | R79: =IF('CALCULATOR CARE V6'!B29="YES",R78*R29,0) -> 0 | S79: =IF('CALCULATOR CARE V6'!B29="YES",S78*R29,0) -> 0 | X79: 2A
A80: 75+ | B80: >75 Years | D80: 5 | E80: FLOATER | F80: 3 | G80: 2 | H80: 1 | I80: 1 | J80: Zone 1 | K80: =G80&"+"&H80 -> 2+1 | L80: =VLOOKUP(A80,'ZONE 1 PREMIUM'!$A$4:$N$16,14,0) -> 12 | M80: =VLOOKUP(D80,DROPDOWN!B:C,2,0) -> 4 | N80: =VLOOKUP(K80,$AQ$3:$AR$12,2,0) -> X98:AP109 | O80: =INDEX(INDIRECT(N80),L80,M80) -> 248555.25 | Y80: Care 3 | AA80: Care 4 | AD80: Care 5 | AI80: Care 6 | AL80: Care 7 | AT80: 2A | AV80: Care 3 | AX80: Care 4 | BA80: Care 5 | BF80: Care 6 | BI80: Care 7 | BQ80: 2A | BS80: Care 3 | BU80: Care 4 | BX80: Care 5 | CC80: Care 6 | CF80: Care 7 | CN80: 2A | CP80: Care 3 | CR80: Care 4 | CU80: Care 5 | CZ80: Care 6 | DC80: Care 7
A81: 18-24 | B81: 18 Years | C81: 24 Years | D81: 5 | E81: FLOATER | F81: 4 | G81: 2 | H81: 2 | I81: 1 | J81: Zone 1 | K81: =G81&"+"&H81 -> 2+2 | L81: =VLOOKUP(A81,'ZONE 1 PREMIUM'!$A$4:$N$16,14,0) -> 2 | M81: =VLOOKUP(D81,DROPDOWN!B:C,2,0) -> 4 | N81: =VLOOKUP(K81,$AQ$3:$AR$12,2,0) -> X113:AP124 | O81: =INDEX(INDIRECT(N81),L81,M81) -> 32672.65 | X81: Age-Band/ SI | Y81: 3L | Z81: 4L | AA81: 5L | AB81: 7L | AC81: 10L | AD81: 15L | AE81: 20L | AF81: 25L | AG81: 30L | AH81: 40L | AI81: 50L | AJ81: 60L | AK81: 75L | AL81: 1 CR | AM81: 1.5 CR | AN81: 2 CR | AO81: 3 CR | AP81: 6 CR | AU81: Age-Band/ SI | AV81: 3L | AW81: 4L | AX81: 5L | AY81: 7L | AZ81: 10L | BA81: 15L | BB81: 20L | BC81: 25L | BD81: 30L | BE81: 40L | BF81: 50L | BG81: 60L | BH81: 75L | BI81: 1 CR | BJ81: 1.5 CR | BK81: 2 CR | BL81: 3 CR | BM81: 6 CR | BR81: Age-Band/ SI | BS81: 3L | BT81: 4L | BU81: 5L | BV81: 7L | BW81: 10L | BX81: 15L | BY81: 20L | BZ81: 25L | CA81: 30L | CB81: 40L | CC81: 50L | CD81: 60L | CE81: 75L | CF81: 1 CR | CG81: 1.5 CR | CH81: 2 CR | CI81: 3 CR | CJ81: 6 CR | CO81: Age-Band/ SI | CP81: 3L | CQ81: 4L | CR81: 5L | CS81: 7L | CT81: 10L | CU81: 15L | CV81: 20L | CW81: 25L | CX81: 30L | CY81: 40L | CZ81: 50L | DA81: 60L | DB81: 75L | DC81: 1 CR | DD81: 1.5 CR | DE81: 2 CR | DF81: 3 CR | DG81: 6 CR
A82: 25-35 | B82: 25 Years | C82: 35 Years | D82: 5 | E82: FLOATER | F82: 4 | G82: 2 | H82: 2 | I82: 1 | J82: Zone 1 | K82: =G82&"+"&H82 -> 2+2 | L82: =VLOOKUP(A82,'ZONE 1 PREMIUM'!$A$4:$N$16,14,0) -> 3 | M82: =VLOOKUP(D82,DROPDOWN!B:C,2,0) -> 4 | N82: =VLOOKUP(K82,$AQ$3:$AR$12,2,0) -> X113:AP124 | O82: =INDEX(INDIRECT(N82),L82,M82) -> 35733.95 | X82: 18-24 | Y82: 15155.85 | Z82: 18627.7 | AA82: 22973.55 | AB82: 25042.4 | AC82: 26942.2 | AD82: 33865.2 | AE82: 37247.35 | AF82: 40223.55 | AG82: 44833.9 | AH82: 55563.4 | AI82: 115870.55 | AJ82: 138736 | AK82: 164454.6 | AL82: 228914.4 | AM82: 271858.85 | AN82: 319432.05 | AO82: 374643.55 | AP82: 501437.95 | AU82: 18-24 | AV82: 13457.25 | AW82: 16531.875 | AX82: 20409.75 | AY82: 22241.25 | AZ82: 23923.125 | BA82: 30083.625 | BB82: 33078.375 | BC82: 35714.25 | BD82: 39795.75 | BE82: 49297.5 | BF82: 102701.25 | BG82: 122950.12 | BH82: 145724.62 | BI82: 202928.62 | BJ82: 240958.12 | BK82: 283084.88 | BL82: 331976.25 | BM82: 444255.75 | BR82: 18-24 | BS82: 12421.2 | BT82: 15253.7 | BU82: 18841.9 | BV82: 20530.4 | BW82: 22080.3 | BX82: 27771.7 | BY82: 30532.7 | BZ82: 32961.5 | CA82: 36722.4 | CB82: 45478.4 | CC82: 94691.3 | CD82: 113350.6 | CE82: 134337.5 | CF82: 187117.7 | CG82: 222162.6 | CH82: 260982.7 | CI82: 306037.6 | CJ82: 409505.8 | CO82: 18-24 | CP82: 11440.64 | CQ82: 14045.74 | CR82: 17360.43 | CS82: 18912.59 | CT82: 20338.31 | CU82: 25587.75 | CV82: 28125.27 | CW82: 30358.68 | CX82: 33817.25 | CY82: 41869.08 | CZ82: 87121.52 | DA82: 104279.21 | DB82: 123576.57 | DC82: 172175.31 | DD82: 204400.07 | DE82: 240096.48 | DF82: 281525.2 | DG82: 376666.94
A83: 36-40 | B83: 36 Years | C83: 40 Years | D83: 5 | E83: FLOATER | F83: 4 | G83: 2 | H83: 2 | I83: 1 | J83: Zone 1 | K83: =G83&"+"&H83 -> 2+2 | L83: =VLOOKUP(A83,'ZONE 1 PREMIUM'!$A$4:$N$16,14,0) -> 4 | M83: =VLOOKUP(D83,DROPDOWN!B:C,2,0) -> 4 | N83: =VLOOKUP(K83,$AQ$3:$AR$12,2,0) -> X113:AP124 | O83: =INDEX(INDIRECT(N83),L83,M83) -> 40105.1 | X83: 25-35 | Y83: 17531.75 | Z83: 21131.25 | AA83: 26207.35 | AB83: 28571.75 | AC83: 30747.55 | AD83: 38712.45 | AE83: 42351.05 | AF83: 45548.05 | AG83: 50773.65 | AH83: 62898.1 | AI83: 129868.35 | AJ83: 157108.4 | AK83: 188372.3 | AL83: 255949.75 | AM83: 305642.4 | AN83: 360860.8 | AO83: 425074.5 | AP83: 572296.35 | AU83: 25-35 | AV83: 15574.5 | AW83: 18761.625 | AX83: 23297.625 | AY83: 25390.125 | AZ83: 27317.25 | BA83: 34410.375 | BB83: 37632.375 | BC83: 40464 | BD83: 45091.125 | BE83: 55828.125 | BF83: 115132.5 | BG83: 139253.62 | BH83: 166938.75 | BI83: 226949.62 | BJ83: 270955.12 | BK83: 319852.12 | BL83: 376715.25 | BM83: 507084.75 | BR83: 25-35 | BS83: 14379.2 | BT83: 17315.1 | BU83: 21516 | BV83: 23445.4 | BW83: 25220.8 | BX83: 31777.9 | BY83: 34746.8 | BZ83: 37356 | CA83: 41619.6 | CB83: 51515.2 | CC83: 106164.3 | CD83: 128393.1 | CE83: 153905.4 | CF83: 209295.9 | CG83: 249847.4 | CH83: 294907.8 | CI83: 347308.5 | CJ83: 467446.1 | CO83: 25-35 | CP83: 13247.86 | CQ83: 15948.88 | CR83: 19832.55 | CS83: 21605.98 | CT83: 23238.8 | CU83: 29290.48 | CV83: 32019.84 | CW83: 34418.93 | CX83: 38339.66 | CY83: 47437.89 | CZ83: 97690.16 | DA83: 118129.84 | DB83: 141588.82 | DC83: 192611.72 | DD83: 229900.62 | DE83: 271333.7 | DF83: 319517.15 | DG83: 429987.56
A84: 41-45 | B84: 41 Years | C84: 45 Years | D84: 5 | E84: FLOATER | F84: 4 | G84: 2 | H84: 2 | I84: 1 | J84: Zone 1 | K84: =G84&"+"&H84 -> 2+2 | L84: =VLOOKUP(A84,'ZONE 1 PREMIUM'!$A$4:$N$16,14,0) -> 5 | M84: =VLOOKUP(D84,DROPDOWN!B:C,2,0) -> 4 | N84: =VLOOKUP(K84,$AQ$3:$AR$12,2,0) -> X113:AP124 | O84: =INDEX(INDIRECT(N84),L84,M84) -> 45392.8 | X84: 36-40 | Y84: 19407.4 | Z84: 23395.6 | AA84: 29059.35 | AB84: 31712.4 | AC84: 34159.6 | AD84: 43019.2 | AE84: 47055.7 | AF84: 50602.3 | AG84: 56465 | AH84: 70031.55 | AI84: 134730.55 | AJ84: 165436.7 | AK84: 200767 | AL84: 264695.5 | AM84: 319514.85 | AN84: 380609.75 | AO84: 451789 | AP84: 614761.25 | AU84: 36-40 | AV84: 17236.125 | AW84: 20767.5 | AX84: 25824.375 | AY84: 28173.375 | AZ84: 30341.25 | BA84: 38227.5 | BB84: 41801.625 | BC84: 44942.625 | BD84: 50133.375 | BE84: 62147.25 | BF84: 119440.12 | BG84: 146631.38 | BH84: 177917.62 | BI84: 234702 | BJ84: 283245.75 | BK84: 337347 | BL84: 400378.5 | BM84: 544695.75 | BR84: 36-40 | BS84: 15910.4 | BT84: 19165.3 | BU84: 23845.8 | BV84: 26010.6 | BW84: 28008.2 | BX84: 35296.8 | BY84: 38590.2 | BZ84: 41484.3 | CA84: 46268.2 | CB84: 57339.7 | CC84: 110136.4 | CD84: 135193.3 | CE84: 164024.3 | CF84: 216442.6 | CG84: 261177.4 | CH84: 311031.6 | CI84: 369117.1 | CJ84: 502108.2 | CO84: 36-40 | CP84: 14657.23 | CQ84: 17649.28 | CR84: 21975.49 | CS84: 23966.92 | CT84: 25802.48 | CU84: 32526.69 | CV84: 35555.8 | CW84: 38216.49 | CX84: 42615.73 | CY84: 52795.24 | CZ84: 101343.84 | DA84: 124384.26 | DB84: 150895.24 | DC84: 199187.69 | DD84: 240322.11 | DE84: 286164.24 | DF84: 339575.33 | DG84: 461863.52
A85: 46-50 | B85: 46 Years | C85: 50 Years | D85: 5 | E85: FLOATER | F85: 4 | G85: 2 | H85: 2 | I85: 1 | J85: Zone 1 | K85: =G85&"+"&H85 -> 2+2 | L85: =VLOOKUP(A85,'ZONE 1 PREMIUM'!$A$4:$N$16,14,0) -> 6 | M85: =VLOOKUP(D85,DROPDOWN!B:C,2,0) -> 4 | N85: =VLOOKUP(K85,$AQ$3:$AR$12,2,0) -> X113:AP124 | O85: =INDEX(INDIRECT(N85),L85,M85) -> 55753.15 | X85: 41-45 | Y85: 22403.15 | Z85: 27061.8 | AA85: 33631.75 | AB85: 36755.15 | AC85: 39643.95 | AD85: 49939.9 | AE85: 54544.5 | AF85: 58541.9 | AG85: 65418.9 | AH85: 81276.25 | AI85: 148309.75 | AJ85: 184546.25 | AK85: 226302.75 | AL85: 282847.1 | AM85: 345852.15 | AN85: 416303.45 | AO85: 498566.4 | AP85: 686570.7 | AU85: 41-45 | AV85: 19888.875 | AW85: 24014.25 | AX85: 29873.25 | AY85: 32639.625 | AZ85: 35197.875 | BA85: 44355.375 | BB85: 48433.5 | BC85: 51972.75 | BD85: 58063.5 | BE85: 72104.625 | BF85: 131464.12 | BG85: 163553.62 | BH85: 200530.12 | BI85: 250776 | BJ85: 306568.12 | BK85: 368955 | BL85: 441801 | BM85: 608284.12 | BR85: 41-45 | BS85: 18355.7 | BT85: 22157.3 | BU85: 27577 | BV85: 30125.7 | BW85: 32484.1 | BX85: 40944.2 | BY85: 44701.8 | BZ85: 47963.3 | CA85: 53575.5 | CB85: 66515.9 | CC85: 121216.7 | CD85: 150786.9 | CE85: 184861.6 | CF85: 231255.2 | CG85: 282669.2 | CH85: 340159.6 | CI85: 407288.2 | CJ85: 560706.3 | CO85: 41-45 | CP85: 16904.81 | CQ85: 20400.44 | CR85: 25406.81 | CS85: 27750.31 | CT85: 29918.32 | CU85: 37719.45 | CV85: 41174.75 | CW85: 44174.43 | CX85: 49334.49 | CY85: 61232.93 | CZ85: 111532.07 | DA85: 138723.21 | DB85: 170055.26 | DC85: 212807.24 | DD85: 260083.81 | DE85: 312947.72 | DF85: 374674.42 | DG85: 515746.58
A86: 51-55 | B86: 51 Years | C86: 55 Years | D86: 5 | E86: FLOATER | F86: 4 | G86: 2 | H86: 2 | I86: 1 | J86: Zone 1 | K86: =G86&"+"&H86 -> 2+2 | L86: =VLOOKUP(A86,'ZONE 1 PREMIUM'!$A$4:$N$16,14,0) -> 7 | M86: =VLOOKUP(D86,DROPDOWN!B:C,2,0) -> 4 | N86: =VLOOKUP(K86,$AQ$3:$AR$12,2,0) -> X113:AP124 | O86: =INDEX(INDIRECT(N86),L86,M86) -> 72176.3 | X86: 46-50 | Y86: 28238.25 | Z86: 34168.8 | AA86: 42558.05 | AB86: 48845.1 | AC86: 52751.65 | AD86: 64020.5 | AE86: 69930.35 | AF86: 75045.55 | AG86: 83968.4 | AH86: 104461.4 | AI86: 184336.95 | AJ86: 231707.75 | AK86: 286373 | AL86: 335080.1 | AM86: 415154.6 | AN86: 505011 | AO86: 610173.9 | AP86: 850067.35 | AU86: 46-50 | AV86: 25066.125 | AW86: 30318.75 | AX86: 37794.375 | AY86: 43362 | AZ86: 46822.5 | BA86: 56848.5 | BB86: 62082 | BC86: 66612.375 | BD86: 74514.375 | BE86: 92660.625 | BF86: 163392.75 | BG86: 205341.75 | BH86: 253749.38 | BI86: 297085.5 | BJ86: 367994.25 | BK86: 447564.38 | BL86: 540689.62 | BM86: 753122.25 | BR86: 46-50 | BS86: 23130.8 | BT86: 27970.8 | BU86: 34885.4 | BV86: 40016.9 | BW86: 43204.7 | BX86: 52470 | BY86: 57292.4 | BZ86: 61466.9 | CA86: 68748.9 | CB86: 85471.1 | CC86: 150651.6 | CD86: 189308.9 | CE86: 233917.2 | CF86: 273960.5 | CG86: 339303.8 | CH86: 412629.8 | CI86: 498446.3 | CJ86: 694207.8 | CO86: 46-50 | CP86: 21300.78 | CQ86: 25752.34 | CR86: 32136.47 | CS86: 36853.99 | CT86: 39786.09 | CU86: 48330.6 | CV86: 52765.81 | CW86: 56603.7 | CX86: 63299.57 | CY86: 78676.2 | CZ86: 138612.03 | DA86: 174158.02 | DB86: 215175.81 | DC86: 252106.1 | DD86: 312191.26 | DE86: 379616.48 | DF86: 458527.03 | DG86: 638533.99
A87: 56-60 | B87: 56 Years | C87: 60 Years | D87: 5 | E87: FLOATER | F87: 4 | G87: 2 | H87: 2 | I87: 1 | J87: Zone 1 | K87: =G87&"+"&H87 -> 2+2 | L87: =VLOOKUP(A87,'ZONE 1 PREMIUM'!$A$4:$N$16,14,0) -> 8 | M87: =VLOOKUP(D87,DROPDOWN!B:C,2,0) -> 4 | N87: =VLOOKUP(K87,$AQ$3:$AR$12,2,0) -> X113:AP124 | O87: =INDEX(INDIRECT(N87),L87,M87) -> 94680.65 | X87: 51-55 | Y87: 36929.95 | Z87: 44785.6 | AA87: 55824.45 | AB87: 65415.45 | AC87: 70746.85 | AD87: 84590.55 | AE87: 92543.95 | AF87: 99460.05 | AG87: 111455.7 | AH87: 138906.2 | AI87: 252881.55 | AJ87: 317072.25 | AK87: 391246.1 | AL87: 435833.9 | AM87: 542956.4 | AN87: 663478.7 | AO87: 804795.3 | AP87: 1126576.8 | AU87: 51-55 | AV87: 32767.875 | AW87: 39724.875 | AX87: 49552.875 | AY87: 58044.375 | AZ87: 62766 | BA87: 75078 | BB87: 82120.5 | BC87: 88245 | BD87: 98868.375 | BE87: 123176.25 | BF87: 224104.5 | BG87: 280947.38 | BH87: 346630.5 | BI87: 386362.12 | BJ87: 481222.12 | BK87: 587948.62 | BL87: 713089.12 | BM87: 998035.88 | BR87: 51-55 | BS87: 30231.3 | BT87: 36641 | BU87: 45725.9 | BV87: 53551.3 | BW87: 57901.8 | BX87: 69275.8 | BY87: 75765.8 | BZ87: 81408.8 | CA87: 91198.8 | CB87: 113598.1 | CC87: 206605.3 | CD87: 258988.4 | CE87: 319515.9 | CF87: 356260.3 | CG87: 443676.2 | CH87: 542026.1 | CI87: 657345.7 | CJ87: 919928.9 | CO87: 51-55 | CP87: 27833.15 | CQ87: 33727.87 | CR87: 42108.88 | CS87: 49305.06 | CT87: 53305.36 | CU87: 63791.16 | CV87: 69758.91 | CW87: 74948.4 | CX87: 83949.62 | CY87: 104547.35 | CZ87: 190069.84 | DA87: 238236.94 | DB87: 293893.43 | DC87: 327813.14 | DD87: 408194.1 | DE87: 498629.22 | DF87: 604668.78 | DG87: 846121.22
A88: 61-65 | B88: 61 Years | C88: 65 Years | D88: 5 | E88: FLOATER | F88: 4 | G88: 2 | H88: 2 | I88: 1 | J88: Zone 1 | K88: =G88&"+"&H88 -> 2+2 | L88: =VLOOKUP(A88,'ZONE 1 PREMIUM'!$A$4:$N$16,14,0) -> 9 | M88: =VLOOKUP(D88,DROPDOWN!B:C,2,0) -> 4 | N88: =VLOOKUP(K88,$AQ$3:$AR$12,2,0) -> X113:AP124 | O88: =INDEX(INDIRECT(N88),L88,M88) -> 124194.25 | X88: 56-60 | Y88: 51562.55 | Z88: 62643.95 | AA88: 78168.95 | AB88: 89254.95 | AC88: 96647.15 | AD88: 116546.75 | AE88: 127678.75 | AF88: 136216.35 | AG88: 152846.5 | AH88: 190756.25 | AI88: 351229.55 | AJ88: 440099.25 | AK88: 542986.3 | AL88: 600025.15 | AM88: 748733.95 | AN88: 916401.65 | AO88: 1113313.8 | AP88: 1560876.6 | AU88: 56-60 | AV88: 45740.25 | AW88: 55552.5 | AX88: 69364.125 | AY88: 79180.875 | AZ88: 85727.25 | BA88: 103412.25 | BB88: 113270.62 | BC88: 120831.75 | BD88: 135558 | BE88: 169126.88 | BF88: 311231.25 | BG88: 389928.38 | BH88: 481037.62 | BI88: 531857.25 | BJ88: 663544.12 | BK88: 812018.25 | BL88: 986389.88 | BM88: 1382719.5 | BR88: 56-60 | BS88: 42191.6 | BT88: 51234.7 | BU88: 63995.8 | BV88: 73042.2 | BW88: 79074.6 | BX88: 95405.2 | BY88: 104490.1 | BZ88: 111457.5 | CA88: 125028.2 | CB88: 155963.5 | CC88: 286914.1 | CD88: 359436 | CE88: 443394.6 | CF88: 490388.8 | CG88: 611740.8 | CH88: 748563.2 | CI88: 909250.1 | CJ88: 1274475.4 | CO88: 56-60 | CP88: 38838.88 | CQ88: 47154.49 | CR88: 58922.13 | CS88: 67241.01 | CT88: 72786.93 | CU88: 87838.74 | CV88: 96191.41 | CW88: 102598.43 | CX88: 115076.75 | CY88: 143522.48 | CZ88: 263934.78 | DA88: 330619.89 | DB88: 407822.41 | DC88: 451200.05 | DD88: 562786.62 | DE88: 688597.69 | DF88: 836353.73 | DG88: 1172187.1
A89: 66-70 | B89: 66 Years | C89: 70 Years | D89: 5 | E89: FLOATER | F89: 4 | G89: 2 | H89: 2 | I89: 1 | J89: Zone 1 | K89: =G89&"+"&H89 -> 2+2 | L89: =VLOOKUP(A89,'ZONE 1 PREMIUM'!$A$4:$N$16,14,0) -> 10 | M89: =VLOOKUP(D89,DROPDOWN!B:C,2,0) -> 4 | N89: =VLOOKUP(K89,$AQ$3:$AR$12,2,0) -> X113:AP124 | O89: =INDEX(INDIRECT(N89),L89,M89) -> 162243.15 | X89: 61-65 | Y89: 71704.8 | Z89: 87293.05 | AA89: 108993.55 | AB89: 126442.5 | AC89: 137105.3 | AD89: 164468.4 | AE89: 180459.15 | AF89: 191656.7 | AG89: 215382.35 | AH89: 269265.6 | AI89: 491305.3 | AJ89: 617386.7 | AK89: 763672.45 | AL89: 849095.6 | AM89: 1061558.1 | AN89: 1301613.7 | AO89: 1583995 | AP89: 2224666.9 | AU89: 61-65 | AV89: 63583.875 | AW89: 77387.625 | AX89: 96674.625 | AY89: 112126.5 | AZ89: 121568.62 | BA89: 145868.62 | BB89: 160029 | BC89: 169944.75 | BD89: 190954.12 | BE89: 238669.88 | BF89: 435292.88 | BG89: 546941.25 | BH89: 676481.62 | BI89: 752463 | BJ89: 940604.62 | BK89: 1153181.2 | BL89: 1403238.4 | BM89: 1970572.5 | BR89: 61-65 | BS89: 58639.9 | BT89: 71360.3 | BU89: 89170.4 | BV89: 103408.8 | BW89: 112109.8 | BX89: 134539.9 | BY89: 147589.2 | BZ89: 156726.9 | CA89: 176086.9 | CB89: 220058.3 | CC89: 401249.2 | CD89: 504135.5 | CE89: 623510.8 | CF89: 693705.1 | CG89: 867081.6 | CH89: 1062975.1 | CI89: 1293407.5 | CJ89: 1816216.6 | CO89: 61-65 | CP89: 53968.08 | CQ89: 65663.78 | CR89: 82078.09 | CS89: 95171.17 | CT89: 103171.77 | CU89: 123833.81 | CV89: 135832.53 | CW89: 144234.25 | CX89: 162037.22 | CY89: 202469.68 | CZ89: 369079.45 | DA89: 463686 | DB89: 573454.45 | DC89: 638178.65 | DD89: 797603.14 | DE89: 977732.18 | DF89: 1189620.6 | DG89: 1670356.3
A90: 71-75 | B90: 71 Years | C90: 75 Years | D90: 5 | E90: FLOATER | F90: 4 | G90: 2 | H90: 2 | I90: 1 | J90: Zone 1 | K90: =G90&"+"&H90 -> 2+2 | L90: =VLOOKUP(A90,'ZONE 1 PREMIUM'!$A$4:$N$16,14,0) -> 11 | M90: =VLOOKUP(D90,DROPDOWN!B:C,2,0) -> 4 | N90: =VLOOKUP(K90,$AQ$3:$AR$12,2,0) -> X113:AP124 | O90: =INDEX(INDIRECT(N90),L90,M90) -> 198956.9 | X90: 66-70 | Y90: 100959.65 | Z90: 123162.7 | AA90: 153867.7 | AB90: 175695.85 | AC90: 190773.5 | AD90: 228013.95 | AE90: 250632.15 | AF90: 269324.25 | AG90: 303118.15 | AH90: 379587.4 | AI90: 676517.4 | AJ90: 854597.2 | AK90: 1061708.8 | AL90: 1199439.6 | AM90: 1502487.6 | AN90: 1845624.6 | AO90: 2249920.9 | AP90: 3165567 | AU90: 66-70 | AV90: 89492.625 | AW90: 109155.38 | AX90: 136414.12 | AY90: 155745 | AZ90: 169095.38 | BA90: 202143.38 | BB90: 222177.38 | BC90: 238729.5 | BD90: 268655.62 | BE90: 336371.62 | BF90: 599322.38 | BG90: 757017 | BH90: 940421.25 | BI90: 1062703.1 | BJ90: 1331060.6 | BK90: 1634918.6 | BL90: 1992935.2 | BM90: 2803767.8 | BR90: 66-70 | BS90: 82516.5 | BT90: 100635.7 | BU90: 125792.7 | BV90: 143606.1 | BW90: 155909.6 | BX90: 186400.5 | BY90: 204864 | BZ90: 220117.7 | CA90: 247694.7 | CB90: 310096.6 | CC90: 552416.7 | CD90: 697734.4 | CE90: 866745 | CF90: 979597.3 | CG90: 1226893.8 | CH90: 1506904.3 | CI90: 1836824 | CJ90: 2584021 | CO90: 66-70 | CP90: 75923.95 | CQ90: 92585.69 | CR90: 115754.73 | CS90: 132134.16 | CT90: 143447.27 | CU90: 171522.4 | CV90: 188502.42 | CW90: 202528.54 | CX90: 227887.39 | CY90: 285266.08 | CZ90: 508091.51 | DA90: 641715.7 | DB90: 797124.63 | DC90: 901063.76 | DD90: 1128459.6 | DE90: 1385936.1 | DF90: 1689306 | DG90: 2376372.2
A91: 75+ | B91: >75 Years | D91: 5 | E91: FLOATER | F91: 4 | G91: 2 | H91: 2 | I91: 1 | J91: Zone 1 | K91: =G91&"+"&H91 -> 2+2 | L91: =VLOOKUP(A91,'ZONE 1 PREMIUM'!$A$4:$N$16,14,0) -> 12 | M91: =VLOOKUP(D91,DROPDOWN!B:C,2,0) -> 4 | N91: =VLOOKUP(K91,$AQ$3:$AR$12,2,0) -> X113:AP124 | O91: =INDEX(INDIRECT(N91),L91,M91) -> 251697.05 | X91: 71-75 | Y91: 125332.75 | Z91: 153154.7 | AA91: 191587.7 | AB91: 216802.6 | AC91: 235691.35 | AD91: 281801.75 | AE91: 310187.2 | AF91: 335215.8 | AG91: 377762.35 | AH91: 473694.2 | AI91: 819238.15 | AJ91: 1041359.5 | AK91: 1300324.5 | AL91: 1500143.9 | AM91: 1882219.9 | AN91: 2315713.6 | AO91: 2827271.5 | AP91: 3983850.7 | AU91: 71-75 | AV91: 111076.88 | AW91: 135714.38 | AX91: 169816.5 | AY91: 192145.5 | AZ91: 208872 | BA91: 249773.62 | BB91: 274916.25 | BC91: 297081 | BD91: 334756.12 | BE91: 419707.12 | BF91: 725711.62 | BG91: 922407.75 | BH91: 1151728.9 | BI91: 1328979.4 | BJ91: 1667318.6 | BK91: 2051190 | BL91: 2504189.2 | BM91: 3528374.6 | BR91: 71-75 | BS91: 102407.8 | BT91: 125110.7 | BU91: 156572.9 | BV91: 177149.5 | BW91: 192563.8 | BX91: 230291.6 | BY91: 253465.3 | BZ91: 273890.1 | CA91: 308609.4 | CB91: 386893.1 | CC91: 668890.2 | CD91: 850149.3 | CE91: 1061472.5 | CF91: 1224972.1 | CG91: 1536758.3 | CH91: 1890504 | CI91: 2307950.7 | CJ91: 3251757.3 | CO91: 71-75 | CP91: 94214.15 | CQ91: 115090.92 | CR91: 144057.67 | CS91: 162978.98 | CT91: 177152.25 | CU91: 211880.74 | CV91: 233193.51 | CW91: 251974.21 | CX91: 283899.22 | CY91: 355883.91 | CZ91: 615196 | DA91: 781867.9 | DB91: 976185.47 | DC91: 1126688.3 | DD91: 1413383.4 | DE91: 1738661.2 | DF91: 2122514.5 | DG91: 2990368.1
A92: 18-24 | B92: 18 Years | C92: 24 Years | D92: 5 | E92: FLOATER | F92: 5 | G92: 2 | H92: 3 | I92: 1 | J92: Zone 1 | K92: =G92&"+"&H92 -> 2+3 | L92: =VLOOKUP(A92,'ZONE 1 PREMIUM'!$A$4:$N$16,14,0) -> 2 | M92: =VLOOKUP(D92,DROPDOWN!B:C,2,0) -> 4 | N92: =VLOOKUP(K92,$AQ$3:$AR$12,2,0) -> X128:AP139 | O92: =INDEX(INDIRECT(N92),L92,M92) -> 37440.55 | X92: 75+ | Y92: 159386.55 | Z92: 195094.05 | AA92: 244326.7 | AB92: 276870.55 | AC92: 301375.9 | AD92: 360594 | AE92: 397444.6 | AF92: 430105.75 | AG92: 485351.75 | AH92: 609455.15 | AI92: 1018173.2 | AJ92: 1303705.5 | AK92: 1637476.9 | AL92: 1935345.3 | AM92: 2432267.2 | AN92: 2997245 | AO92: 3665052.3 | AP92: 5172175.6 | AU92: 75+ | AV92: 141231.38 | AW92: 172850.62 | AX92: 216515.25 | AY92: 245335.5 | AZ92: 267034.5 | BA92: 319542.75 | BB92: 352182.38 | BC92: 381105 | BD92: 430025.62 | BE92: 539923.5 | BF92: 901870.88 | BG92: 1154719.1 | BH92: 1450283.6 | BI92: 1714353.8 | BJ92: 2154393 | BK92: 2654697.4 | BL92: 3246061.5 | BM92: 4580664.8 | BR92: 75+ | BS92: 130193.8 | BT92: 159332.8 | BU92: 199606 | BV92: 226163.3 | BW92: 246160.2 | BX92: 294583.3 | BY92: 324665 | BZ92: 351318 | CA92: 396400.4 | CB92: 497673 | CC92: 831222.7 | CD92: 1064226.9 | CE92: 1336594.6 | CF92: 1580098.3 | CG92: 1985602.3 | CH92: 2446643.1 | CI92: 2991595.2 | CJ92: 4221457.9 | CO92: 75+ | CP92: 119764.84 | CQ92: 146558.13 | CR92: 183626.85 | CS92: 208047.21 | CT92: 226434.42 | CU92: 270996.89 | CV92: 298661.09 | CW92: 323169.74 | CX92: 364623.53 | CY92: 457746.59 | CZ92: 764461.69 | DA92: 978715.36 | DB92: 1229164.7 | DC92: 1453231.6 | DD92: 1826102.1 | DE92: 2250041.2 | DF92: 2751138.2 | DG92: 3882027.4
A93: 25-35 | B93: 25 Years | C93: 35 Years | D93: 5 | E93: FLOATER | F93: 5 | G93: 2 | H93: 3 | I93: 1 | J93: Zone 1 | K93: =G93&"+"&H93 -> 2+3 | L93: =VLOOKUP(A93,'ZONE 1 PREMIUM'!$A$4:$N$16,14,0) -> 3 | M93: =VLOOKUP(D93,DROPDOWN!B:C,2,0) -> 4 | N93: =VLOOKUP(K93,$AQ$3:$AR$12,2,0) -> X128:AP139 | O93: =INDEX(INDIRECT(N93),L93,M93) -> 40415.6
A94: 36-40 | B94: 36 Years | C94: 40 Years | D94: 5 | E94: FLOATER | F94: 5 | G94: 2 | H94: 3 | I94: 1 | J94: Zone 1 | K94: =G94&"+"&H94 -> 2+3 | L94: =VLOOKUP(A94,'ZONE 1 PREMIUM'!$A$4:$N$16,14,0) -> 4 | M94: =VLOOKUP(D94,DROPDOWN!B:C,2,0) -> 4 | N94: =VLOOKUP(K94,$AQ$3:$AR$12,2,0) -> X128:AP139 | O94: =INDEX(INDIRECT(N94),L94,M94) -> 45525.05
A95: 41-45 | B95: 41 Years | C95: 45 Years | D95: 5 | E95: FLOATER | F95: 5 | G95: 2 | H95: 3 | I95: 1 | J95: Zone 1 | K95: =G95&"+"&H95 -> 2+3 | L95: =VLOOKUP(A95,'ZONE 1 PREMIUM'!$A$4:$N$16,14,0) -> 5 | M95: =VLOOKUP(D95,DROPDOWN!B:C,2,0) -> 4 | N95: =VLOOKUP(K95,$AQ$3:$AR$12,2,0) -> X128:AP139 | O95: =INDEX(INDIRECT(N95),L95,M95) -> 51155.45
A96: 46-50 | B96: 46 Years | C96: 50 Years | D96: 5 | E96: FLOATER | F96: 5 | G96: 2 | H96: 3 | I96: 1 | J96: Zone 1 | K96: =G96&"+"&H96 -> 2+3 | L96: =VLOOKUP(A96,'ZONE 1 PREMIUM'!$A$4:$N$16,14,0) -> 6 | M96: =VLOOKUP(D96,DROPDOWN!B:C,2,0) -> 4 | N96: =VLOOKUP(K96,$AQ$3:$AR$12,2,0) -> X128:AP139 | O96: =INDEX(INDIRECT(N96),L96,M96) -> 62213.85 | X96: 2A1C
A97: 51-55 | B97: 51 Years | C97: 55 Years | D97: 5 | E97: FLOATER | F97: 5 | G97: 2 | H97: 3 | I97: 1 | J97: Zone 1 | K97: =G97&"+"&H97 -> 2+3 | L97: =VLOOKUP(A97,'ZONE 1 PREMIUM'!$A$4:$N$16,14,0) -> 7 | M97: =VLOOKUP(D97,DROPDOWN!B:C,2,0) -> 4 | N97: =VLOOKUP(K97,$AQ$3:$AR$12,2,0) -> X128:AP139 | O97: =INDEX(INDIRECT(N97),L97,M97) -> 78741.65 | Y97: Care 3 | AA97: Care 4 | AD97: Care 5 | AI97: Care 6 | AL97: Care 7 | AT97: 2A1C | AV97: Care 3 | AX97: Care 4 | BA97: Care 5 | BF97: Care 6 | BI97: Care 7 | BQ97: 2A1C | BS97: Care 3 | BU97: Care 4 | BX97: Care 5 | CC97: Care 6 | CF97: Care 7 | CN97: 2A1C | CP97: Care 3 | CR97: Care 4 | CU97: Care 5 | CZ97: Care 6 | DC97: Care 7
A98: 56-60 | B98: 56 Years | C98: 60 Years | D98: 5 | E98: FLOATER | F98: 5 | G98: 2 | H98: 3 | I98: 1 | J98: Zone 1 | K98: =G98&"+"&H98 -> 2+3 | L98: =VLOOKUP(A98,'ZONE 1 PREMIUM'!$A$4:$N$16,14,0) -> 8 | M98: =VLOOKUP(D98,DROPDOWN!B:C,2,0) -> 4 | N98: =VLOOKUP(K98,$AQ$3:$AR$12,2,0) -> X128:AP139 | O98: =INDEX(INDIRECT(N98),L98,M98) -> 100651.45 | X98: Age-Band/ SI | Y98: 3L | Z98: 4L | AA98: 5L | AB98: 7L | AC98: 10L | AD98: 15L | AE98: 20L | AF98: 25L | AG98: 30L | AH98: 40L | AI98: 50L | AJ98: 60L | AK98: 75L | AL98: 1 CR | AM98: 1.5 CR | AN98: 2 CR | AO98: 3 CR | AP98: 6 CR | AU98: Age-Band/ SI | AV98: 3L | AW98: 4L | AX98: 5L | AY98: 7L | AZ98: 10L | BA98: 15L | BB98: 20L | BC98: 25L | BD98: 30L | BE98: 40L | BF98: 50L | BG98: 60L | BH98: 75L | BI98: 1 CR | BJ98: 1.5 CR | BK98: 2 CR | BL98: 3 CR | BM98: 6 CR | BR98: Age-Band/ SI | BS98: 3L | BT98: 4L | BU98: 5L | BV98: 7L | BW98: 10L | BX98: 15L | BY98: 20L | BZ98: 25L | CA98: 30L | CB98: 40L | CC98: 50L | CD98: 60L | CE98: 75L | CF98: 1 CR | CG98: 1.5 CR | CH98: 2 CR | CI98: 3 CR | CJ98: 6 CR | CO98: Age-Band/ SI | CP98: 3L | CQ98: 4L | CR98: 5L | CS98: 7L | CT98: 10L | CU98: 15L | CV98: 20L | CW98: 25L | CX98: 30L | CY98: 40L | CZ98: 50L | DA98: 60L | DB98: 75L | DC98: 1 CR | DD98: 1.5 CR | DE98: 2 CR | DF98: 3 CR | DG98: 6 CR
A99: 61-65 | B99: 61 Years | C99: 65 Years | D99: 5 | E99: FLOATER | F99: 5 | G99: 2 | H99: 3 | I99: 1 | J99: Zone 1 | K99: =G99&"+"&H99 -> 2+3 | L99: =VLOOKUP(A99,'ZONE 1 PREMIUM'!$A$4:$N$16,14,0) -> 9 | M99: =VLOOKUP(D99,DROPDOWN!B:C,2,0) -> 4 | N99: =VLOOKUP(K99,$AQ$3:$AR$12,2,0) -> X128:AP139 | O99: =INDEX(INDIRECT(N99),L99,M99) -> 130142.05 | X99: 18-24 | Y99: 18687.5 | Z99: 22830.95 | AA99: 27904.75 | AB99: 30412.9 | AC99: 32716.35 | AD99: 41247.05 | AE99: 45278.95 | AF99: 48806 | AG99: 54400.75 | AH99: 67433.7 | AI99: 135149.15 | AJ99: 161998.2 | AK99: 193298.9 | AL99: 277240.85 | AM99: 328837.9 | AN99: 385894 | AO99: 452044.3 | AP99: 604047.85 | AU99: 18-24 | AV99: 16598.25 | AW99: 20266.875 | AX99: 24788.25 | AY99: 27010.125 | AZ99: 29049.75 | BA99: 36633.375 | BB99: 40204.125 | BC99: 43327.125 | BD99: 48281.625 | BE99: 59821.875 | BF99: 119787.75 | BG99: 143561.25 | BH99: 171279 | BI99: 246538.12 | BJ99: 292228.88 | BK99: 342753.75 | BL99: 401331.38 | BM99: 535935.38 | BR99: 18-24 | BS99: 15321.9 | BT99: 18702.2 | BU99: 22884.4 | BV99: 24931.5 | BW99: 26811.4 | BX99: 33815.1 | BY99: 37105.2 | BZ99: 39983.9 | CA99: 44548.9 | CB99: 55183.7 | CC99: 110443.3 | CD99: 132352 | CE99: 157894 | CF99: 227734.1 | CG99: 269837.7 | CH99: 316398.5 | CI99: 370378.8 | CJ99: 494418.1 | CO99: 18-24 | CP99: 14115.5 | CQ99: 17224.18 | CR99: 21084.96 | CS99: 22967.39 | CT99: 24695.04 | CU99: 31151.11 | CV99: 34176.95 | CW99: 36823.47 | CX99: 41021.06 | CY99: 50800.54 | CZ99: 101613.07 | DA99: 121758.45 | DB99: 145244.68 | DC99: 209956.89 | DD99: 248672.6 | DE99: 291486.71 | DF99: 341123.13 | DG99: 455180.73
A100: 66-70 | B100: 66 Years | C100: 70 Years | D100: 5 | E100: FLOATER | F100: 5 | G100: 2 | H100: 3 | I100: 1 | J100: Zone 1 | K100: =G100&"+"&H100 -> 2+3 | L100: =VLOOKUP(A100,'ZONE 1 PREMIUM'!$A$4:$N$16,14,0) -> 10 | M100: =VLOOKUP(D100,DROPDOWN!B:C,2,0) -> 4 | N100: =VLOOKUP(K100,$AQ$3:$AR$12,2,0) -> X128:AP139 | O100: =INDEX(INDIRECT(N100),L100,M100) -> 167864.35 | X100: 25-35 | Y100: 20997.85 | Z100: 25256.3 | AA100: 31052.3 | AB100: 33847.95 | AC100: 36420.5 | AD100: 45965.5 | AE100: 50242.35 | AF100: 53981 | AG100: 60174.9 | AH100: 74562.55 | AI100: 149000.9 | AJ100: 180037.1 | AK100: 216788.8 | AL100: 303016.95 | AM100: 361208.1 | AN100: 425746.1 | AO100: 500713.45 | AP100: 672713.2 | AU100: 25-35 | AV100: 18657 | AW100: 22428 | AX100: 27600.75 | AY100: 30076.875 | AZ100: 32355 | BA100: 40846.5 | BB100: 44633.25 | BC100: 47944.125 | BD100: 53429.625 | BE100: 66170.25 | BF100: 132088.5 | BG100: 159571.12 | BH100: 192115.12 | BI100: 269403.75 | BJ100: 320933.25 | BK100: 378084.38 | BL100: 444469.5 | BM100: 596781 | BR100: 25-35 | BS100: 17226 | BT100: 20700.9 | BU100: 25488.1 | BV100: 27770.6 | BW100: 29869.4 | BX100: 37716.8 | BY100: 41206 | BZ100: 44257.4 | CA100: 49310.8 | CB100: 61052.2 | CC100: 121797.5 | CD100: 147122.8 | CE100: 177113.2 | CF100: 248825.5 | CG100: 296311.4 | CH100: 348976.1 | CI100: 410151.5 | CJ100: 550509.3 | CO100: 25-35 | CP100: 15873.67 | CQ100: 19068.46 | CR100: 23491.68 | CS100: 25589.93 | CT100: 27520.32 | CU100: 34756.83 | CV100: 37965.79 | CW100: 40771.45 | CX100: 45419.21 | CY100: 56215.66 | CZ100: 112072.71 | DA100: 135359.47 | DB100: 162936.47 | DC100: 229371.97 | DD100: 273036.28 | DE100: 321463.89 | DF100: 377716.61 | DG100: 506779.15
...

Sheet ZONE 1 PREMIUM
A1: 1A | B1: Zone 1
B2: Care 4 | E2: Care 5 | J2: Care 6 | O2: ARRAY
A3: Age-Band/ SI | B3: 5L | C3: 7L | D3: 10L | E3: 15L | F3: 20L | G3: 25L | H3: 30L | I3: 40L | J3: 50L | K3: 60L | L3: 75L | O3: 1+0 | P3: A3:L16
A4: 00-04 | B4: 3298.4569 | C4: 3596.2461 | D4: 3869.0766 | E4: 4514.5176 | F4: 4913.9165 | G4: 5252.5662 | H4: 5858.8143 | I4: 7275.6768 | J4: 11187.446 | K4: 14255.914 | L4: 17689.078 | M4: 2 | O4: 1+1 | P4: A20:L31
A5: 05-17 | B5: 2529.391 | C5: 2759.3334 | D5: 2970.7534 | E5: 3467.1899 | F5: 3776.886 | G5: 4040.7645 | H5: 4510.2594 | I5: 5602.8289 | J5: 9162.1148 | K5: 11551.805 | L5: 14225.47 | M5: 3 | O5: 1+2 | P5: A35:L46
A6: 18-24 | B6: 6776.1183 | C6: 7392.0976 | D6: 7957.8732 | E6: 9366.3985 | F6: 10309.144 | G6: 11138.68 | H6: 12423.336 | I6: 15413.752 | J6: 32221.938 | K6: 38594.695 | L6: 45762.658 | M6: 4 | N6: 2 | O6: 1+3 | P6: A50:L61
A7: 25-35 | B7: 7791.0758 | C7: 8502.1523 | D7: 9156.8059 | E7: 10798.186 | F7: 11817.849 | G7: 12714.104 | H7: 14184.194 | I7: 17595.192 | J7: 36410.708 | K7: 44101.604 | L7: 52940.238 | M7: 5 | N7: 3 | O7: 1+4 | P7: A65:L76
A8: 36-40 | B8: 8977.4968 | C8: 9809.9588 | D8: 10578.686 | E8: 12476.264 | F8: 13657.959 | G8: 14696.022 | H8: 16418.043 | I8: 20398.52 | J8: 38008.774 | K8: 47033.733 | L8: 57423.602 | M8: 6 | N8: 4 | O8: 2+0 | P8: A81:L92
A9: 41-45 | B9: 10433.258 | C9: 11416.107 | D9: 12325.914 | E9: 14540.16 | F9: 15878.32 | G9: 17033.024 | H9: 19054.805 | I9: 23710.541 | J9: 42970.576 | K9: 53648.552 | L9: 65958.272 | M9: 7 | N9: 5 | O9: 2+1 | P9: A98:L109
A10: 46-50 | B10: 12935.045 | C10: 14166.983 | D10: 15310.386 | E10: 18081.662 | F10: 19765.594 | G10: 21225.218 | H10: 23767.01 | I10: 29598.372 | J10: 51770.805 | K10: 65292.878 | L10: 80903.138 | M10: 8 | N10: 6 | O10: 2+2 | P10: A113:L124
A11: 51-55 | B11: 16983.873 | C11: 18630.251 | D11: 20162.878 | E11: 23809.084 | F11: 26068.873 | G11: 28036.458 | H11: 31444.264 | I11: 39233.606 | J11: 72674.013 | K11: 90950.869 | L11: 112077.58 | M11: 9 | N11: 7 | O11: 2+3 | P11: A128:L139
A12: 56-60 | B12: 22961.412 | C12: 25214.242 | D12: 27316.869 | E12: 32287.902 | F12: 35392.551 | G12: 37651.83 | H12: 42273.164 | I12: 52796.653 | J12: 97100.769 | K12: 121762.65 | L12: 150331.02 | M12: 10 | N12: 8 | O12: 2+4 | P12: A143:L154
A13: 61-65 | B13: 31682.789 | C13: 34844.432 | D13: 37803.224 | E13: 44685.549 | F13: 49060.369 | G13: 52079.027 | H13: 58562.295 | I13: 73271.745 | J13: 133390.8 | K13: 167789.08 | L13: 207723.94 | M13: 11 | N13: 9
A14: 66-70 | B14: 40366.648 | C14: 44453.187 | D14: 48287.942 | E14: 57105.273 | F14: 62803.961 | G14: 67812.506 | H14: 76355.33 | I14: 95666.351 | J14: 169150.5 | K14: 214049.9 | L14: 266304.88 | M14: 12 | N14: 10
A15: 71-75 | B15: 48357.798 | C15: 53320.105 | D15: 57989.097 | E15: 68628.876 | F15: 75572.974 | G15: 81706.173 | H15: 92116.176 | I15: 115562.19 | J15: 197896.37 | K15: 252082.89 | L15: 315306.75 | M15: 13 | N15: 11
A16: 75+ | B16: 64744.602 | C16: 71482.673 | D16: 77839.51 | E16: 92183.36 | F16: 101643.87 | G16: 110041.97 | H16: 124227.35 | I16: 156060.94 | J16: 258141.27 | K16: 331251.82 | L16: 416776.81 | M16: 14 | N16: 12
A18: 1A1C
B19: Care 4 | E19: Care 5 | J19: Care 6
A20: Age-Band/ SI | B20: 5L | C20: 7L | D20: 10L | E20: 15L | F20: 20L | G20: 25L | H20: 30L | I20: 40L | J20: 50L | K20: 60L | L20: 75L
A21: 18-24 | B21: 7370.0411 | C21: 7779.0772 | D21: 8367.4373 | E21: 10571.752 | F21: 11589.383 | G21: 12475.821 | H21: 13906.32 | I21: 17240.048 | J21: 33134.026 | K21: 40273.902 | L21: 48291.845
A22: 25-35 | B22: 8156.6241 | C22: 8610.5499 | D22: 9264.0485 | E22: 11713.144 | F22: 12791.327 | G22: 13730.469 | H22: 15306.114 | I22: 18968.733 | J22: 36496.734 | K22: 44669.028 | L22: 53995.778
A23: 36-40 | B23: 9407.7149 | C23: 9942.1497 | D23: 10707.813 | E23: 13553.771 | F23: 14819.224 | G23: 15924.528 | H23: 17770.67 | I23: 22048.406 | J23: 38993.855 | K23: 48566.376 | L23: 59510.469
A24: 41-45 | B24: 11050.68 | C24: 11691.919 | D24: 12605.73 | E24: 15963.09 | F24: 17433.356 | G24: 18703.493 | H24: 20894.719 | I24: 25955.155 | J24: 45054.695 | K24: 56482.416 | L24: 69570.935
A25: 46-50 | B25: 13447.271 | C25: 15002.803 | D25: 16192.9 | E25: 19681.985 | F25: 21521.493 | G25: 23118.155 | H25: 25851.073 | I25: 32140.875 | J25: 54431.188 | K25: 68779.135 | L25: 85248.595
A26: 51-55 | B26: 17409.197 | C26: 19469.422 | D26: 21040.157 | E26: 25560.394 | F26: 27996.751 | G26: 30121.186 | H26: 33727.228 | I26: 42000.886 | J26: 74379.207 | K26: 93432.96 | L26: 115339.39
A27: 56-60 | B27: 23669.313 | C27: 25752.808 | D27: 27861.729 | E27: 34084.318 | F27: 37368.748 | G27: 39846.418 | H27: 44668.731 | I27: 55690.438 | J27: 98772.563 | K27: 124214.31 | L27: 153550.04
A28: 61-65 | B28: 31949.763 | C28: 35923.466 | D28: 38927.929 | E28: 47004.923 | F28: 51605.418 | G28: 54894.449 | H28: 61645.54 | I28: 77011.927 | J28: 136570.36 | K28: 172108.71 | L28: 213214.89
A29: 66-70 | B29: 41691.97 | C29: 45483.786 | D29: 49357.478 | E29: 59455.133 | F29: 65383.319 | G29: 70593.036 | H29: 79396.466 | I29: 99353.662 | J29: 172487.32 | K29: 218509.19 | L29: 271905.37
A30: 71-75 | B30: 49038.387 | C30: 53590.099 | D30: 58226.146 | E30: 70108.289 | F30: 77188.879 | G30: 83439.527 | H30: 93968.597 | I30: 117747.75 | J30: 198973.1 | K30: 253571.1 | L30: 317095.26
A31: 75+ | B31: 66336.093 | C31: 72644.723 | D31: 79039.956 | E31: 95075.652 | F31: 104809.85 | G31: 113444.77 | H31: 127951.9 | I31: 160581.9 | J31: 263492.06 | K31: 338091.17 | L31: 425158.29
A33: 1A2C
B34: Care 4 | E34: Care 5 | J34: Care 6
A35: Age-Band/ SI | B35: 5L | C35: 7L | D35: 10L | E35: 15L | F35: 20L | G35: 25L | H35: 30L | I35: 40L | J35: 50L | K35: 60L | L35: 75L
A36: 18-24 | B36: 9211.0902 | C36: 10043.471 | D36: 10807.175 | E36: 13710.813 | F36: 15010.735 | G36: 16136.572 | H36: 17995.539 | I36: 22330.471 | J36: 41008.041 | K36: 50317.044 | L36: 60761.918
A37: 25-35 | B37: 9896.119 | C37: 10791.306 | D37: 11613.903 | E37: 14737.783 | F37: 16088.083 | G37: 17257.943 | H37: 19246.886 | I37: 23875.1 | J37: 44080.594 | K37: 54344.965 | L37: 66011.527
A38: 36-40 | B38: 11422.832 | C38: 12467.993 | D38: 13430.531 | E38: 17059.508 | F38: 18656.1 | G38: 20046.021 | H38: 22376.759 | I38: 27784.894 | J38: 47771.182 | K38: 59781.507 | L38: 73456.699
A39: 41-45 | B39: 12796.734 | C39: 13981.333 | D39: 15074.503 | E39: 19152.157 | F39: 20935.829 | G39: 22477.73 | H39: 25114.638 | I39: 31214.77 | J39: 52921.828 | K39: 66569.393 | L39: 82138.041
A40: 46-50 | B40: 15833.269 | C40: 18074.46 | D40: 19505.629 | E40: 23948.016 | F40: 26212.531 | G40: 28179.77 | H40: 31510.5 | I40: 39191.761 | J40: 65147.542 | K40: 82484.895 | L40: 102311.2
A41: 51-55 | B41: 20343.342 | C41: 23276.665 | D41: 25146.055 | E41: 30847.638 | F41: 33822.129 | G41: 36418.226 | H41: 40767.753 | I41: 50772.022 | J41: 87438.722 | K41: 110193.67 | L41: 136260.09
A42: 56-60 | B42: 26675.55 | C42: 29854.286 | D42: 32284.895 | E42: 39780.046 | F42: 43647.862 | G42: 46637.628 | H42: 52261.696 | I42: 65149.675 | J42: 112769.34 | K42: 142197 | L42: 176013.98
A43: 61-65 | B43: 34007.908 | C43: 39222.32 | D43: 42480.95 | E43: 51656.311 | F43: 56739.298 | G43: 60470.314 | H43: 67873.064 | I43: 84764.849 | J43: 147470.48 | K43: 186199.12 | L43: 230864.28
A44: 66-70 | B44: 44116.124 | C44: 49562.18 | D44: 53754.117 | E44: 65137.777 | F44: 71652.956 | G44: 77378.766 | H44: 86980.797 | I44: 108799.71 | J44: 186235.68 | K44: 236210.16 | L44: 294043.03
A45: 71-75 | B45: 51914.097 | C45: 58434.785 | D45: 63454.103 | E45: 76802.509 | F45: 84572.968 | G45: 91430.5 | H45: 102908.12 | I45: 128889.63 | J45: 215533.14 | K45: 274857.04 | L45: 343712.69
A46: 75+ | B46: 67547.984 | C46: 76222.708 | D46: 82889.786 | E46: 100116.81 | F46: 110372.45 | G46: 119465.02 | H46: 134668.85 | I46: 168934.87 | J46: 275408.55 | K46: 353432.99 | L46: 444312.87
A48: 1A3C
B49: Care 4 | E49: Care 5 | J49: Care 6
A50: Age-Band/ SI | B50: 5L | C50: 7L | D50: 10L | E50: 15L | F50: 20L | G50: 25L | H50: 30L | I50: 40L | J50: 50L | K50: 60L | L50: 75L
A51: 18-24 | B51: 11284.126 | C51: 12307.865 | D51: 13246.913 | E51: 16849.875 | F51: 18432.087 | G51: 19797.323 | H51: 22084.758 | I51: 27420.894 | J51: 48882.057 | K51: 60360.185 | L51: 73231.991
A52: 25-35 | B52: 11931.663 | C52: 13014.9 | D52: 14009.848 | E52: 17820.696 | F52: 19448.477 | G52: 20853.729 | H52: 23263.807 | I52: 28875.84 | J52: 51846.029 | K52: 64243.136 | L52: 78295.912
A53: 36-40 | B53: 13779.407 | C53: 15043.3 | D53: 16206.521 | E53: 20632.677 | F53: 22566.703 | G53: 24246.74 | H53: 27071.259 | I53: 33631.076 | J53: 56742.509 | K53: 71238.262 | L53: 87699
A54: 41-45 | B54: 15302.277 | C54: 16720.436 | D54: 18028.112 | E54: 22955.19 | F54: 25108.815 | G54: 26971.332 | H54: 30138.199 | I54: 37472.661 | J54: 62521.833 | K54: 78828.771 | L54: 97380.952
A55: 46-50 | B55: 18642.547 | C55: 21146.116 | D55: 22818.357 | E55: 28214.047 | F55: 30903.568 | G55: 33241.385 | H55: 37169.927 | I55: 46242.647 | J55: 75863.897 | K55: 96190.656 | L55: 119373.8
A56: 51-55 | B56: 23468.094 | C56: 26677.649 | D56: 28813.173 | E56: 35592.858 | F56: 39052.795 | G56: 42074.538 | H56: 47091.154 | I56: 58650.01 | J56: 98990.763 | K56: 125050.06 | L56: 154823.08
A57: 56-60 | B57: 29437.954 | C57: 32852.201 | D57: 35515.049 | E57: 43997.812 | F57: 48304.349 | G57: 51692.402 | H57: 57909.384 | I57: 72184.121 | J57: 122646.22 | K57: 154973.85 | L57: 192027.38
A58: 61-65 | B58: 37069.94 | C58: 42529.41 | D58: 46043.764 | E58: 56305.078 | F58: 61869.209 | G58: 66037.366 | H58: 74092.056 | I58: 92508.188 | J58: 158467.54 | K58: 200397.56 | L58: 248639.74
A59: 66-70 | B59: 46566.642 | C59: 52200.156 | D59: 56589.471 | E59: 68915.691 | F59: 75826.679 | G59: 81900.552 | H59: 92021.816 | I59: 115065.94 | J59: 194628.38 | K59: 247108.85 | L59: 307709.24
A60: 71-75 | B60: 54243.205 | C60: 60929.766 | D60: 66131.288 | E60: 80400.846 | F60: 88547.657 | G60: 95735.434 | H60: 107700.15 | I60: 134838.15 | J60: 223456.88 | K60: 285125.7 | L60: 356552.87
A61: 75+ | B61: 70018.481 | C61: 78869.819 | D61: 85728.758 | E61: 103923.32 | F61: 114573.76 | G61: 124011.86 | H61: 139727.31 | I61: 175209.91 | J61: 283997 | K61: 364502.2 | L61: 458100.83
A63: 1A4C
B64: Care 4 | E64: Care 5 | J64: Care 6
A65: Age-Band/ SI | B65: 5L | C65: 7L | D65: 10L | E65: 15L | F65: 20L | G65: 25L | H65: 30L | I65: 40L | J65: 50L | K65: 60L | L65: 75L
A66: 18-24 | B66: 13357.162 | C66: 14572.259 | D66: 15686.651 | E66: 19988.937 | F66: 21853.439 | G66: 23458.075 | H66: 26173.977 | I66: 32511.316 | J66: 56756.072 | K66: 70403.327 | L66: 85702.064
A67: 25-35 | B67: 13967.207 | C67: 15238.494 | D67: 16405.792 | E67: 20903.61 | F67: 22808.872 | G67: 24449.514 | H67: 27280.728 | I67: 33876.579 | J67: 59611.464 | K67: 74141.307 | L67: 90580.297
A68: 36-40 | B68: 16135.982 | C68: 17618.608 | D68: 18982.511 | E68: 24205.845 | F68: 26477.306 | G68: 28447.46 | H68: 31765.759 | I68: 39477.258 | J68: 65713.835 | K68: 82695.016 | L68: 101941.3
A69: 41-45 | B69: 17807.82 | C69: 19459.539 | D69: 20981.721 | E69: 26758.223 | F69: 29281.801 | G69: 31464.934 | H69: 35161.761 | I69: 43730.552 | J69: 72121.839 | K69: 91088.15 | L69: 112623.86
A70: 46-50 | B70: 21451.825 | C70: 24217.772 | D70: 26131.085 | E70: 32480.078 | F70: 35594.605 | G70: 38303 | H70: 42829.354 | I70: 53293.532 | J70: 86580.251 | K70: 109896.42 | L70: 136436.4
A71: 51-55 | B71: 26078.767 | C71: 29501.049 | D71: 31856.747 | E71: 39558.13 | F71: 43426.605 | G71: 46806.753 | H71: 52380.607 | I71: 65240.151 | J71: 108447.65 | K71: 137247.91 | L71: 170086.92
A72: 56-60 | B72: 31956.525 | C72: 35583.521 | D72: 38457.697 | E72: 47845.356 | F72: 52552.695 | G72: 56305.747 | H72: 63063.529 | I72: 78603.718 | J72: 131613.31 | K72: 166581.82 | L72: 206580.63
A73: 61-65 | B73: 39666.892 | C73: 45312.705 | D73: 49040.335 | E73: 60247.54 | F73: 66221.986 | G73: 70770.579 | H73: 79376.79 | I73: 99086.071 | J73: 167575.86 | K73: 212193.66 | L73: 263426.99
A74: 66-70 | B74: 49095.247 | C74: 54931.765 | D74: 59527.7 | E74: 72800.703 | F74: 80117.291 | G74: 86547.822 | H74: 97206.039 | I74: 121513.32 | J74: 203450.95 | K74: 258539.71 | L74: 322032.83
A75: 71-75 | B75: 56784.678 | C75: 63669.818 | D75: 69076.123 | E75: 84306.091 | F75: 92859.72 | G75: 100404.72 | H75: 112904.81 | I75: 141306.03 | J75: 232345.44 | K75: 296616.94 | L75: 370921.96
A76: 75+ | B76: 72647.212 | C76: 81700.732 | D76: 88769.089 | E76: 107958.97 | F76: 119027.49 | G76: 128831.93 | H76: 145096.28 | I76: 181877.09 | J76: 293285.98 | K76: 376468.62 | L76: 473021.46
A79: 2A
B80: Care 4 | E80: Care 5 | J80: Care 6
A81: Age-Band/ SI | B81: 5L | C81: 7L | D81: 10L | E81: 15L | F81: 20L | G81: 25L | H81: 30L | I81: 40L | J81: 50L | K81: 60L | L81: 75L
A82: 18-24 | B82: 9988.6015 | C82: 10887.931 | D82: 11713.964 | E82: 14723.944 | F82: 16194.627 | G82: 17488.703 | H82: 19492.767 | I82: 24157.816 | J82: 50378.585 | K82: 60320.086 | L82: 71502.109
A83: 25-35 | B83: 11394.625 | C83: 12422.384 | D83: 13368.446 | E83: 16831.587 | F83: 18413.263 | G83: 19803.614 | H83: 22075.259 | I83: 27347.208 | J83: 56464.554 | K83: 68308.131 | L83: 81900.932
A84: 36-40 | B84: 12634.541 | C84: 13787.907 | D84: 14851.958 | E84: 18704.048 | F84: 20459.024 | G84: 22000.975 | H84: 24549.773 | I84: 30448.381 | J84: 58578.45 | K84: 71928.989 | L84: 87290.21
A85: 41-45 | B85: 14622.32 | C85: 15980.431 | D85: 17236.658 | E85: 21713.07 | F85: 23715.169 | G85: 25452.822 | H85: 28443.131 | I85: 35337.388 | J85: 64482.263 | K85: 80237.358 | L85: 98392.282
A86: 46-50 | B86: 18503.314 | C86: 21236.914 | D86: 22935.557 | E86: 27834.771 | F86: 30404.259 | G86: 32628.638 | H86: 36508.167 | I86: 45418.045 | J86: 80146.321 | K86: 100742.6 | L86: 124510.11
A87: 51-55 | B87: 24271.717 | C87: 28441.256 | D87: 30759.278 | E87: 36778.63 | F87: 40236.471 | G87: 43243.334 | H87: 48459.232 | I87: 60394.033 | J87: 109948.35 | K87: 137857.65 | L87: 170106.86
A88: 56-60 | B88: 33986.517 | C88: 38806.522 | D88: 42020.382 | E88: 50672.419 | F88: 55512.532 | G88: 59224.718 | H88: 66455.236 | I88: 82937.435 | J88: 152708.35 | K88: 191347.72 | L88: 236081.06
A89: 61-65 | B89: 47388.514 | C89: 54975.247 | D89: 59611.17 | E89: 71507.928 | F89: 78460.326 | G89: 83328.814 | H89: 93644.348 | I89: 117071.99 | J89: 213610.94 | K89: 268428.83 | L89: 332031.61
A90: 66-70 | B90: 66898.85 | C90: 76389.706 | D90: 82944.966 | E90: 99136.622 | F90: 108970.27 | G90: 117097.49 | H90: 131790.66 | I90: 165038.17 | J90: 294138.25 | K90: 371564.09 | L90: 461612.69
A91: 71-75 | B91: 83298.832 | C91: 94262.233 | D91: 102474.6 | E91: 122522.73 | F91: 134863.95 | G91: 145746.17 | H91: 164244.48 | I91: 205954.14 | J91: 356190.31 | K91: 452765.02 | L91: 565358.51
A92: 75+ | B92: 106228.75 | C92: 120378.67 | D92: 131032.97 | E92: 156780.13 | F92: 172801.92 | G92: 187002.68 | H92: 211022.35 | I92: 264980.57 | J92: 442683.86 | K92: 566828.65 | L92: 711946.67
A96: 2A1C
B97: Care 4 | E97: Care 5 | J97: Care 6
A98: Age-Band/ SI | B98: 5L | C98: 7L | D98: 10L | E98: 15L | F98: 20L | G98: 25L | H98: 30L | I98: 40L | J98: 50L | K98: 60L | L98: 75L
A99: 18-24 | B99: 12132.355 | C99: 13223.043 | D99: 14224.419 | E99: 17933.724 | F99: 19686.696 | G99: 21220.172 | H99: 23652.704 | I99: 29318.956 | J99: 58760.743 | K99: 70433.946 | L99: 84042.9
A100: 25-35 | B100: 13500.887 | C100: 14716.696 | D100: 15835.108 | E100: 19985.218 | F100: 21844.375 | G100: 23470.117 | H100: 26162.898 | I100: 32418.665 | J100: 64782.963 | K100: 78277.019 | L100: 94256.034
A101: 36-40 | B101: 15080.397 | C101: 16452.495 | D101: 17717.229 | E101: 22380.248 | F101: 24472.659 | G101: 26304.725 | H101: 29347.305 | I101: 36397.595 | J101: 68160.205 | K101: 83488.775 | L101: 101635.54
A102: 41-45 | B102: 17230.403 | C102: 18822.075 | D102: 20292.807 | E102: 25642.216 | F102: 28014.269 | G102: 30072.537 | H102: 33592.806 | I102: 41721.391 | J102: 74764.944 | K102: 92622.849 | L102: 113761.31
A103: 46-50 | B103: 21431.045 | C103: 24427.022 | D103: 26366.738 | E103: 32254.613 | F103: 35249.107 | G103: 37844.063 | H103: 42321.405 | I103: 52622.742 | J103: 91699.11 | K103: 114602.17 | L103: 141726.52
A104: 51-55 | B104: 27898.822 | C104: 32393.47 | D104: 35010.147 | E104: 42265.847 | F104: 46261.823 | G104: 49740.348 | H104: 55699.731 | I104: 69365.143 | J104: 124131.9 | K104: 154818.34 | L104: 191227.53
A105: 56-60 | B105: 37893.372 | C105: 43063.579 | D105: 46599.126 | E105: 56586.586 | F105: 62010.086 | G105: 66234.368 | H105: 74266.639 | I105: 92615.11 | J105: 168175.49 | K105: 209548.85 | L105: 258763.44
A106: 61-65 | B106: 51365.306 | C106: 59308.515 | D106: 64271.883 | E106: 77528.833 | F106: 85075.93 | G106: 90466.623 | H106: 101598.48 | I106: 126926.3 | J106: 229775.58 | K106: 286940.07 | L106: 355104.41
A107: 66-70 | B107: 69376.507 | C107: 79002.121 | D107: 85735.216 | E107: 102944.86 | F107: 113156.62 | G107: 121629.24 | H107: 136807.81 | I107: 171209.08 | J107: 304072.99 | K107: 381532.89 | L107: 474091.02
A108: 71-75 | B108: 85215.615 | C108: 96254.698 | D108: 104587.66 | E108: 125527.7 | F108: 138162.88 | G108: 149302.84 | H108: 168157.15 | I108: 210732.64 | J108: 364325.65 | K108: 459824.08 | L108: 574147.9
A109: 75+ | B109: 108067.74 | C109: 122278.4 | D109: 133041.2 | E109: 159659.7 | F109: 175957.6 | G109: 190398.71 | H109: 214747.08 | I109: 269514.44 | J109: 451380.34 | K109: 573685.41 | L109: 720389.74
...

Sheet DROPDOWN
A2: 3L | B2: 3 | C2: 2 | D2: 2 | E2: 4
A3: 4L | B3: 4 | C3: 3 | D3: 3 | E3: 5
A4: 5L | B4: 5 | C4: 4 | D4: 4 | E4: 6 | K4: 1 | L4: 00-04 | M4: Upto 45 Years | N4: Upto 45 Years
A5: 7L | B5: 7 | C5: 5 | D5: 5 | E5: 7 | F5: 1000 | G5: 1 | I5: ZONE 1 | J5: 5000 | K5: 2 | L5: 00-04 | M5: Upto 45 Years | N5: Upto 45 Years
A6: 10L | B6: 10 | C6: 6 | D6: 6 | E6: 8 | F6: 2000 | G6: 2 | H6: YES | I6: ZONE 1A | J6: 10000 | K6: 3 | L6: 00-04 | M6: Upto 45 Years | N6: Upto 45 Years
A7: 15L | B7: 15 | C7: 7 | E7: 9 | F7: 3000 | G7: 3 | H7: NO | I7: ZONE 2 | J7: 15000 | K7: 4 | L7: 00-04 | M7: Upto 45 Years | N7: Upto 45 Years
A8: 20L | B8: 20 | C8: 8 | E8: 10 | F8: 4000 | G8: 4 | I8: ZONE 3 | J8: 20000 | K8: 5 | L8: 05-17 | M8: Upto 45 Years | N8: Upto 45 Years
A9: 25L | B9: 25 | C9: 9 | E9: 10 | F9: 5000 | G9: 5 | J9: 25000 | K9: 6 | L9: 05-17 | M9: Upto 45 Years | N9: Upto 45 Years
A10: 30L | B10: 30 | C10: 10 | E10: 10 | F10: 6000 | G10: 6 | J10: 30000 | K10: 7 | L10: 05-17 | M10: Upto 45 Years | N10: Upto 45 Years | O10: 3L | P10: 4L | Q10: 5L | R10: 7L | S10: 10L | T10: 15L | U10: 20L | V10: 25L | W10: 30L | X10: 40L | Y10: 50L | Z10: 60L | AA10: 75L | AB10: 1 CR | AC10: 1.5 CR | AD10: 2 CR | AE10: 3 CR | AF10: 6CR
A11: 40L | B11: 40 | C11: 11 | E11: 10 | F11: 7000 | G11: 7 | J11: 35000 | K11: 8 | L11: 05-17 | M11: Upto 45 Years | N11: Upto 45 Years
A12: 50L | B12: 50 | C12: 12 | E12: 10 | F12: 8000 | G12: 8 | J12: 40000 | K12: 9 | L12: 05-17 | M12: Upto 45 Years | N12: Upto 45 Years
A13: 60L | B13: 60 | C13: 13 | E13: 10 | F13: 9000 | G13: 9 | J13: 45000 | K13: 10 | L13: 05-17 | M13: Upto 45 Years | N13: Upto 45 Years
A14: 75L | B14: 75 | C14: 14 | E14: 10 | F14: 10000 | G14: 10 | J14: 50000 | K14: 11 | L14: 05-17 | M14: Upto 45 Years | N14: Upto 45 Years | O14: Age-Band/ SI
A15: 1 CR | B15: 100 | C15: 15 | E15: 10 | O15: 00-04 | P15: 2 | R15: TRAVEL PLUS
A16: 1.5 CR | B16: 150 | C16: 16 | E16: 10 | O16: 05-17 | P16: 3 | R16: 2
A17: 2 CR | B17: 200 | C17: 17 | E17: 10 | O17: 18-24 | P17: 4 | Q17: 2 | R17: 3 | S17: 2
A18: 3 CR | B18: 300 | C18: 18 | E18: 10 | O18: 25-35 | P18: 5 | Q18: 3 | R18: 4 | S18: 3
A19: 6 CR | B19: 600 | C19: 19 | E19: 10 | O19: 36-40 | P19: 6 | Q19: 4 | R19: 5 | S19: 4
K20: 12 | L20: 05-17 | M20: Upto 45 Years | N20: Upto 45 Years | O20: 41-45 | P20: 7 | Q20: 5 | R20: 6 | S20: 5
A21: Option 1 | B21: 5000 | C21: CARE | K21: 13 | L21: 05-17 | M21: Upto 45 Years | N21: Upto 45 Years | O21: 46-50 | P21: 8 | Q21: 6 | R21: 7 | S21: 6
A22: Option 2 | B22: 10000 | C22: CARE SENIOR | K22: 14 | L22: 05-17 | M22: Upto 45 Years | N22: Upto 45 Years | O22: 51-55 | P22: 9 | Q22: 7 | R22: 8 | S22: 7
B23: 25000 | K23: 15 | L23: 05-17 | M23: Upto 45 Years | N23: Upto 45 Years | O23: 56-60 | P23: 10 | Q23: 8 | R23: 9 | S23: 8
A24: INCL US | B24: 50000 | K24: 16 | L24: 05-17 | M24: Upto 45 Years | N24: Upto 45 Years | O24: 61-65 | P24: 11 | Q24: 9 | R24: 10 | S24: 9
A25: EXCL US | B25: 100000 | K25: 17 | L25: 05-17 | M25: Upto 45 Years | N25: Upto 45 Years | O25: 66-70 | P25: 12 | Q25: 10 | R25: 11 | S25: 10
B26: 200000 | K26: 18 | L26: 18-24 | M26: Upto 45 Years | N26: Upto 45 Years | O26: 71-75 | P26: 13 | Q26: 11 | R26: 12 | S26: 11
B27: 300000 | K27: 19 | L27: 18-24 | M27: Upto 45 Years | N27: Upto 45 Years | O27: 75+ | P27: 14 | Q27: 12 | R27: 13 | S27: 12
B28: 500000 | K28: 20 | L28: 18-24 | M28: Upto 45 Years | N28: Upto 45 Years
K29: 21 | L29: 18-24 | M29: Upto 45 Years | N29: Upto 45 Years
K30: 22 | L30: 18-24 | M30: Upto 45 Years | N30: Upto 45 Years
K31: 23 | L31: 18-24 | M31: Upto 45 Years | N31: Upto 45 Years
K32: 24 | L32: 18-24 | M32: Upto 45 Years | N32: Upto 45 Years
K33: 25 | L33: 25-35 | M33: Upto 45 Years | N33: Upto 45 Years
K34: 26 | L34: 25-35 | M34: Upto 45 Years | N34: Upto 45 Years
K35: 27 | L35: 25-35 | M35: Upto 45 Years | N35: Upto 45 Years
K36: 28 | L36: 25-35 | M36: Upto 45 Years | N36: Upto 45 Years
K37: 29 | L37: 25-35 | M37: Upto 45 Years | N37: Upto 45 Years
K38: 30 | L38: 25-35 | M38: Upto 45 Years | N38: Upto 45 Years
K39: 31 | L39: 25-35 | M39: Upto 45 Years | N39: Upto 45 Years
K40: 32 | L40: 25-35 | M40: Upto 45 Years | N40: Upto 45 Years
... K110: 102 | L110: 75+ | M110: Above 70 Years | N110: Above 75 Years

Sheet CALCULATOR CARE V6
A1: Basic Details | B1: Inputs | D1: Age
A2: DOB of Eldest member | B2: 21 | E2: =B2+1 -> 22 | F2: =B2+2 -> 23 | H2: AGE OF ALL MEMBERS | I2: ALLOWED
A3: No. of Adults/Individual | B3: 1 | G3: ADULT | H3: =B2 -> 21 | I3: YES | J3: =IF(I3="YES",IF(H3<18,0,1),0) -> 1 | K3: =IF(I3="YES",IF(H3<13,0,1),0) -> 1 | M3: Health Discount | N3: =1-Sheet1!E17 -> 0.775
A4: No. of Children | B4: 0 | G4: ADULT | H4: 32 | I4: NO | J4: =IF(I4="YES",IF(H4<18,0,1),0) -> 0 | K4: =IF(I4="YES",IF(H4<13,0,1),0) -> 0 | M4: Senior citizen | N4: =1-5% -> 0.95
A5: Cover Type | B5: Floater | G5: CHILD | H5: 22 | I5: NO | J5: =IF(I5="YES",IF(H5<18,0,1),0) -> 0 | K5: =IF(I5="YES",IF(H5<13,0,1),0) -> 0
A6: Sum Insured | B6: 6 CR | G6: CHILD | H6: 23 | I6: NO | J6: =IF(I6="YES",IF(H6<18,0,1),0) -> 0 | K6: =IF(I6="YES",IF(H6<13,0,1),0) -> 0
A7: PRODUCT | B7: CARE | G7: CHILD | H7: 20 | I7: NO | J7: =IF(I7="YES",IF(H7<18,0,1),0) -> 0 | K7: =IF(I7="YES",IF(H7<13,0,1),0) -> 0
A8: ZONE | B8: ZONE 3 | G8: CHILD | H8: 17 | I8: NO | J8: =IF(I8="YES",IF(H8<18,0,1),0) -> 0 | K8: =IF(I8="YES",IF(H8<13,0,1),0) -> 0
A9: Base Premium | D9: ='CARE SHEET'!R11 -> 186859.54
A10: HEALTH SCORE | B10: 0 | J10: =SUM(J3:J8) -> 1 | K10: =SUM(K3:K8) -> 1
A12: Ncb-super | B12: NO
A13: Smart select | B13: NO
A14: Reduction in PED | B14: NO
A15: Room Rent modification | B15: NO
A16: Unlimited recharge | B16: NO
A17: CO-PAYMENT | B17: YES
A18: Everyday care | B18: YES
A19: Care Shield | B19: YES
A20: OPD Care | B20: YES | C20: 10000
A21: Air Ambulance | B21: NO
A22: BE-FIT | B22: NO
A23: INTERNATIONAL SECOND OPINION | B23: NO
A24: Daily Allowance+ | B24: NO | C24: 1000
A25: Advance Annual Health Check up | B25: NO | C25: Option 1
A26: Personal Accident | B26: NO | C26: 300
A27: DEDUCTIBLE | B27: NO | C27: 5000
A28: GLOBAL COVERAGE TOTAL | B28: NO
A29: EXT OF GLOBAL COVERAGE | B29: NO | C29: INCL US
A30: TRAVEL PLUS | B30: NO
A31: ADD SI
P32: 189048.93 | R32: 526096.76
A33: Final premium excluding taxes( tenure 1 year) | C33: =D33 -> 196386.14 | D33: ='CARE SHEET'!R31 -> 196386.14 | E33: ='CARE SHEET'!R72 -> 196386.14 | F33: ='CARE SHEET'!S72 -> 196386.14 | P33: 117483.66 | R33: 480986.34
A34: Final premium including GST@18% ( tenure 1 year) | C34: =D34 -> 231735.65 | D34: =D33*1.18 -> 231735.65 | P34: =P32+P33*95% -> 300658.41 | R34: 205133.86
A35: Final premium excluding taxes ( tenure 2 year) | C35: =D35 -> 378043.32 | D35: =D33+E33*92.5% -> 378043.32 | R35: 77439.284
A36: Final premium including GST@18% ( tenure 2 year) | C36: =D36 -> 446091.12 | D36: =D35*1.18 -> 446091.12 | R36: 65589.533
A37: Final premium excluding taxes (tenure 3 year) | C37: =D37 -> 554790.85 | D37: =D33+E33*92.5%+F33*90% -> 554790.85 | R37: 59858.287
A38: Final premium including GST@18% (tenure 3 year) | C38: =D38 -> 654653.21 | D38: =D37*1.18 -> 654653.21 | R38: =SUM(R33:R37) -> 889007.3
R39: =R32+R38*90% -> 1326203.3
D41: 111716.56 | E41: 111716.56 | F41: 41650.297 | G41: 33501.971 | H41: =D41+E41*90%+F41*90%+G41*90% -> 279898.51
D42: 131825.54 | E42: 131825.54 | F42: 49147.35 | G42: 39532.326 | H42: =D42+E42*90%+F42*90%+G42*90% -> 330280.24
D43: 215054.38 | E43: 215054.38 | F43: 91323.242 | G43: 64491.294 | H43: =D43+E43*90%+F43*90%+G43*90% -> 548836.4
D44: 253764.17 | E44: 253764.17 | F44: 107761.43 | G44: 76099.727 | H44: =D44+E44*90%+F44*90%+G44*90% -> 647626.96
D45: 315599.28 | E45: 315599.28 | F45: 139653.68 | G45: 94643.068 | H45: =D45+E45*90%+F45*90%+G45*90% -> 810505.71
D46: 372407.16 | E46: 372407.16 | F46: 164791.34 | G46: 111678.82 | H46: =D46+E46*90%+F46*90%+G46*90% -> 956396.74

Sheet optional benefits
A1: OPTIONAL BENEFITS
A3: No Claims Bonus Super - Optional Cover
B4: Percentage of the gross premium to be charged to the customers:
B5: Plan/Age Band | C5: Care 2 | D5: Care 3/Care 8 | F5: Care 4/Care 9 | I5: Care 5 | N5: Care 6
C6: 3L | D6: 4L | E6: 5L | F6: 7L | G6: 10L | H6: 15L | I6: 20L | J6: 25L | K6: 30L | L6: 40L | M6: 50L | N6: 60L | O6: 75L
B7: Less than or equal to 45 years | C7: 0.2 | D7: 0.2 | E7: 0.1 | F7: 0.1 | G7: 0.1 | H7: 0.1 | I7: 0.1 | J7: 0.1 | K7: 0.1 | L7: 0.1 | M7: 0.075 | N7: 0.075 | O7: 0.075
B8: Greater than 45 years | C8: 0.3 | D8: 0.3 | E8: 0.2 | F8: 0.2 | G8: 0.2 | H8: 0.2 | I8: 0.2 | J8: 0.2 | K8: 0.2 | L8: 0.2 | M8: 0.15 | N8: 0.15 | O8: 0.15
A10: Unlimited Automatic Recharge - Optional Cover
B11: Percentage of the gross premium to be charged to the customers:
B12: Plan/Age Band | C12: Care 2 | D12: Care 3/Care 8 | F12: Care 4/Care 9 | I12: Care 5 | N12: Care 6
C13: 3L | D13: 4L | E13: 5L | F13: 7L | G13: 10L | H13: 15L | I13: 20L | J13: 25L | K13: 30L | L13: 40L | M13: 50L | N13: 60L | O13: 75L | P13: 75 Lacs
B14: Less than or equal to 45 years | C14: 0.175 | D14: 0.175 | E14: 0.075 | F14: 0.075 | G14: 0.075 | H14: 0.075 | I14: 0.075 | J14: 0.075 | K14: 0.075 | L14: 0.075 | M14: 0.05 | N14: 0.05 | O14: 0.05
B15: Greater than 45 years | C15: 0.25 | D15: 0.25 | E15: 0.15 | F15: 0.15 | G15: 0.15 | H15: 0.15 | I15: 0.15 | J15: 0.15 | K15: 0.15 | L15: 0.15 | M15: 0.1 | N15: 0.1 | O15: 0.1
A18: EVERYDAY CARE - Optional Cover
B19: Care 2 | C19: Care 3/Care 8 | E19: Care 4/Care 9 | H19: Care 5 | M19: Care 6 | P19: Care 7
A20: Flaoter Combination | B20: 2 Lacs | C20: 3L | D20: 4L | E20: 5L | F20: 7L | G20: 10L | H20: 15L | I20: 20L | J20: 25L | K20: 30L | L20: 40L | M20: 50L | N20: 60L | O20: 75L | P20: 1 CR | Q20: 1.5 CR | R20: 2 CR | S20: 3 CR | T20: 6 CR
A21: 1+0 | B21: 1562.8565 | C21: 2259.5484 | D21: 2956.2402 | E21: 3652.9321 | F21: 5046.3158 | G21: 6110.8165 | H21: 7175.3172 | I21: 8509.9151 | J21: 9844.513 | K21: 11179.111 | L21: 12885.49 | M21: 14591.868 | N21: 16568.344 | O21: 18544.82 | P21: 20893.077 | Q21: 23241.334 | R21: 26129.785 | S21: 29018.236 | T21: 31906.687
A22: 1+1 | B22: 1795.0871 | C22: 2607.8943 | D22: 3420.7015 | E22: 4233.5087 | F22: 5859.123 | G22: 7101.0405 | H22: 8342.958 | I22: 9899.9888 | J22: 11457.02 | K22: 13014.051 | L22: 15004.826 | M22: 16995.601 | N22: 19301.489 | O22: 21607.378 | P22: 24347.011 | Q22: 27086.644 | R22: 30456.503 | S22: 33826.363 | T22: 37196.223
A23: 1+2 | B23: 2015.7062 | C23: 2938.8229 | D23: 3861.9397 | E23: 4785.0564 | F23: 6631.2898 | G23: 8041.7533 | H23: 9452.2167 | I23: 11220.559 | J23: 12988.901 | K23: 14757.243 | L23: 17018.195 | M23: 19279.147 | N23: 21897.977 | O23: 24516.808 | P23: 27628.248 | Q23: 30739.688 | R23: 34566.886 | S23: 38394.084 | T23: 42221.282
A24: 1+3 | B24: 2224.7138 | C24: 3252.3343 | D24: 4279.9548 | E24: 5307.5753 | F24: 7362.8163 | G24: 8932.9548 | H24: 10503.093 | I24: 12471.625 | J24: 14440.157 | K24: 16408.689 | L24: 18925.598 | M24: 21442.506 | N24: 24357.808 | O24: 27273.11 | P24: 30736.789 | Q24: 34200.468 | R24: 38460.933 | S24: 42721.398 | T24: 46981.864
A25: 1+4 | B25: 2422.1098 | C25: 3548.4283 | D25: 4674.7468 | E25: 5801.0654 | F25: 8053.7024 | G25: 9774.6452 | H25: 11495.588 | I25: 13653.188 | J25: 15810.788 | K25: 17968.388 | L25: 20727.033 | M25: 23485.679 | N25: 26680.982 | O25: 29876.284 | P25: 33672.633 | Q25: 37468.981 | R25: 42138.644 | S25: 46808.307 | T25: 51477.969
A26: 2+0 | B26: 2073.7639 | C26: 3025.9094 | D26: 3978.055 | E26: 4930.2005 | F26: 6834.4916 | G26: 8289.3093 | H26: 9744.1269 | I26: 11568.077 | J26: 13392.028 | K26: 15215.978 | L26: 17548.029 | M26: 19880.08 | N26: 22581.264 | O26: 25282.448 | P26: 28491.732 | Q26: 31701.016 | R26: 35648.566 | S26: 39596.116 | T26: 43543.666
A27: 2+1 | B27: 2282.7714 | C27: 3339.4208 | D27: 4396.0701 | E27: 5452.7194 | F27: 7566.0181 | G27: 9180.5108 | H27: 10795.004 | I27: 12819.144 | J27: 14843.284 | K27: 16867.424 | L27: 19455.432 | M27: 22043.439 | N27: 25041.094 | O27: 28038.75 | P27: 31600.272 | Q27: 35161.795 | R27: 39542.613 | S27: 43923.43 | T27: 48304.248
A28: 2+2 | B28: 2480.1675 | C28: 3635.5148 | D28: 4790.8622 | E28: 5946.2095 | F28: 8256.9042 | G28: 10022.201 | H28: 11787.498 | I28: 14000.706 | J28: 16213.914 | K28: 18427.123 | L28: 21256.867 | M28: 24086.612 | N28: 27364.268 | O28: 30641.924 | P28: 34536.116 | Q28: 38430.309 | R28: 43220.324 | S28: 48010.338 | T28: 52800.353
A29: 2+3 | B29: 2665.952 | C29: 3914.1916 | D29: 5162.4312 | E29: 6410.6708 | F29: 8907.15 | G29: 10814.38 | H29: 12721.611 | I29: 15112.765 | J29: 17503.92 | K29: 19895.074 | L29: 22952.336 | M29: 26009.598 | N29: 29550.784 | O29: 33091.97 | P29: 37299.263 | Q29: 41506.557 | R29: 46681.698 | S29: 51856.84 | T29: 57031.982
A30: 2+4 | B30: 2840.1249 | C30: 4175.451 | D30: 5510.7771 | E30: 6846.1032 | F30: 9516.7553 | G30: 11557.048 | H30: 13597.341 | I30: 16155.321 | J30: 18713.3 | K30: 21271.279 | L30: 24541.838 | M30: 27812.398 | N30: 31600.643 | O30: 35388.889 | P30: 39889.714 | Q30: 44390.539 | R30: 49926.737 | S30: 55462.935 | T30: 60999.133
A32: OPD Care
B34: AGE BAND/SI | C34: 5000 | D34: 10000 | E34: 15000 | F34: 20000 | G34: 25000 | H34: 30000 | I34: 35000 | J34: 40000 | K34: 45000 | L34: 50000
B35: 1+1 | C35: 1283.7862 | D35: 3170.9519 | E35: 5215.3815 | F35: 6884.3035 | G35: 8711.7732 | H35: 12091.34 | I35: 15546.009 | J35: 18169.398 | K35: 21109.1 | L35: 23513.339
B36: 1+2 | C36: 1619.1898 | D36: 3999.3988 | E36: 6577.9586 | F36: 8682.9054 | G36: 10987.822 | H36: 15250.339 | I36: 19607.579 | J36: 22916.358 | K36: 26624.09 | L36: 29656.463
B37: 1+3 | C37: 1908.3309 | D37: 4713.5772 | E37: 7752.5941 | F37: 10233.424 | G37: 12949.933 | H37: 17973.614 | I37: 23108.932 | J37: 27008.565 | K37: 31378.392 | L37: 34952.26
B38: 1+4 | C38: 2012.4216 | D38: 4970.6814 | E38: 8175.4629 | F38: 10791.611 | G38: 13656.293 | H38: 18953.993 | I38: 24369.42 | J38: 28481.759 | K38: 33089.94 | L38: 36858.747
B39: 2+0 | C39: 1665.4524 | D39: 4113.6674 | E39: 6765.9003 | F39: 8930.9884 | G39: 11301.76 | H39: 15686.063 | I39: 20167.796 | J39: 23571.111 | K39: 27384.778 | L39: 30503.791
B40: 2+1 | C40: 1966.1591 | D40: 4856.4129 | E40: 7987.5212 | F40: 10543.528 | G40: 13342.355 | H40: 18518.269 | I40: 23809.203 | J40: 27827.006 | K40: 32329.252 | L40: 36011.42
B41: 2+2 | C41: 2081.8155 | D41: 5142.0842 | E41: 8457.3754 | F41: 11163.735 | G41: 14127.2 | H41: 19607.579 | I41: 25209.744 | J41: 29463.889 | K41: 34230.973 | L41: 38129.739
B42: 2+3 | C42: 2266.8657 | D42: 5599.1584 | E42: 9024.9592 | F42: 11912.946 | G42: 15075.292 | H42: 20923.465 | I42: 26901.598 | J42: 31441.243 | K42: 36528.251 | L42: 40688.668
B43: 2+4 | C43: 2220.6032 | D43: 5484.8898 | E43: 9021.2004 | F43: 11907.985 | G43: 15069.013 | H43: 20914.751 | I43: 26890.394 | J43: 31428.148 | K43: 36513.038 | L43: 40671.721
B44: 1+0 | C44: 925.25132 | D44: 2285.3708 | E44: 3758.8335 | F44: 4961.6602 | G44: 6278.7555 | H44: 8714.4796 | I44: 11204.331 | J44: 13095.062 | K44: 15213.766 | L44: 16946.55
A45: Note: Sum Insured mentioned is the OPD Care Sum Insured are over and above the Base Sum Insured
A48: Reduction in PED Wait Period - Optional Cover
A49: Following percentage of premium will be charged for reducing PED wait period to 2 years:
B50: Age band/Plan name | C50: % of base policy premium
B51: Upto 45 Years | C51: 0.15
B52: 46 to 60 Years | C52: 0.25
B53: 61 to 70 Years | C53: 0.3
B54: Above 70 Years | C54: 0.4
A57: AIR AMBULANCE-OPTIONAL COVER
B58: Age Band | C58: Gross Premium
B59: All age bands | C59: 635.5228
A61: CARE SHIELD-OPTIONAL COVER
A62: Base Plan Sum Insured | B62: Care Shield Premium*
A63: Up to 5 Lakhs | B63: 0.065
A64: Greater than 5 Lakhs | B64: 0.05
A67: *This premium(%) will be applicable on base premium and any Cumulative Bonus premium (if available as Optional Cover/Benefit)
A69: Copayment
A71: If age of Insured Person or eldest Insured Person (in case of Floater) is 61 years or more, then the Insured Person / Policyholder may choose for co-payment of 20% per claim and a corresponding 20% discount will be applicable
A73: 0.2
A74: Smart Select - Optional Cover
A75: Discount of 15% on the Individual/flaoter policy's gross premium if opted.
A79: Be-Fit Benefit
B81: Premium | C81: 254.58361
A82: Note: Premium is per insured
A84: Room Rent Modification
C86: Loading
B87: SI Less than 5L | C87: 0.25
B88: SI Greater & Equal to 5L | C88: 0.125
A90: Advance Annual Health Check up
C92: Premium
B93: Option 1 | C93: 268.53197
B94: Option 2 | C94: 537.06395
A95: Note: Premium is per insured
A97: Global coverage total
A99: % of Base Premium | B99: 1 CR | C99: 1.5 CR | D99: 2 CR | E99: 3 CR | F99: 6 CR
B100: 0.2 | C100: 0.25 | D100: 0.275 | E100: 0.3 | F100: 0.4
A103: Extension of Global coverage
A104: Global Extension (excl US) | C104: 5% of Base Premium
C105: S%
A108: Global Extension (incl US)
A110: % of Base Premium | B110: 1 CR | C110: 1.5 CR | D110: 2 CR | E110: 3 CR | F110: 6 CR
B111: 0.06 | C111: 0.06 | D111: 0.075 | E111: 0.075 | F111: 0.1
A112: Daily Allowance+ | M112: Zone 3
A113: Individual | B113: zone 1 | E113: zone 1a | I113: zone 2 | M113: Individual
A114: Age band/Plan Name | B114: Premium Rate (per 1000 Rupees Sum Insured) | E114: Age band/Plan Name | F114: Premium Rate (per 1000 Rupees Sum Insured) | I114: Age band/Plan Name | J114: Premium Rate (per 1000 Rupees Sum Insured) | M114: Age band/Plan Name | N114: Premium Rate (per 1000 Rupees Sum Insured)
A115: Upto 45 years | B115: 413.08982 | E115: Upto 45 years | F115: 378.66567 | I115: Upto 45 years | J115: 361.45359 | M115: Upto 45 years | N115: 344.24152
A116: 46 to 60 Years | B116: 660.94371 | E116: 46 to 60 Years | F116: 605.86507 | I116: 46 to 60 Years | J116: 578.32575 | M116: 46 to 60 Years | N116: 550.78643
A117: 61 to 75 Years | B117: 1436.2815 | E117: 61 to 75 Years | F117: 1316.5914 | I117: 61 to 75 Years | J117: 1256.7463 | M117: 61 to 75 Years | N117: 1196.9013
A118: Above 75 Years | B118: 3203.0349 | E118: Above 75 Years | F118: 2936.1153 | I118: Above 75 Years | J118: 2802.6556 | M118: Above 75 Years | N118: 2669.1958
A120: A discount of 5% applies to each additional member added for floater policies.
A122: Personal accident
A123: All Age Bands | B123: 70.748403 | C123: Per Lac
A125: International Second Opinion - Optional Cover
B126: Gross Rate per policy: | C126: 1051.1191
A129: Deductible Option - Optional Cover
B130: Discount on the Gross Premium is applicable for the deductible option chosen by the customers:
B131: Plan & Sum Insured/Dedcutible Amount: | C131: Care 1 | D131: Care 2 | E131: Care 3/Care 8 | G131: Care 4/Care 9 | J131: Care 5 | O131: Care 6 | R131: Care 7
C132: 1 Lac | D132: 2 Lacs | E132: 3L | F132: 4L | G132: 5L | H132: 7L | I132: 10L | J132: 15L | K132: 20L | L132: 25L | M132: 30L | N132: 40L | O132: 50L | P132: 60L | Q132: 75L | R132: 1 CR | S132: 1.5 CR | T132: 2 CR | U132: 3 CR | V132: 6 CR
B133: 5000 | C133: 0.185 | D133: 0.155 | E133: 0.13 | F133: 0.1075 | G133: 0.09 | H133: 0.0725 | I133: 0.055 | J133: 0.04 | K133: 0.035 | L133: 0.03 | M133: 0.025 | N133: 0.0225 | O133: 0.02 | P133: 0.0175 | Q133: 0.015 | R133: 0.0125 | S133: 0.01 | T133: 0.0075 | U133: 0.005 | V133: 0.0025
B134: 10000 | C134: 0.275 | D134: 0.23 | E134: 0.1925 | F134: 0.16 | G134: 0.1325 | H134: 0.105 | I134: 0.08 | J134: 0.0575 | K134: 0.0525 | L134: 0.0475 | M134: 0.0425 | N134: 0.04 | O134: 0.0375 | P134: 0.035 | Q134: 0.0325 | R134: 0.03 | S134: 0.0275 | T134: 0.025 | U134: 0.0225 | V134: 0.02
B135: 25000 | C135: 0.365 | D135: 0.305 | E135: 0.255 | F135: 0.2125 | G135: 0.175 | H135: 0.14 | I135: 0.1075 | J135: 0.0775 | K135: 0.0725 | L135: 0.0675 | M135: 0.0625 | N135: 0.06 | O135: 0.0575 | P135: 0.055 | Q135: 0.0525 | R135: 0.05 | S135: 0.0475 | T135: 0.045 | U135: 0.0425 | V135: 0.04
B136: 50000 | C136: 0.45 | D136: 0.375 | E136: 0.3125 | F136: 0.26 | G136: 0.215 | H136: 0.1725 | I136: 0.1325 | J136: 0.095 | K136: 0.09 | L136: 0.085 | M136: 0.08 | N136: 0.0775 | O136: 0.075 | P136: 0.0725 | Q136: 0.07 | R136: 0.0675 | S136: 0.065 | T136: 0.0625 | U136: 0.06 | V136: 0.0575
...

Sheet CARE SENIOR
B1: ZONE 1 | K1: Zone 1a | V1: Zone 2 | AF1: Zone 3
A2: 1A | C2: Care 8 | E2: Care 9 | K2: 1A | M2: Care 8 | O2: Care 9 | U2: 1A | W2: Care 8 | Y2: Care 9 | AE2: 1A | AG2: Care 8 | AI2: Care 9
B3: Age-Band/ SI | C3: 300000 | D3: 400000 | E3: 500000 | F3: 700000 | G3: 1000000 | L3: Age-Band/ SI | M3: 300000 | N3: 400000 | O3: 500000 | P3: 700000 | Q3: 1000000 | V3: Age-Band/ SI | W3: 300000 | X3: 400000 | Y3: 500000 | Z3: 700000 | AA3: 1000000 | AF3: Age-Band/ SI | AG3: 300000 | AH3: 400000 | AI3: 500000 | AJ3: 700000 | AK3: 1000000
B4: 00-04 | C4: 5176.15 | D4: 6233 | E4: 6858.6 | F4: 7672.8 | G4: 8566.35 | H4: ARRAY | L4: 00-04 | M4: 4595.625 | N4: 5532.75 | O4: 6085.125 | P4: 6806.25 | Q4: 7599.375 | R4: ARRAY | V4: 00-04 | W4: 4241.6 | X4: 5105.1 | Y4: 5614.4 | Z4: 6278.8 | AA4: 7009.2 | AB4: ARRAY | AF4: 00-04 | AG4: 3907.65 | AH4: 4701.17 | AI4: 5168.78 | AJ4: 5780.27 | AK4: 6451.71 | AL4: ARRAY
B5: 05-17 | C5: 3890.45 | D5: 4698.9 | E5: 5258.95 | F5: 5886.85 | G5: 6578 | H5: 1+0 | I5: B3:G16 | L5: 05-17 | M5: 3458.25 | N5: 4173.75 | O5: 4668.75 | P5: 5225.625 | Q5: 5837.625 | R5: 1+0 | S5: L3:Q16 | V5: 05-17 | W5: 3193.3 | X5: 3852.2 | Y5: 4308.7 | Z5: 4821.3 | AA5: 5385.6 | AB5: 1+0 | AC5: V3:AA16 | AF5: 05-17 | AG5: 2943 | AH5: 3549.04 | AI5: 3968.69 | AJ5: 4439.57 | AK5: 4959.5 | AL5: 1+0 | AM5: AF3:AK16 | AQ5: =VLOOKUP('CALCULATOR CARE V6'!B2,DROPDOWN!K:L,2,0) -> 18-24 | AR5: =VLOOKUP('CALCULATOR CARE V6'!E2,DROPDOWN!K:L,2,0) -> 18-24 | AS5: =VLOOKUP('CALCULATOR CARE V6'!F2,DROPDOWN!K:L,2,0) -> 18-24
B6: 18-24 | C6: 9847.45 | D6: 12232.55 | E6: 14089.8 | F6: 15771.1 | G6: 17620.3 | H6: 1+1 | I6: B20:G31 | L6: 18-24 | M6: 8736.75 | N6: 10849.5 | O6: 12506.625 | P6: 13996.125 | Q6: 15635.25 | R6: 1+1 | S6: L20:Q31 | V6: 18-24 | W6: 8060.8 | X6: 10006.7 | Y6: 11540.1 | Z6: 12914 | AA6: 14424.3 | AB6: 1+1 | AC6: V20:AA31 | AF6: 18-24 | AG6: 7420.72 | AH6: 9211.59 | AI6: 10627.5 | AJ6: 11890.81 | AK6: 13280.56 | AL6: 1+1 | AM6: AF20:AK31 | AP6: COMBINATIO | AQ6: ='CALCULATOR CARE V6'!B3&"+"&'CALCULATOR CARE V6'!B4 -> 1+0
B7: 25-35 | C7: 11642.6 | D7: 14025.4 | E7: 15936.7 | F7: 18035.45 | G7: 20148 | H7: 1+2 | I7: B35:G46 | L7: 25-35 | M7: 10334.25 | N7: 12444.75 | O7: 14152.5 | P7: 16013.25 | Q7: 17885.25 | R7: 1+2 | S7: L35:Q46 | V7: 25-35 | W7: 9535.9 | X7: 11481.8 | Y7: 13063.6 | Z7: 14778.5 | AA7: 16505.5 | AB7: 1+2 | AC7: V35:AA46 | AF7: 25-35 | AG7: 8782.13 | AH7: 10570.82 | AI7: 12033.6 | AJ7: 13611.92 | AK7: 15200.05 | AL7: 1+2 | AM7: AF35:AK46 | AP7: ROW NO | AQ7: =IF(AQ6="1+0",AR7,AS7) -> 4 | AR7: =VLOOKUP(AQ5,DROPDOWN!O15:Q27,2,0) -> 4 | AS7: =VLOOKUP(AQ5,DROPDOWN!O15:Q27,3,0) -> 2 | AT7: =VLOOKUP(AR5,DROPDOWN!O15:Q27,2,0) -> 4 | AU7: =VLOOKUP(AR5,DROPDOWN!O15:Q27,3,0) -> 2 | AV7: =VLOOKUP(AS5,DROPDOWN!O15:Q27,2,0) -> 4 | AW7: =VLOOKUP(AS5,DROPDOWN!O15:Q27,3,0) -> 2
B8: 36-40 | C8: 13294 | D8: 16049.4 | E8: 18259.7 | F8: 20704.6 | G8: 23169.05 | H8: 1+3 | I8: B50:G61 | L8: 36-40 | M8: 11796.75 | N8: 14236.875 | O8: 16209 | P8: 18375.75 | Q8: 20560.5 | R8: 1+3 | S8: L50:Q61 | V8: 36-40 | W8: 10884.5 | X8: 13131.8 | Y8: 14958.9 | Z8: 16956.5 | AA8: 18969.5 | AB8: 1+3 | AC8: V50:AA61 | AF8: 36-40 | AG8: 10021.46 | AH8: 12088.1 | AI8: 13776.51 | AJ8: 15614.25 | AK8: 17466.16 | AL8: 1+3 | AM8: AF50:AK61 | AP8: COLUMN NO | AQ8: =VLOOKUP('CALCULATOR CARE V6'!B6,DROPDOWN!A:C,3,0) -> 19
B9: 41-45 | C9: 15220.25 | D9: 18404.6 | E9: 20886.3 | F9: 23750.95 | G9: 26642.05 | H9: 1+4 | I9: B65:G76 | L9: 41-45 | M9: 13502.25 | N9: 16322.625 | O9: 18535.5 | P9: 21073.5 | Q9: 23635.125 | R9: 1+4 | S9: L65:Q76 | V9: 41-45 | W9: 12455.3 | X9: 15053.5 | Y9: 17101.7 | Z9: 19441.4 | AA9: 21803.1 | AB9: 1+4 | AC9: V65:AA76 | AF9: 41-45 | AG9: 11465.71 | AH9: 13854.99 | AI9: 15747.23 | AJ9: 17898.89 | AK9: 20071.26 | AL9: 1+4 | AM9: AF65:AK76 | AP9: APPLICABLE ARRAY | AQ9: =HLOOKUP(AR10,AS9:AV10,2,0) -> AF3:AK16 | AS9: ZONE 1 | AT9: ZONE 1A | AU9: ZONE 2 | AV9: ZONE 3
B10: 46-50 | C10: 18441.4 | D10: 22321.5 | E10: 25431.1 | F10: 29027.15 | G10: 32546.15 | H10: 2+0 | I10: B81:G92 | L10: 46-50 | M10: 16360.875 | N10: 19797.75 | O10: 22569.75 | P10: 25756.875 | Q10: 28875.375 | R10: 2+0 | S10: L81:Q92 | V10: 46-50 | W10: 15093.1 | X10: 18260 | Y10: 20825.2 | Z10: 23763.3 | AA10: 26637.6 | AB10: 2+0 | AC10: V81:AA92 | AF10: 46-50 | AG10: 13895.32 | AH10: 16806.71 | AI10: 19176.37 | AJ10: 21878.48 | AK10: 24522.82 | AL10: 2+0 | AM10: AF81:AK92 | AP10: ZONE | AR10: ='CALCULATOR CARE V6'!B8 -> ZONE 3 | AS10: =VLOOKUP(AQ6,H5:I15,2,0) -> B3:G16 | AT10: =VLOOKUP(AQ6,R5:S15,2,0) -> L3:Q16 | AU10: =VLOOKUP(AQ6,AB5:AC14,2,0) -> V3:AA16 | AV10: =VLOOKUP(AQ6,AL5:AM14,2,0) -> AF3:AK16
B11: 51-55 | C11: 23887.8 | D11: 28976.55 | E11: 32972.8 | F11: 37720 | G11: 42385.55 | H11: 2+1 | I11: B98:G109 | L11: 51-55 | M11: 21183.75 | N11: 25689.375 | O11: 29247.75 | P11: 33454.125 | Q11: 37588.5 | R11: 2+1 | S11: L98:Q109 | V11: 51-55 | W11: 19537.1 | X11: 23689.6 | Y11: 26978.6 | Z11: 30856.1 | AA11: 34666.5 | AB11: 2+1 | AC11: V98:AA109 | AF11: 51-55 | AG11: 17980.64 | AH11: 21798.91 | AI11: 24834.56 | AJ11: 28399.95 | AK11: 31905.39 | AL11: 2+1 | AM11: AF98:AK109
B12: 56-60 | C12: 31886.05 | D12: 38734.3 | E12: 44176.1 | F12: 50629.9 | G12: 57021.6 | H12: 2+2 | I12: B113:G124 | L12: 56-60 | M12: 28275.75 | N12: 34339.5 | O12: 39184.875 | P12: 44903.25 | Q12: 50565.375 | R12: 2+2 | S12: L113:Q124 | V12: 56-60 | W12: 26077.7 | X12: 31665.7 | Y12: 36143.8 | Z12: 41415 | AA12: 46634.5 | AB12: 2+2 | AC12: V113:AA124 | AF12: 56-60 | AG12: 24000.71 | AH12: 29138.97 | AI12: 33270.07 | AJ12: 38118.39 | AK12: 42919.84 | AL12: 2+2 | AM12: AF113:AK124 | AP12: CARE SENIOR | AQ12: =INDEX(INDIRECT(AQ9),AQ7,AQ8) -> #REF! | AR12: =INDEX(INDIRECT(AQ9),AQ15,AQ8) -> #REF! | AS12: =INDEX(INDIRECT(AQ9),AQ16,AQ8) -> #REF!
B13: 61-65 | C13: 41258.55 | D13: 50215.9 | E13: 57192.95 | F13: 65719.05 | G13: 75958.65 | H13: 2+3 | I13: B128:G139 | L13: 61-65 | M13: 36573.75 | N13: 44505 | O13: 50707.125 | P13: 58260.375 | Q13: 67332.375 | R13: 2+3 | S13: L128:Q139 | V13: 61-65 | W13: 33722.7 | X13: 41032.2 | Y13: 46759.9 | Z13: 53721.8 | AA13: 62084 | AB13: 2+3 | AC13: V128:AA139 | AF13: 61-65 | AG13: 31029.03 | AH13: 37749.97 | AI13: 43029.93 | AJ13: 49432.59 | AK13: 57124.72 | AL13: 2+3 | AM13: AF128:AK139
B14: 66-70 | C14: 54069.55 | D14: 65947.9 | E14: 75433.1 | F14: 86828.45 | G14: 98281.3 | H14: 2+4 | I14: B143:G154 | L14: 66-70 | M14: 47921.625 | N14: 58439.25 | O14: 66864.375 | P14: 76957.875 | Q14: 87103.125 | R14: 2+4 | S14: L143:Q154 | V14: 66-70 | W14: 44181.5 | X14: 53874.7 | Y14: 61650.6 | Z14: 70954.4 | AA14: 80304.4 | AB14: 2+4 | AC14: V143:AA154 | AF14: 66-70 | AG14: 40648.28 | AH14: 49560.12 | AI14: 56724.69 | AJ14: 65281.19 | AK14: 73880.2 | AL14: 2+4 | AM14: AF143:AK154
B15: 71-75 | C15: 63981.4 | D15: 78166.65 | E15: 89388.35 | F15: 103049.2 | G15: 116834.25 | L15: 71-75 | M15: 56697.75 | N15: 69259.5 | O15: 79221.375 | P15: 91321.875 | Q15: 103531.5 | V15: 71-75 | W15: 52269.8 | X15: 63845.1 | Y15: 73038.9 | Z15: 84190.7 | AA15: 95443.7 | AF15: 71-75 | AG15: 48085.35 | AH15: 58728.11 | AI15: 67195.23 | AJ15: 77451.04 | AK15: 87800.59 | AQ15: =IF(AQ6="1+0",AT7,AU7) -> 4
B16: 75+ | C16: 83595.8 | D16: 102295.95 | E16: 118655.85 | F16: 136998.35 | G16: 157395.9 | L16: 75+ | M16: 74066.625 | N16: 90625.5 | O16: 105138 | P16: 121384.12 | Q16: 139449.38 | V16: 75+ | W16: 68274.8 | X16: 83534 | Y16: 96919.9 | Z16: 111893.1 | AA16: 128542.7 | AF16: 75+ | AG16: 62801.44 | AH16: 76833.01 | AI16: 89154.37 | AJ16: 102924.34 | AK16: 118236.66 | AQ16: =IF(AQ6="1+0",AV7,AW7) -> 4
